Workbook
Name Teams: #REF!
Name Teams: 'PI Commitments'!$AH$3:$AH$93

Sheet Sheet1
A1: Match | B1: ID | C1: Title | D1: Work Item Type | E1: Assigned To | F1: Time Criticality | G1: Priority | H1: Effort | I1: Target Date | J1: State | K1: Tags | L1: Area Path
A2: =VLOOKUP(B2,'PI Commitments'!#REF!,1,FALSE) -> #REF! | B2: 165196 | C2: Generation of manual JSON files for Langhorne | D2: Feature | E2: Polannagari, Govardhan | F2: 0.5 | G2: 2 | H2: 2 | I2: 43686 | J2: Closed | K2: Langhorne | L2: GlobalREApps\Debt
A3: =VLOOKUP(B3,'PI Commitments'!#REF!,1,FALSE) -> #REF! | B3: 65960 | C3: EMEA data for Dublin Bank | D3: Feature | E3: Cole, Lisa | F3: 8 | G3: 1 | H3: 1 | I3: 43694 | J3: Closed | K3: _Ready; CLS; OneSource | L3: GlobalREApps\Debt\LMW
A4: =VLOOKUP(B4,'PI Commitments'!#REF!,1,FALSE) -> #REF! | B4: 127851 | C4: Real-time data processing new loans | D4: Feature | E4: Talluru, Praveena | F4: 4 | G4: 1 | H4: 2 | I4: 43694 | J4: Closed | K4: _Ready; CLS | L4: GlobalREApps\Debt\LMW
A5: =VLOOKUP(B5,'PI Commitments'!#REF!,1,FALSE) -> #REF! | B5: 49326 | C5: Final Concluded Property Value/LTV in Feed From Backshop to LMW | D5: Feature | E5: Mitchell, Aj | F5: 3 | G5: 1 | H5: 3 | I5: 43694 | J5: Closed | K5: _Ready; LMW | L5: GlobalREApps\Debt\LMW
A6: =VLOOKUP(B6,'PI Commitments'!#REF!,1,FALSE) -> #REF! | B6: 133868 | C6: CLS Implementation for CECL Enhancements | D6: Feature | E6: Montoya, Fabio | F6: 1.75 | G6: 1 | H6: 4 | I6: 43694 | J6: Closed | K6: _Ready; CECL; CLS | L6: GlobalREApps\Debt\CLS
A7: =VLOOKUP(B7,'PI Commitments'!#REF!,1,FALSE) -> #REF! | B7: 133865 | C7: Backshop Implementation for CECL Enhancements | D7: Feature | E7: Montoya, Fabio | F7: 1.667 | G7: 1 | H7: 1 | I7: 43694 | J7: Closed | K7: _Ready; Backshop; Backshop_Met; CECL | L7: GlobalREApps\Debt\CLS
A8: =VLOOKUP(B8,'PI Commitments'!#REF!,1,FALSE) -> #REF! | B8: 119226 | C8: Client Reporting : Beneficial Borrower Report feed to SSB for CMIF loans | D8: Feature | E8: Bose, Siddhartha | F8: 1.2 | G8: 1 | H8: 5 | I8: 43694 | J8: Closed | K8: _Ready; MIS | L8: GlobalREApps\Debt\MIS
A9: =VLOOKUP(B9,'PI Commitments'!#REF!,1,FALSE) -> #REF! | B9: 49574 | C9: Automatically generate and attach the FTM Compare Report to the the "FTM Review Approved" notification | D9: Feature | E9: Mitchell, Aj | F9: 1 | G9: 1 | H9: 6 | I9: 43694 | J9: Closed | K9: _Ready; Backshop | L9: GlobalREApps\Debt
A10: =VLOOKUP(B10,'PI Commitments'!#REF!,1,FALSE) -> #REF! | B10: 156184 | C10: Script Request - Loan 702826 Rating and Valuation Review - Loan Commentary | D10: Feature | E10: Ramaraj, Vinoth | F10: 8 | G10: 2 | H10: 1 | I10: 43694 | J10: Closed | K10: _Ready; LMW | L10: GlobalREApps\Debt
A11: =VLOOKUP(B11,'PI Commitments'!#REF!,1,FALSE) -> #REF! | B11: 156201 | C11: Data Script request to update mortgage rating grade for loan 540151 | D11: Feature | E11: Ramaraj, Vinoth | F11: 8 | G11: 2 | H11: 1 | I11: 43694 | J11: Closed | K11: _Ready; LMW | L11: GlobalREApps\Debt
A12: =VLOOKUP(B12,'PI Commitments'!#REF!,1,FALSE) -> #REF! | B12: 160978 | C12: CECL - Publish MetLife Internal Ratings in Loan Rating file | D12: Feature | E12: Montoya, Fabio | F12: 4 | G12: 2 | H12: 1 | I12: 43694 | J12: Closed | K12: _Ready; CECL; MIS | L12: GlobalREApps\Debt\CLS
A13: =VLOOKUP(B13,'PI Commitments'!#REF!,1,FALSE) -> #REF! | B13: 162295 | C13: BHF: new compliance fields for ADW | D13: Feature | E13: Cole, Lisa | F13: 3 | G13: 2 | H13: 1 | I13: 43694 | J13: Closed | K13: _Ready; CLS | L13: GlobalREApps\Debt
... A29: =VLOOKUP(B29,'PI Commitments'!#REF!,1,FALSE) -> #REF! | B29: 151392 | C29: Change GA Reportable to Delegated Authority Reportable in LMW | D29: Feature | E29: Mitchell, Aj | F29: 1 | G29: 3 | H29: 1 | I29: 43694 | J29: Closed | K29: _Ready; LMW | L29: GlobalREApps\Debt
A30: =VLOOKUP(B30,'PI Commitments'!#REF!,1,FALSE) -> #REF! | B30: 169146 | C30: Loan Search - Report run and export issues | D30: Feature | E30: Polannagari, Govardhan | G30: 1 | I30: 43701 | J30: Closed | K30: Debt; High Risk; Loan Search; MIS | L30: GlobalREApps\Debt\MIS
A31: =VLOOKUP(B31,'PI Commitments'!#REF!,1,FALSE) -> #REF! | B31: 134972 | C31: BHF : Incorrect REI Market Area & attributes in MIS and upstream systems | D31: Feature | E31: Polannagari, Govardhan | F31: 2 | G31: 1 | H31: 4 | I31: 43701 | J31: Closed | K31: _Ready; MIS | L31: GlobalREApps\Debt\MIS
A32: =VLOOKUP(B32,'PI Commitments'!#REF!,1,FALSE) -> #REF! | B32: 164350 | C32: Subledger data break - Fix for loan#703141 | D32: Feature | E32: Polannagari, Govardhan | G32: 2 | I32: 43701 | J32: Closed | K32: MIS; Problem | L32: GlobalREApps\Debt\MIS
A33: =VLOOKUP(B33,'PI Commitments'!#REF!,1,FALSE) -> #REF! | B33: 145409 | C33: Market Value : Caps and Floors Error | D33: Feature | E33: Polannagari, Govardhan | F33: 4 | G33: 2 | H33: 1 | I33: 43701 | J33: Closed | K33: _Ready; Market Value; MIS | L33: GlobalREApps\Debt\MIS
A34: =VLOOKUP(B34,'PI Commitments'!#REF!,1,FALSE) -> #REF! | B34: 142570 | C34: MARS - Step rate loans incorrectly categorized as ARMs in MIS due to EDM field MetLifeInterestType consumption derivation logic changed. | D34: Feature | E34: Polannagari, Govardhan | F34: 3 | G34: 2 | H34: 2 | I34: 43701 | J34: Closed | K34: _Ready; MARS; MIS | L34: GlobalREApps\Debt\MIS
A35: =VLOOKUP(B35,'PI Commitments'!#REF!,1,FALSE) -> #REF! | B35: 146115 | C35: MIS_PAMTransExtract Load Batch Job update | D35: Feature | E35: Polannagari, Govardhan | F35: 2.5 | G35: 2 | H35: 2 | I35: 43701 | J35: Closed | K35: _Ready; MIS | L35: GlobalREApps\Debt
A36: =VLOOKUP(B36,'PI Commitments'!#REF!,1,FALSE) -> #REF! | B36: 159170 | C36: MIS : Company name issue - AVIVA Life & Pensions UK Limited | D36: Feature | E36: Polannagari, Govardhan | F36: 2 | G36: 2 | H36: 2 | I36: 43701 | J36: Closed | K36: MIS; Technical Debt | L36: GlobalREApps\Debt\MIS
A37: =VLOOKUP(B37,'PI Commitments'!#REF!,1,FALSE) -> #REF! | B37: 161675 | C37: MIS Veracode Findings 2019 - High Flaws | D37: Feature | E37: Polannagari, Govardhan | F37: 2 | G37: 2 | H37: 3 | I37: 43701 | J37: Closed | K37: MIS; Technical Debt; Veracode | L37: GlobalREApps\Debt\MIS
A38: =VLOOKUP(B38,'PI Commitments'!#REF!,1,FALSE) -> #REF! | B38: 146600 | C38: MIS Asset File is missing country sub div codes | D38: Feature | E38: Polannagari, Govardhan | F38: 1.333 | G38: 2 | H38: 3 | I38: 43701 | J38: Closed | K38: _Ready; EDM Sub Div Code; MIS | L38: GlobalREApps\Debt
A39: =VLOOKUP(B39,'PI Commitments'!#REF!,1,FALSE) -> #REF! | B39: 158916 | C39: MARS : MIS consumption of TDR fields | D39: Feature | E39: Polannagari, Govardhan | F39: 1.333 | G39: 2 | H39: 3 | I39: 43701 | J39: Closed | K39: _Ready; MARS; MIS | L39: GlobalREApps\Debt\MIS
A40: =VLOOKUP(B40,'PI Commitments'!#REF!,1,FALSE) -> #REF! | B40: 166747 | C40: Incorrect Property Type - Schedule B | D40: Feature | E40: Polannagari, Govardhan | F40: 7 | G40: 1 | H40: 1 | I40: 43722 | J40: Active | K40: _Ready; MIS; Sched B | L40: GlobalREApps\Debt\MIS
A41: =VLOOKUP(B41,'PI Commitments'!#REF!,1,FALSE) -> #REF! | B41: 173796 | C41: MIS Domain Mapping - missing Country Admin Subdivision | D41: Feature | E41: Polannagari, Govardhan | F41: 3 | G41: 1 | H41: 1 | I41: 43722 | J41: New | K41: _Ready; MIS | L41: GlobalREApps\Debt
A42: =VLOOKUP(B42,'PI Commitments'!#REF!,1,FALSE) -> #REF! | B42: 119203 | C42: Data at rest encryption | D42: Feature | E42: Polannagari, Govardhan | F42: 2.25 | G42: 1 | H42: 2 | I42: 43722 | J42: Active | K42: _Ready; MIS | L42: GlobalREApps\Debt\MIS
A43: =VLOOKUP(B43,'PI Commitments'!#REF!,1,FALSE) -> #REF! | B43: 87842 | C43: Ethical Hack: Remediate PrimeOn - medium flaws – Phase 3 | D43: Feature | E43: Talluru, Praveena | F43: 1.6 | G43: 1 | H43: 5 | I43: 43722 | J43: Active | K43: _Ready; LMW | L43: GlobalREApps\Debt\LMW
A44: =VLOOKUP(B44,'PI Commitments'!#REF!,1,FALSE) -> #REF! | B44: 113622 | C44: AG : Servicer compare report enhancement | D44: Feature | E44: Polannagari, Govardhan | F44: 1.2 | G44: 1 | H44: 5 | I44: 43722 | J44: Active | K44: _Ready; AG; MIS | L44: GlobalREApps\Debt\MIS
... A61: =VLOOKUP(B61,'PI Commitments'!#REF!,1,FALSE) -> #REF! | B61: 122060 | C61: MIS : Portfolio Exposure Data Dump Report Enhancement | D61: Feature | E61: Polannagari, Govardhan | F61: 0.778 | G61: 2 | H61: 9 | I61: 43722 | J61: Active | K61: _Ready; MIS | L61: GlobalREApps\Debt\MIS
A62: =VLOOKUP(B62,'PI Commitments'!#REF!,1,FALSE) -> #REF! | B62: 155876 | C62: Backshop Field Extract for MIST | D62: Feature | E62: Anderson, William | G62: 2 | H62: 8 | I62: 43728 | J62: Active | K62: Backshop | L62: GlobalREApps\Debt\Backshop
A63: =VLOOKUP(B63,'PI Commitments'!#REF!,1,FALSE) -> #REF! | B63: 162136 | C63: FTP Activities for Backshop Field Extract for MIST | D63: Feature | E63: Anderson, William | G63: 2 | H63: 3 | I63: 43728 | J63: New | K63: Backshop; Backshop_Met | L63: GlobalREApps\Debt
A64: =VLOOKUP(B64,'PI Commitments'!#REF!,1,FALSE) -> #REF! | B64: 156000 | C64: Revisions and additions to the REI Market Area reference data_Backshop | D64: Feature | E64: Mitchell, Aj | F64: 3 | G64: 2 | H64: 2 | I64: 43728 | J64: Active | K64: _Ready; Backshop | L64: GlobalREApps\Debt
A65: =VLOOKUP(B65,'PI Commitments'!#REF!,1,FALSE) -> #REF! | B65: 150715 | C65: Increase the Commitment Fee (BPS) field size from 1 decimal to 2 decimal places in MIM notification | D65: Feature | E65: Anderson, William | F65: 3 | G65: 2 | H65: 1 | I65: 43728 | J65: New | K65: _Ready; Backshop | L65: GlobalREApps\Debt
A66: =VLOOKUP(B66,'PI Commitments'!#REF!,1,FALSE) -> #REF! | B66: 160505 | C66: BackShop Audit file generation delays | D66: Feature | E66: Anderson, William | F66: 1.333 | G66: 2 | H66: 3 | I66: 43728 | J66: New | K66: Backshop; Backshop_Met; Japan Item | L66: GlobalREApps\Debt
A67: =VLOOKUP(B67,'PI Commitments'!#REF!,1,FALSE) -> #REF! | B67: 113634 | C67: Calculate Relative Value for Comm and AG Assets | D67: Feature | E67: Mitchell, Aj | F67: 1.167 | G67: 2 | H67: 6 | I67: 43728 | J67: Active | K67: _Spike; Backshop; Backshop_Met | L67: GlobalREApps\Debt
A68: =VLOOKUP(B68,'PI Commitments'!#REF!,1,FALSE) -> #REF! | B68: 61014 | C68: Capitalized Interest Transactions | D68: Feature | E68: Cole, Lisa | F68: 0.8333 | G68: 2 | H68: 6 | I68: 43728 | J68: New | K68: _Spike; CLS | L68: GlobalREApps\Debt
A69: =VLOOKUP(B69,'PI Commitments'!#REF!,1,FALSE) -> #REF! | B69: 160836 | C69: Insert New REI Market Areas and revise several existing | D69: Feature | E69: Polannagari, Govardhan | G69: 2 | I69: 43729 | J69: New | K69: LMW | L69: GlobalREApps\Debt
A70: =VLOOKUP(B70,'PI Commitments'!#REF!,1,FALSE) -> #REF! | B70: 143186 | C70: SFR loans to CLS from Midland | D70: Feature | E70: Lopez, Ascension | F70: 1.333 | G70: 1 | H70: 4 | I70: 43735 | J70: New | K70: _Ready; CLS | L70: GlobalREApps\Debt
A71: =VLOOKUP(B71,'PI Commitments'!#REF!,1,FALSE) -> #REF! | B71: 161827 | C71: Discovery: Move calculation of price from MIS to LMW | D71: Feature | E71: Mitchell, Aj | F71: 2.667 | G71: 1 | H71: 3 | I71: 43736 | J71: New | K71: _Spike; LMW | L71: GlobalREApps\Debt
A72: =VLOOKUP(B72,'PI Commitments'!#REF!,1,FALSE) -> #REF! | B72: 149953 | C72: Discovery: Add a new data field for Investor Summary Commentary in LMW Watchlist comments control | D72: Feature | E72: Mitchell, Aj | F72: 2.33 | G72: 1 | H72: 3 | I72: 43736 | J72: New | K72: _Spike; LMW; MIM Client Portal | L72: GlobalREApps\Debt
A73: =VLOOKUP(B73,'PI Commitments'!#REF!,1,FALSE) -> #REF! | B73: 163297 | C73: EMEA data for Dublin Bank - Paid in full loans | D73: Feature | E73: Cole, Lisa | F73: 1.333 | G73: 1 | H73: 3 | I73: 43736 | J73: New | K73: _Ready; CLS; OneSource | L73: GlobalREApps\Debt\LMW
A74: =VLOOKUP(B74,'PI Commitments'!#REF!,1,FALSE) -> #REF! | B74: 144510 | C74: Langhorne: Transactions JSON Implementation | D74: Feature | E74: Polannagari, Govardhan | F74: 1 | G74: 2 | H74: 2 | I74: 43736 | J74: New | K74: _Ready; CLS; Digital Portal; Framework; Langhorne | L74: GlobalREApps\Debt\CLS
A75: =VLOOKUP(B75,'PI Commitments'!#REF!,1,FALSE) -> #REF! | B75: 144511 | C75: Langhorne: Commitment JSON Implementation | D75: Feature | E75: Polannagari, Govardhan | F75: 1 | G75: 2 | H75: 6 | I75: 43736 | J75: New | K75: CECL; Digital Portal; Framework; Langhorne | L75: GlobalREApps\Debt\CLS
A76: =VLOOKUP(B76,'PI Commitments'!#REF!,1,FALSE) -> #REF! | B76: 151869 | C76: Langhorne: Property Valuation JSON | D76: Feature | E76: Polannagari, Govardhan | F76: 1 | G76: 2 | H76: 4 | I76: 43736 | J76: New | K76: _R; Digital Portal; Langhorne; MIS | L76: GlobalREApps\Debt
A77: =VLOOKUP(B77,'PI Commitments'!#REF!,1,FALSE) -> #REF! | B77: 151727 | C77: Langhorne - Asset (Loan) Masters JSON NEW ELEMENTS to EDM | D77: Feature | E77: Polannagari, Govardhan | F77: 1.286 | G77: 1 | H77: 7 | I77: 43743 | J77: New | K77: Digital Portal; Langhorne | L77: GlobalREApps\Debt
A78: =VLOOKUP(B78,'PI Commitments'!#REF!,1,FALSE) -> #REF! | B78: 161828 | C78: Phase 1: Move calculation of price from MIS to LMW | D78: Feature | E78: Mitchell, Aj | F78: 1.2 | G78: 1 | H78: 5 | I78: 43743 | J78: New | K78: LMW | L78: GlobalREApps\Debt
A79: =VLOOKUP(B79,'PI Commitments'!#REF!,1,FALSE) -> #REF! | B79: 163491 | C79: Portfolio code expansion - Phase 3 | D79: Feature | E79: Cole, Lisa | F79: 1 | G79: 1 | H79: 4 | I79: 43743 | J79: New | K79: _Ready; CLS; LMW | L79: GlobalREApps\Debt
A80: =VLOOKUP(B80,'PI Commitments'!#REF!,1,FALSE) -> #REF! | B80: 163497 | C80: Portfolio code expansion - Phase 3 | D80: Feature | E80: Polannagari, Govardhan | F80: 1 | G80: 1 | H80: 6 | I80: 43743 | J80: Active | K80: _Ready; MIS | L80: GlobalREApps\Debt
A81: =VLOOKUP(B81,'PI Commitments'!#REF!,1,FALSE) -> #REF! | B81: 165192 | C81: Langhorne ME - Asset Rating JSON | D81: Feature | E81: Polannagari, Govardhan | F81: 2 | G81: 2 | H81: 3 | I81: 43743 | J81: New | K81: CLS; Langhorne; LMW | L81: GlobalREApps\Debt
... A91: =VLOOKUP(B91,'PI Commitments'!#REF!,1,FALSE) -> #REF! | B91: 161232 | C91: Adding new balance fields in CLS for CECL Accounting and publish to MIS (Phase 1) | D91: Feature | E91: Montoya, Fabio | F91: 0.75 | G91: 1 | H91: 5 | I91: 43746 | J91: New | K91: CECL; CLS | L91: GlobalREApps\Debt\CLS
A92: =VLOOKUP(B92,'PI Commitments'!#REF!,1,FALSE) -> #REF! | B92: 166870 | C92: CECL - Additional corrections in CSV Input feed | D92: Feature | E92: Montoya, Fabio | G92: 2 | H92: 3 | I92: 43746 | J92: New | K92: CECL; LMW | L92: GlobalREApps\Debt\CLS
A93: =VLOOKUP(B93,'PI Commitments'!#REF!,1,FALSE) -> #REF! | B93: 144514 | C93: Langhorne: Amortization Schedule in JSON Implementation | D93: Feature | E93: Soundararajan, Madhan Kumar | F93: 1 | G93: 2 | H93: 2 | I93: 43746 | J93: Active | K93: Langhorne | L93: GlobalREApps\Debt\CLS
A94: =VLOOKUP(B94,'PI Commitments'!#REF!,1,FALSE) -> #REF! | B94: 150749 | C94: Discovery - Make non REI managed loans viewable | D94: Feature | E94: Mitchell, Aj | F94: 1 | G94: 2 | H94: 3 | I94: 43746 | J94: New | K94: _Spike; LMW | L94: GlobalREApps\Debt
A95: =VLOOKUP(B95,'PI Commitments'!#REF!,1,FALSE) -> #REF! | B95: 120687 | C95: Chile Commercial mortgages data for input into calculator | D95: Feature | E95: Montoya, Fabio | F95: 3 | G95: 3 | H95: 1 | I95: 43746 | J95: New | K95: CECL; LMW | L95: GlobalREApps\Debt\CLS
A96: =VLOOKUP(B96,'PI Commitments'!#REF!,1,FALSE) -> #REF! | B96: 161707 | C96: Chile Commercial mortgages data for outbound into calculator | D96: Feature | E96: Montoya, Fabio | F96: 3 | G96: 3 | H96: 1 | I96: 43746 | J96: New | K96: CECL; LMW | L96: GlobalREApps\Debt\CLS

Sheet Start Here
B1: PI Sprint # | C1: Cloud Services Sprint # | D1: Start Date | E1: End Date | G1: Release | H1: PI-Sprint | I1: Env | J1: Abbrev | K1: Start Date | L1: End Date | N1: Red = Holiday
A2: PI-8 Sprint Dates | B2: 5 | C2: 96 | D2: 44643 | E2: 44656 | G2: April 2022 | H2: (PI-8) 3-5 | I2: DEV | J2: DA | K2: =K5-47 -> 44620 | L2: =K5-22 -> 44645 | O2: S | P2: M | Q2: T | R2: W | S2: T | T2: F | U2: S | X2: S | Y2: M | Z2: T | AA2: W | AB2: T | AC2: F | AD2: S
B3: 6 | C3: =C2+1 -> 97 | D3: 44657 | E3: 44670 | H3: (PI-8) 5-6 | I3: SIT/INT | J3: SA | K3: =K5-19 -> 44648 | L3: =K5-15 -> 44652 | N3: April | T3: 1 | U3: 2 | W3: May | X3: 1 | Y3: 2 | Z3: 3 | AA3: 4 | AB3: 5 | AC3: 6 | AD3: 7
A4: PI-9 Sprint Dates | B4: 1 | C4: =C3+1 -> 98 | D4: =D3+14 -> 44671 | E4: =E3+14 -> 44684 | H4: (PI-8) 6 | I4: UAT/QA | J4: UA | K4: =K5-12 -> 44655 | L4: =K5-4 -> 44663 | T4: SA, UA, DY | U4: SA, UA, DY | X4: SY,UY | Y4: UY,DU | Z4: UY,DU | AA4: UY,DU | AB4: UY,DU | AC4: UY,DU | AD4: UY,DU
B5: 2 | C5: =C4+1 -> 99 | D5: =D4+14 -> 44685 | E5: =E4+14 -> 44698 | H5: (PI-9) 1 | I5: PROD+DR | J5: PA | K5: 44667 | O5: 3 | P5: 4 | Q5: 5 | R5: 6 | S5: 7 | T5: 8 | U5: 9 | X5: 8 | Y5: 9 | Z5: 10 | AA5: 11 | AB5: 12 | AC5: 13 | AD5: 14
B6: 3 | C6: =C5+1 -> 100 | D6: =D5+14 -> 44699 | E6: =E5+14 -> 44712 | G6: May 2022 | H6: (PI-8) 5-6 (PI-9) 1 | I6: DEV | J6: DY | K6: =K9-47 -> 44648 | L6: =K9-22 -> 44673 | O6: SA, UA, DY | P6: UA, DY | Q6: UA, DY | R6: UA, DY | S6: UA, DY | T6: UA, DY | U6: UA, DY | X6: UY,DU | Y6: UY,DU | Z6: UY,DU | AA6: PY,DU | AB6: PY,DU | AC6: PY,DU | AD6: PY,DU
B7: 4 | C7: =C6+1 -> 101 | D7: =D6+14 -> 44713 | E7: =E6+14 -> 44726 | H7: (PI-9) 1 | I7: SIT/INT | J7: SY | K7: =K9-19 -> 44676 | L7: =K9-15 -> 44680 | O7: 10 | P7: 11 | Q7: 12 | R7: 13 | S7: 14 | T7: 15 | U7: 16 | X7: 15 | Y7: 16 | Z7: 17 | AA7: 18 | AB7: 19 | AC7: 20 | AD7: 21
B8: 5 | C8: =C7+1 -> 102 | D8: =D7+14 -> 44727 | E8: =E7+14 -> 44740 | H8: (PI-9) 1-2 | I8: UAT/QA | J8: UY | K8: =K9-12 -> 44683 | L8: =K9-4 -> 44691 | O8: UA, DY | P8: UA, DY | Q8: UA, DY | R8: PA,DY | S8: PA,DY | T8: PA,DY | U8: PA,DY | X8: DU | Y8: DU | Z8: DU | AA8: DU | AB8: DU | AC8: DU | AD8: DU
B9: 6 | C9: =C8+1 -> 103 | D9: =D8+14 -> 44741 | E9: =E8+14 -> 44754 | H9: (PI-9) 3 | I9: PROD+DR | J9: PY | K9: 44695 | O9: 17 | P9: 18 | Q9: 19 | R9: 20 | S9: 21 | T9: 22 | U9: 23 | X9: 22 | Y9: 23 | Z9: 24 | AA9: 25 | AB9: 26 | AC9: 27 | AD9: 28
A10: PI-10 | B10: 1 | C10: =C9+1 -> 104 | D10: =D9+14 -> 44755 | E10: =E9+14 -> 44768 | G10: June 2022 | H10: (PI-9) 1-3 | I10: DEV | J10: DU | K10: =K13-47 -> 44683 | L10: =K13-22 -> 44708 | O10: DY | P10: DY | Q10: DY | R10: DY | S10: DY | T10: DY,SY | U10: DY,SY | X10: DU | Y10: DU | Z10: DU | AA10: DU | AB10: DU | AC10: DU,SU | AD10: DU,SU
B11: 2 | C11: =C10+1 -> 105 | D11: =D10+14 -> 44769 | E11: =E10+14 -> 44782 | H11: (PI-9) 3 | I11: SIT/INT | J11: SU | K11: =K13-19 -> 44711 | L11: =K13-15 -> 44715 | O11: 24 | P11: 25 | Q11: 26 | R11: 27 | S11: 28 | T11: 29 | U11: 30 | X11: 29 | Y11: 30 | Z11: 31
H12: (PI-9) 3-4 | I12: UAT/QA | J12: UU | K12: =K13-12 -> 44718 | L12: =K13-4 -> 44726 | O12: DY,SY | P12: SY | Q12: SY | R12: SY | S12: SY | T12: SY,UY | U12: SY,UY | X12: DU,SU | Y12: SU,DL | Z12: SU,DL
H13: (PI-8) 4 | I13: PROD+DR | J13: PU | K13: 44730
G14: July 2022 | H14: (PI-8) 3-5 | I14: DEV | J14: DL | K14: =K17-47 -> 44711 | L14: =K17-22 -> 44736
H15: (PI-8) 5-6 | I15: SIT/INT | J15: SL | K15: =K17-19 -> 44739 | L15: =K17-15 -> 44743
H16: (PI-8) 6 | I16: UAT/QA | J16: UL | K16: =K17-12 -> 44746 | L16: =K17-4 -> 44754 | O16: S | P16: M | Q16: T | R16: W | S16: T | T16: F | U16: S | X16: S | Y16: M | Z16: T | AA16: W | AB16: T | AC16: F | AD16: S
D17: Planned | E17: Available=Actual - Holidays | H17: (PI-9) 1 | I17: PROD+DR | J17: PL | K17: 44758 | N17: June | R17: 1 | S17: 2 | T17: 3 | U17: 4 | W17: July | AC17: 1 | AD17: 2
D18: 74 | G18: Aug 2022 | H18: (PI-8) 5-6 (PI-9) 1 | I18: DEV | J18: DG | K18: =K21-47 -> 44746 | L18: =K21-22 -> 44771 | R18: SU,DL | S18: SU,DL | T18: SU,UU,DL | U18: SU,UU,DL | AC18: SL,UL | AD18: SL,UL
H19: (PI-9) 1-2 | I19: SIT/INT | J19: SG | K19: =K21-19 -> 44774 | L19: =K21-15 -> 44778 | O19: 5 | P19: 6 | Q19: 7 | R19: 8 | S19: 9 | T19: 10 | U19: 11 | X19: 3 | Y19: 4 | Z19: 5 | AA19: 6 | AB19: 7 | AC19: 8 | AD19: 9
H20: (PI-9) 2 | I20: UAT/QA | J20: UG | K20: =K21-12 -> 44781 | L20: =K21-4 -> 44789 | O20: SU,UU,DL | P20: UU,DL | Q20: UU,DL | R20: UU,DL | S20: UU,DL | T20: UU,DL | U20: UU,DL | X20: SL,UL | Y20: UL,DG | Z20: UL,DG | AA20: UL,DG | AB20: UL,DG | AC20: UL,DG | AD20: UL,DG
H21: (PI-9) 3 | I21: PROD+DR | J21: PG | K21: 44793 | O21: 12 | P21: 13 | Q21: 14 | R21: 15 | S21: 16 | T21: 17 | U21: 18 | X21: 10 | Y21: 11 | Z21: 12 | AA21: 13 | AB21: 14 | AC21: 15 | AD21: 16
O22: UU,DL | P22: UU,DL | Q22: UU,DL | R22: PU,DL | S22: PU,DL | T22: PU,DL | U22: PU,DL | X22: UL,DG | Y22: UL,DG | Z22: UL,DG | AA22: PL,DG | AB22: PL,DG | AC22: PL,DG | AD22: PL,DG
G23: Abbreviations | H23: Environments | I23: Months | O23: 19 | P23: 20 | Q23: 21 | R23: 22 | S23: 23 | T23: 24 | U23: 25 | X23: 17 | Y23: 18 | Z23: 19 | AA23: 20 | AB23: 21 | AC23: 22 | AD23: 23
D24: Ninjas | E24: Samurais | G24: (Legend) | I24: J = January | K24: L = July | O24: DL | P24: DL | Q24: DL | R24: DL | S24: DL | T24: DL,SL | U24: DL,SL | X24: DG | Y24: DG | Z24: DG | AA24: DG | AB24: DG | AC24: DG | AD24: DG
A25: 1 | B25: 44671 | C25: 44684 | D25: sprint 59 | E25: Sprint 98 | H25: D = Dev | I25: F = February | K25: G = August | O25: 26 | P25: 27 | Q25: 28 | R25: 29 | S25: 30 | X25: 24 | Y25: 25 | Z25: 26 | AA25: 27 | AB25: 28 | AC25: 29 | AD25: 30
A26: 2 | B26: 44685 | C26: 44698 | D26: sprint 60 | E26: Sprint 99 | H26: S = SIT/INT | I26: M = March | K26: S = September | O26: DL,SL | P26: SL | Q26: SL | R26: SL | S26: SL | X26: DG | Y26: DG | Z26: DG | AA26: DG | AB26: DG | AC26: DG,SG | AD26: DG,SG
A27: 3 | B27: 44699 | C27: 44712 | D27: sprint 61 | E27: Sprint 100 | H27: U = UAT/QA | I27: A = April | K27: O = October | X27: 31
A28: 4 | B28: 44713 | C28: 44726 | D28: sprint 62 | E28: Sprint 101 | H28: P = PROD+DR | I28: Y = May | K28: N = November | X28: DG,SG
A29: 5 | B29: 44727 | C29: 44740 | D29: sprint 63 | E29: Sprint 102 | I29: U = June | K29: D = December
A30: 6 | B30: 44741 | C30: 44754 | D30: sprint 64 | E30: Sprint 103 | O30: S | P30: M | Q30: T | R30: W | S30: T | T30: F | U30: S
N31: August | P31: 1 | Q31: 2 | R31: 3 | S31: 4 | T31: 5 | U31: 6
H32: =E4-D4+1 -> 14 | I32: =E7-D7+1 -> 14
H33: =K10-D4+1 -> 13 | I33: =L12-E7+1 -> 1 | O33: 7 | P33: 8 | Q33: 9 | R33: 10 | S33: 11 | T33: 12 | U33: 13
A34: swapna | B34: 44572 | C34: 1 | H34: =CEILING((1-H33/H32)*5,1) -> 1 | I34: =CEILING((1-I33/I32)*5,1) -> 5
A35: abhijith | O35: 14 | P35: 15 | Q35: 16 | R35: 17 | S35: 18 | T35: 19 | U35: 20
A36: Krishna
A37: Prasob | B37: 1/24,2/18 | C37: 2 | O37: 21 | P37: 22 | Q37: 23 | R37: 24 | S37: 25 | T37: 26 | U37: 27
A38: lokesh | B38: 1/27,28; 2/14,15; | C38: 4
A39: manoj | O39: 28 | P39: 29 | Q39: 30 | R39: 31
A40: smba | B40: 1/17,18; march 5 days | C40: 7
A43: Aravind
A44: Ashish
A46: Anoop
A47: Abdul Hanan
A48: Mala
A49: Vijay
A50: Pradeep

Sheet Resource Planning
B1: End Date | E1: 44657 | F1: =E1+14 -> 44671 | G1: =F1+14 -> 44685 | H1: =G1+14 -> 44699 | I1: =H1+14 -> 44713 | J1: =I1+14 -> 44727 | K1: =J1+14 -> 44741 | N1: Black Widow
C2: Name | D2: Team | E2: Allotment | F2: S1 | G2: S2 | H2: S3 | I2: S4 | J2: S5 | K2: S6 | N2: Captain America | R2: Commit
B3: AJ | C3: Abhijith Jayakumar | D3: The Ninjas | E3: 1 | F3: =(1-(COUNTIF($AE$10:$AQ$23, $B3)/10))*$E3 -> 0.9 | G3: =(1-(COUNTIF($AE$24:$AQ$37, $B3)/10))*$E3 -> 1 | H3: =(1-(COUNTIF($AE$38:$AQ$51, $B3)/10))*$E3 -> 0.9 | I3: =(1-(COUNTIF($AE$52:$AQ$65, $B3)/10))*$E3 -> 1 | J3: =(1-(COUNTIF($AE$66:$AQ$79, $B3)/10))*$E3 -> 1 | K3: =(1-(COUNTIF($AE$80:$AQ$93, $B3)/10))*$E3 -> 1 | L3: =SUM(F3:K3)*8 -> 46.4 | M3: =SUM(F3:K3) *8 -> 46.4 | N3: Hulk | R3: Resolved
B4: JB | C4: Jagadeesan Balasubramanian | D4: The Ninjas | E4: 1 | F4: =(1-(COUNTIF($AE$10:$AQ$23, $B4)/10))*$E4 -> 1 | G4: =(1-(COUNTIF($AE$24:$AQ$37, $B4)/10))*$E4 -> 1 | H4: =(1-(COUNTIF($AE$38:$AQ$51, $B4)/10))*$E4 -> 0.9 | I4: =(1-(COUNTIF($AE$52:$AQ$65, $B4)/10))*$E4 -> 1 | J4: =(1-(COUNTIF($AE$66:$AQ$79, $B4)/10))*$E4 -> 1 | K4: =(1-(COUNTIF($AE$80:$AQ$93, $B4)/10))*$E4 -> 0.9 | L4: =SUM(F4:K4)*8 -> 46.4 | M4: =SUM(F4:K4) *8 -> 46.4 | N4: Ironman | R4: Stretch
A5: 11 | B5: KCK | C5: Krishna chandar kandula | D5: The Ninjas | E5: 1 | F5: =(1-(COUNTIF($AE$10:$AQ$23, $B5)/10))*$E5 -> 0.9 | G5: =(1-(COUNTIF($AE$24:$AQ$37, $B5)/10))*$E5 -> 1 | H5: =(1-(COUNTIF($AE$38:$AQ$51, $B5)/10))*$E5 -> 1 | I5: =(1-(COUNTIF($AE$52:$AQ$65, $B5)/10))*$E5 -> 1 | J5: =(1-(COUNTIF($AE$66:$AQ$79, $B5)/10))*$E5 -> 1 | K5: =(1-(COUNTIF($AE$80:$AQ$93, $B5)/10))*$E5 -> 1 | L5: =SUM(F5:K5)*8 -> 47.2 | M5: =SUM(F5:K5) *8 -> 47.2 | N5: Vision | R5: Vendor
B6: KN | C6: Krishnaraj Nagaraj | D6: The Ninjas | E6: 0.9 | F6: =(1-(COUNTIF($AE$10:$AQ$23, $B6)/10))*$E6 -> 0.9 | G6: =(1-(COUNTIF($AE$24:$AQ$37, $B6)/10))*$E6 -> 0.9 | H6: =(1-(COUNTIF($AE$38:$AQ$51, $B6)/10))*$E6 -> 0.9 | I6: =(1-(COUNTIF($AE$52:$AQ$65, $B6)/10))*$E6 -> 0.9 | J6: =(1-(COUNTIF($AE$66:$AQ$79, $B6)/10))*$E6 -> 0.9 | K6: =(1-(COUNTIF($AE$80:$AQ$93, $B6)/10))*$E6 -> 0.9 | L6: =SUM(F6:K6)*8 -> 43.2 | M6: =SUM(F6:K6) *8 -> 43.2
B7: LS | C7: Lokeshwaran Sankar | D7: The Ninjas | E7: 1 | F7: =(1-(COUNTIF($AE$10:$AQ$23, $B7)/10))*$E7 -> 0.9 | G7: =(1-(COUNTIF($AE$24:$AQ$37, $B7)/10))*$E7 -> 1 | H7: =(1-(COUNTIF($AE$38:$AQ$51, $B7)/10))*$E7 -> 1 | I7: =(1-(COUNTIF($AE$52:$AQ$65, $B7)/10))*$E7 -> 1 | J7: =(1-(COUNTIF($AE$66:$AQ$79, $B7)/10))*$E7 -> 1 | K7: =(1-(COUNTIF($AE$80:$AQ$93, $B7)/10))*$E7 -> 1 | L7: =SUM(F7:K7)*8 -> 47.2 | M7: =SUM(F7:K7) *8 -> 47.2
B8: MM | C8: Manoj Madhavan | D8: The Ninjas | E8: 1 | F8: =(1-(COUNTIF($AE$10:$AQ$23, $B8)/10))*$E8 -> 0.7 | G8: =(1-(COUNTIF($AE$24:$AQ$37, $B8)/10))*$E8 -> 0.9 | H8: =(1-(COUNTIF($AE$38:$AQ$51, $B8)/10))*$E8 -> 0.9 | I8: =(1-(COUNTIF($AE$52:$AQ$65, $B8)/10))*$E8 -> 1 | J8: =(1-(COUNTIF($AE$66:$AQ$79, $B8)/10))*$E8 -> 1 | K8: =(1-(COUNTIF($AE$80:$AQ$93, $B8)/10))*$E8 -> 1 | L8: =SUM(F8:K8)*8 -> 44 | M8: =SUM(F8:K8) *8 -> 44 | S8: SAMURAIS | AE8: NINJAS
B9: MHA | C9: Meraj Husen Ansari | D9: The Ninjas | E9: 1 | F9: =(1-(COUNTIF($AE$10:$AQ$23, $B9)/10))*$E9 -> 0.9 | G9: =(1-(COUNTIF($AE$24:$AQ$37, $B9)/10))*$E9 -> 1 | H9: =(1-(COUNTIF($AE$38:$AQ$51, $B9)/10))*$E9 -> 1 | I9: =(1-(COUNTIF($AE$52:$AQ$65, $B9)/10))*$E9 -> 1 | J9: =(1-(COUNTIF($AE$66:$AQ$79, $B9)/10))*$E9 -> 1 | K9: =(1-(COUNTIF($AE$80:$AQ$93, $B9)/10))*$E9 -> 1 | L9: =SUM(F9:K9)*8 -> 47.2 | M9: =SUM(F9:K9) *8 -> 47.2 | S9: AN | T9: AM | U9: ASU | V9: DF | W9: JR | X9: KN | Y9: MN | Z9: RB | AA9: VS | AB9: VG | AC9: AC | AD9: VA | AE9: AJ | AF9: JB | AG9: KCK | AH9: KN | AI9: LS | AJ9: MM | AK9: MHA | AL9: PN | AM9: SSRP | AN9: SS | AO9: SwM | AP9: VS | AQ9: DF
B10: PN | C10: Prasob Nambuthodiyil | D10: The Ninjas | E10: 1 | F10: =(1-(COUNTIF($AE$10:$AQ$23, $B10)/10))*$E10 -> 0.8 | G10: =(1-(COUNTIF($AE$24:$AQ$37, $B10)/10))*$E10 -> 1 | H10: =(1-(COUNTIF($AE$38:$AQ$51, $B10)/10))*$E10 -> 1 | I10: =(1-(COUNTIF($AE$52:$AQ$65, $B10)/10))*$E10 -> 1 | J10: =(1-(COUNTIF($AE$66:$AQ$79, $B10)/10))*$E10 -> 1 | K10: =(1-(COUNTIF($AE$80:$AQ$93, $B10)/10))*$E10 -> 1 | L10: =SUM(F10:K10)*8 -> 46.4 | M10: =SUM(F10:K10) *8 -> 46.4 | Q10: Apr | R10: 20 | AC10: AC
B11: SSRP | C11: Samba siva rao prudhivi | D11: The Ninjas | E11: 1 | F11: =(1-(COUNTIF($AE$10:$AQ$23, $B11)/10))*$E11 -> 0.9 | G11: =(1-(COUNTIF($AE$24:$AQ$37, $B11)/10))*$E11 -> 1 | H11: =(1-(COUNTIF($AE$38:$AQ$51, $B11)/10))*$E11 -> 1 | I11: =(1-(COUNTIF($AE$52:$AQ$65, $B11)/10))*$E11 -> 1 | J11: =(1-(COUNTIF($AE$66:$AQ$79, $B11)/10))*$E11 -> 1 | K11: =(1-(COUNTIF($AE$80:$AQ$93, $B11)/10))*$E11 -> 1 | L11: =SUM(F11:K11)*8 -> 47.2 | M11: =SUM(F11:K11) *8 -> 47.2 | R11: 21
B12: SS | C12: Shibu Swaminathan (repl) | D12: The Ninjas | E12: 1 | F12: =(1-(COUNTIF($AE$10:$AQ$23, $B12)/10))*$E12 -> 0.9 | G12: =(1-(COUNTIF($AE$24:$AQ$37, $B12)/10))*$E12 -> 1 | H12: =(1-(COUNTIF($AE$38:$AQ$51, $B12)/10))*$E12 -> 1 | I12: =(1-(COUNTIF($AE$52:$AQ$65, $B12)/10))*$E12 -> 1 | J12: =(1-(COUNTIF($AE$66:$AQ$79, $B12)/10))*$E12 -> 1 | K12: =(1-(COUNTIF($AE$80:$AQ$93, $B12)/10))*$E12 -> 1 | L12: =SUM(F12:K12)*8 -> 47.2 | M12: =SUM(F12:K12) *8 -> 47.2 | R12: 22 | AL12: PN
B13: SwM | C13: Swapna Madhu | D13: The Ninjas | E13: 1 | F13: =(1-(COUNTIF($AE$10:$AQ$23, $B13)/10))*$E13 -> 0.9 | G13: =(1-(COUNTIF($AE$24:$AQ$37, $B13)/10))*$E13 -> 1 | H13: =(1-(COUNTIF($AE$38:$AQ$51, $B13)/10))*$E13 -> 1 | I13: =(1-(COUNTIF($AE$52:$AQ$65, $B13)/10))*$E13 -> 1 | J13: =(1-(COUNTIF($AE$66:$AQ$79, $B13)/10))*$E13 -> 1 | K13: =(1-(COUNTIF($AE$80:$AQ$93, $B13)/10))*$E13 -> 1 | L13: =SUM(F13:K13)*8 -> 47.2 | M13: =SUM(F13:K13) *8 -> 47.2 | R13: 23
B14: VS | C14: Varun Sundar | D14: The Ninjas | E14: 0.2 | F14: =(1-(COUNTIF($AE$10:$AQ$23, $B14)/10))*$E14 -> 0.2 | G14: =(1-(COUNTIF($AE$24:$AQ$37, $B14)/10))*$E14 -> 0.2 | H14: =(1-(COUNTIF($AE$38:$AQ$51, $B14)/10))*$E14 -> 0.18 | I14: =(1-(COUNTIF($AE$52:$AQ$65, $B14)/10))*$E14 -> 0.2 | J14: =(1-(COUNTIF($AE$66:$AQ$79, $B14)/10))*$E14 -> 0.2 | K14: =(1-(COUNTIF($AE$80:$AQ$93, $B14)/10))*$E14 -> 0.18 | L14: =SUM(F14:K14)*8 -> 9.28 | M14: =SUM(F14:K14) *8 -> 9.28 | R14: 24
B15: DF | C15: Dana Fillhart | D15: The Ninjas | E15: 0.4 | F15: =(1-(COUNTIF($AE$10:$AQ$23, $B15)/10))*$E15 -> 0.4 | G15: =(1-(COUNTIF($AE$24:$AQ$37, $B15)/10))*$E15 -> 0.4 | H15: =(1-(COUNTIF($AE$38:$AQ$51, $B15)/10))*$E15 -> 0.36 | I15: =(1-(COUNTIF($AE$52:$AQ$65, $B15)/10))*$E15 -> 0.4 | J15: =(1-(COUNTIF($AE$66:$AQ$79, $B15)/10))*$E15 -> 0.28 | K15: =(1-(COUNTIF($AE$80:$AQ$93, $B15)/10))*$E15 -> 0.36 | L15: =SUM(F15:K15)*8 -> 17.6 | M15: =SUM(F15:K15) *8 -> 17.6 | R15: 25
A16: 12 | B16: AN | C16: Abdul Naik | D16: Samurai | E16: 1 | F16: =(1-(COUNTIF($S$10:$AD$23, $B16)/10))*$E16 -> 0.8 | G16: =(1-(COUNTIF($S$24:$AD$37, $B16)/10))*$E16 -> 0.7 | H16: =(1-(COUNTIF($S$38:$AD$51, $B16)/10))*$E16 -> 1 | I16: =(1-(COUNTIF($S$52:$AD$65, $B16)/10))*$E16 -> 1 | J16: =(1-(COUNTIF($S$66:$AD$79, $B16)/10))*$E16 -> 1 | K16: =(1-(COUNTIF($S$80:$AD$93, $B16)/10))*$E16 -> 1 | L16: =SUM(F16:K16)*8 -> 44 | M16: =SUM(F16:K16) *8 -> 44 | R16: 26 | Z16: RB
B17: AM | C17: Anoop Mohan | D17: Samurai | E17: 1 | F17: =(1-(COUNTIF($S$10:$AD$23, $B17)/10))*$E17 -> 0.8 | G17: =(1-(COUNTIF($S$24:$AD$37, $B17)/10))*$E17 -> 0.7 | H17: =(1-(COUNTIF($S$38:$AD$51, $B17)/10))*$E17 -> 1 | I17: =(1-(COUNTIF($S$52:$AD$65, $B17)/10))*$E17 -> 1 | J17: =(1-(COUNTIF($S$66:$AD$79, $B17)/10))*$E17 -> 1 | K17: =(1-(COUNTIF($S$80:$AD$93, $B17)/10))*$E17 -> 1 | L17: =SUM(F17:K17)*8 -> 44 | M17: =SUM(F17:K17) *8 -> 44 | R17: 27 | Z17: RB
B18: ASU | C18: Aravind Syama Unni | D18: Samurai | E18: 1 | F18: =(1-(COUNTIF($S$10:$AD$23, $B18)/10))*$E18 -> 0.9 | G18: =(1-(COUNTIF($S$24:$AD$37, $B18)/10))*$E18 -> 1 | H18: =(1-(COUNTIF($S$38:$AD$51, $B18)/10))*$E18 -> 1 | I18: =(1-(COUNTIF($S$52:$AD$65, $B18)/10))*$E18 -> 0.8 | J18: =(1-(COUNTIF($S$66:$AD$79, $B18)/10))*$E18 -> 1 | K18: =(1-(COUNTIF($S$80:$AD$93, $B18)/10))*$E18 -> 1 | L18: =SUM(F18:K18)*8 -> 45.6 | M18: =SUM(F18:K18) *8 -> 45.6 | R18: 28
B19: DF | C19: Dana Fillhart | D19: Samurai | E19: 0.6 | F19: =(1-(COUNTIF($S$10:$AD$23, $B19)/10))*$E19 -> 0.6 | G19: =(1-(COUNTIF($S$24:$AD$37, $B19)/10))*$E19 -> 0.6 | H19: =(1-(COUNTIF($S$38:$AD$51, $B19)/10))*$E19 -> 0.54 | I19: =(1-(COUNTIF($S$52:$AD$65, $B19)/10))*$E19 -> 0.6 | J19: =(1-(COUNTIF($S$66:$AD$79, $B19)/10))*$E19 -> 0.42 | K19: =(1-(COUNTIF($S$80:$AD$93, $B19)/10))*$E19 -> 0.54 | L19: =SUM(F19:K19)*8 -> 26.4 | M19: =SUM(F19:K19) *8 -> 26.4 | R19: 29 | AJ19: MM
B20: JR | C20: Johnson Robin | D20: Samurai | E20: 1 | F20: =(1-(COUNTIF($S$10:$AD$23, $B20)/10))*$E20 -> 0.8 | G20: =(1-(COUNTIF($S$24:$AD$37, $B20)/10))*$E20 -> 1 | H20: =(1-(COUNTIF($S$38:$AD$51, $B20)/10))*$E20 -> 1 | I20: =(1-(COUNTIF($S$52:$AD$65, $B20)/10))*$E20 -> 1 | J20: =(1-(COUNTIF($S$66:$AD$79, $B20)/10))*$E20 -> 1 | K20: =(1-(COUNTIF($S$80:$AD$93, $B20)/10))*$E20 -> 1 | L20: =SUM(F20:K20)*8 -> 46.4 | M20: =SUM(F20:K20) *8 -> 46.4 | AJ20: MM
B21: KN | C21: Krishnaraj Nagarajan | D21: Samurai | E21: 0.1 | F21: =(1-(COUNTIF($S$10:$AD$23, $B21)/10))*$E21 -> 0.1 | G21: =(1-(COUNTIF($S$24:$AD$37, $B21)/10))*$E21 -> 0.1 | H21: =(1-(COUNTIF($S$38:$AD$51, $B21)/10))*$E21 -> 0.09 | I21: =(1-(COUNTIF($S$52:$AD$65, $B21)/10))*$E21 -> 0.1 | J21: =(1-(COUNTIF($S$66:$AD$79, $B21)/10))*$E21 -> 0.1 | K21: =(1-(COUNTIF($S$80:$AD$93, $B21)/10))*$E21 -> 0.09 | L21: =SUM(F21:K21)*8 -> 4.64 | M21: =SUM(F21:K21) *8 -> 4.64
B22: MN | C22: Mala Nadar | D22: Samurai | E22: 1 | F22: =(1-(COUNTIF($S$10:$AD$23, $B22)/10))*$E22 -> 0.9 | G22: =(1-(COUNTIF($S$24:$AD$37, $B22)/10))*$E22 -> 1 | H22: =(1-(COUNTIF($S$38:$AD$51, $B22)/10))*$E22 -> 0.9 | I22: =(1-(COUNTIF($S$52:$AD$65, $B22)/10))*$E22 -> 0.7 | J22: =(1-(COUNTIF($S$66:$AD$79, $B22)/10))*$E22 -> 1 | K22: =(1-(COUNTIF($S$80:$AD$93, $B22)/10))*$E22 -> 1 | L22: =SUM(F22:K22)*8 -> 44 | M22: =SUM(F22:K22) *8 -> 44 | Q22: May | R22: 2 | S22: AN | T22: AM | U22: ASU | W22: JR | Z22: RB | AE22: AJ | AG22: KCK | AI22: LS | AJ22: MM | AK22: MHA | AL22: PN | AM22: SSRP | AN22: SS | AO22: SwM
B23: RB | C23: Rahul Bishnoi | D23: Samurai | E23: 1 | F23: =(1-(COUNTIF($S$10:$AD$23, $B23)/10))*$E23 -> 0.6 | G23: =(1-(COUNTIF($S$24:$AD$37, $B23)/10))*$E23 -> 1 | H23: =(1-(COUNTIF($S$38:$AD$51, $B23)/10))*$E23 -> 1 | I23: =(1-(COUNTIF($S$52:$AD$65, $B23)/10))*$E23 -> 1 | J23: =(1-(COUNTIF($S$66:$AD$79, $B23)/10))*$E23 -> 1 | K23: =(1-(COUNTIF($S$80:$AD$93, $B23)/10))*$E23 -> 1 | L23: =SUM(F23:K23)*8 -> 44.8 | M23: =SUM(F23:K23) *8 -> 44.8 | R23: 3 | S23: AN | T23: AM | W23: JR | Y23: MN | Z23: RB | AC23: AC | AD23: VA
B24: VS | C24: Varun Sundar | D24: Samurai | E24: 0.8 | F24: =(1-(COUNTIF($S$10:$AD$23, $B24)/10))*$E24 -> 0.8 | G24: =(1-(COUNTIF($S$24:$AD$37, $B24)/10))*$E24 -> 0.8 | H24: =(1-(COUNTIF($S$38:$AD$51, $B24)/10))*$E24 -> 0.72 | I24: =(1-(COUNTIF($S$52:$AD$65, $B24)/10))*$E24 -> 0.8 | J24: =(1-(COUNTIF($S$66:$AD$79, $B24)/10))*$E24 -> 0.8 | K24: =(1-(COUNTIF($S$80:$AD$93, $B24)/10))*$E24 -> 0.72 | L24: =SUM(F24:K24)*8 -> 37.12 | M24: =SUM(F24:K24) *8 -> 37.12 | Q24: May | R24: 4 | S24: AN | T24: AM
B25: VG | C25: Vilasini Ganesan | D25: Samurai | E25: 1 | F25: =(1-(COUNTIF($S$10:$AD$23, $B25)/10))*$E25 -> 1 | G25: =(1-(COUNTIF($S$24:$AD$37, $B25)/10))*$E25 -> 1 | H25: =(1-(COUNTIF($S$38:$AD$51, $B25)/10))*$E25 -> 0.9 | I25: =(1-(COUNTIF($S$52:$AD$65, $B25)/10))*$E25 -> 1 | J25: =(1-(COUNTIF($S$66:$AD$79, $B25)/10))*$E25 -> 1 | K25: =(1-(COUNTIF($S$80:$AD$93, $B25)/10))*$E25 -> 0.9 | L25: =SUM(F25:K25)*8 -> 46.4 | M25: =SUM(F25:K25) *8 -> 46.4 | R25: 5 | S25: AN | T25: AM
B26: AC | C26: Ashish Chourey | D26: Samurai | E26: 1 | F26: =(1-(COUNTIF($S$10:$AD$23, $B26)/10))*$E26 -> 0.8 | G26: =(1-(COUNTIF($S$24:$AD$37, $B26)/10))*$E26 -> 1 | H26: =(1-(COUNTIF($S$38:$AD$51, $B26)/10))*$E26 -> 1 | I26: =(1-(COUNTIF($S$52:$AD$65, $B26)/10))*$E26 -> 1 | J26: =(1-(COUNTIF($S$66:$AD$79, $B26)/10))*$E26 -> 1 | K26: =(1-(COUNTIF($S$80:$AD$93, $B26)/10))*$E26 -> 1 | L26: =SUM(F26:K26)*8 -> 46.4 | M26: =SUM(F26:K26) *8 -> 46.4 | R26: 6 | S26: AN | T26: AM
B27: VA | C27: Vijay Amirtharaj | D27: Samurai | E27: 1 | F27: =(1-(COUNTIF($S$10:$AD$23, $B27)/10))*$E27 -> 0.9 | G27: =(1-(COUNTIF($S$24:$AD$37, $B27)/10))*$E27 -> 1 | H27: =(1-(COUNTIF($S$38:$AD$51, $B27)/10))*$E27 -> 0.9 | I27: =(1-(COUNTIF($S$52:$AD$65, $B27)/10))*$E27 -> 0.7 | J27: =(1-(COUNTIF($S$66:$AD$79, $B27)/10))*$E27 -> 1 | K27: =(1-(COUNTIF($S$80:$AD$93, $B27)/10))*$E27 -> 1 | L27: =SUM(F27:K27)*8 -> 44 | M27: =SUM(F27:K27) *8 -> 44
K29: what does 1,2,3,5 SP mean? | R29: 9
K30: 1- 1-10 | R30: 10 | AJ30: MM
K31: 2 -10-30 | R31: 11
K32: 3 -30-50 | R32: 12
K33: 5 - 50-70 | R33: 13
K34: 8- >70 | O34: =K35*L35*M35 -> 672
K35: 9.6 | L35: 7 | M35: 10
R36: 16
R37: 17
Q38: May | R38: 18
M39: =4.8*8 -> 38.4 | R39: 19
R40: 20 | AD40: VA
R43: 23 | AE43: AJ
R44: 24
R45: 25 | AJ45: MM
R46: 26
R47: 27
L48: Sprint 1 | M48: ='Start Here'!D4 -> 44671 | O48: ='Start Here'!E4 -> 44684
L49: Sprint 2 | M49: ='Start Here'!D5 -> 44685 | O49: ='Start Here'!E5 -> 44698
L50: Sprint 3 | M50: ='Start Here'!D6 -> 44699 | O50: ='Start Here'!E6 -> 44712 | R50: 30
L51: Sprint 4 | M51: ='Start Here'!D7 -> 44713 | O51: ='Start Here'!E7 -> 44726 | R51: 31 | V51: DF | X51: KN | Y51: MN | AA51: VS | AB51: VG | AF51: JB | AP51: VS | AQ51: DF
L52: Sprint 5 | M52: ='Start Here'!D8 -> 44727 | O52: ='Start Here'!E8 -> 44740 | Q52: Jun | R52: 1 | Y52: MN
L53: Sprint 6 | M53: ='Start Here'!D9 -> 44741 | O53: ='Start Here'!E9 -> 44754 | R53: 2 | Y53: MN
R54: 3 | Y54: MN
R57: 6
R58: 7
R59: 8 | AD59: VA
R60: 9 | U60: ASU | AD60: VA
R61: 10 | U61: ASU | AD61: VA
R64: 13
R65: 14
Q66: Jun | R66: 15
R67: 16
R68: 17
R71: 20
R72: 21 | V72: DF | AQ72: DF
R73: 22 | V73: DF | AQ73: DF
R74: 23 | V74: DF | AQ74: DF
R75: 24
R78: 27
R79: 28
Q80: Jun | R80: 29
R81: 30
Q82: Jul | R82: 1
R85: 4 | V85: DF | X85: KN | AA85: VS | AB85: VG | AF85: JB | AP85: VS | AQ85: DF
R86: 5
R87: 6
R88: 7
R89: 8
R92: 11
R93: 12

Sheet ResourceAllocationByPriority
A1: Core | I1: PI-8 Samurai Work Items - Boards (azure.com)
I2: Resource | J2: Story points total till 7/12 | L2: Product description | M2: Product Release | N2: Priority # | P2: Samurai Resource | Q2: Available Hours: Pulled from Resource Planning till 7/12 DO NOT EDIT
D3: NinJa Sprint | E3: Sprint DevOps | F3: Sprint PI | I3: Abhijith Jayakumar | J3: =VLOOKUP($I3, 'Resource Planning'!$C$3:$M$13, 11, FALSE) -> 46.4 | P3: Abdul Naik | Q3: =VLOOKUP($P3, 'Resource Planning'!$C$16:$M$27, 11, FALSE) -> 44
D4: 59 | E4: 98 | F4: 1 | I4: Jagadeesan Balasubramanian | J4: =VLOOKUP($I4, 'Resource Planning'!$C$3:$M$13, 11, FALSE) -> 46.4 | L4: BAU | M4: PROOF | N4: 1 | P4: Anoop Mohan | Q4: =VLOOKUP($P4, 'Resource Planning'!$C$16:$M$27, 11, FALSE) -> 44
D5: 60 | E5: 99 | F5: 2 | I5: Krishna chandar kandula | J5: =VLOOKUP($I5, 'Resource Planning'!$C$3:$M$13, 11, FALSE) -> 47.2 | L5: BAU | M5: GRID | N5: 1 | P5: Aravind Syama Unni | Q5: =VLOOKUP($P5, 'Resource Planning'!$C$16:$M$27, 11, FALSE) -> 45.6
D6: 61 | E6: 100 | F6: 3 | I6: Krishnaraj Nagaraj | J6: =VLOOKUP($I6, 'Resource Planning'!$C$3:$M$13, 11, FALSE) -> 43.2 | L6: BAU | M6: DOS | N6: 1 | P6: Dana Fillhart | Q6: =VLOOKUP($P6, 'Resource Planning'!$C$16:$M$27, 11, FALSE) -> 26.4
D7: 62 | E7: 101 | F7: 4 | I7: Lokeshwaran Sankar | J7: =VLOOKUP($I7, 'Resource Planning'!$C$3:$M$13, 11, FALSE) -> 47.2 | L7: BAU | M7: IDC | N7: 1 | P7: Johnson Robin | Q7: =VLOOKUP($P7, 'Resource Planning'!$C$16:$M$27, 11, FALSE) -> 46.4
D8: 63 | E8: 102 | F8: 5 | I8: Manoj Madhavan | J8: =VLOOKUP($I8, 'Resource Planning'!$C$3:$M$13, 11, FALSE) -> 44 | M8: ADJ | N8: 1 | P8: Krishnaraj Nagarajan | Q8: =VLOOKUP($P8, 'Resource Planning'!$C$16:$M$27, 11, FALSE) -> 4.64
D9: 64 | E9: 103 | F9: 6 | I9: Meraj Husen Ansari | J9: =VLOOKUP($I9, 'Resource Planning'!$C$3:$M$13, 11, FALSE) -> 47.2 | M9: Databricks Optimization | N9: 2 | P9: Mala Nadar | Q9: =VLOOKUP($P9, 'Resource Planning'!$C$16:$M$27, 11, FALSE) -> 44
I10: Prasob Nambuthodiyil | J10: =VLOOKUP($I10, 'Resource Planning'!$C$3:$M$13, 11, FALSE) -> 46.4 | M10: IDC2 | N10: 2.1 | P10: Rahul Bishnoi | Q10: =VLOOKUP($P10, 'Resource Planning'!$C$16:$M$27, 11, FALSE) -> 44.8
I11: Samba siva rao prudhivi | J11: =VLOOKUP($I11, 'Resource Planning'!$C$3:$M$13, 11, FALSE) -> 47.2 | M11: GDV | N11: 2.1 | P11: Varun Sundar | Q11: =VLOOKUP($P11, 'Resource Planning'!$C$16:$M$27, 11, FALSE) -> 37.12
I12: Shibu Swaminathan (repl) | J12: =VLOOKUP($I12, 'Resource Planning'!$C$3:$M$13, 11, FALSE) -> 47.2 | M12: DOS RESI | N12: 2.1 | P12: Vilasini Ganesan | Q12: =VLOOKUP($P12, 'Resource Planning'!$C$16:$M$27, 11, FALSE) -> 46.4
I13: Swapna Madhu (Bishva) | J13: =VLOOKUP($I13, 'Resource Planning'!$C$3:$M$13, 11, FALSE) -> #N/A | M13: DOS QA Automation | N13: 2.3 | P13: Ashish Chourey | Q13: =VLOOKUP($P13, 'Resource Planning'!$C$16:$M$27, 11, FALSE) -> 46.4
M14: GRID QA Automation | N14: 2.3 | P14: Vijay Amirtharaj | Q14: =VLOOKUP($P14, 'Resource Planning'!$C$16:$M$27, 11, FALSE) -> 44
M15: Rewiring | N15: 3 | P15: UNASSIGNED | Q15: =VLOOKUP($P15, 'Resource Planning'!$C$16:$M$27, 11, FALSE) -> #N/A
M16: Historical Load | N16: 3.1
M17: Future State Data project | N17: 3.2
M18: Release on Demand | N18: 3.3
M19: DOS RE Equity | N19: 3.4
B21: Combined Available story points total till 4/15 | C21: Actual story points total til 4/15
B22: Resource | C22: (Pulled from the Resource Planning tab - DO NOT EDIT) | D22: GDV | E22: GRID | F22: GRIDAdjustments | G22: GRIDTestAutomation | H22: IDC | I22: IDC2 | J22: Rewiring | K22: DOS BAU | L22: MIS Refactoring | M22: ResidentialLoans | N22: DatabricksPlatformOptimization | O22: IDC Rewiring | P22: RE Equity | Q22: Release-on-Demand | R22: TechDebt | S22: Untagged
B23: Abdul Naik | C23: =VLOOKUP($B23, 'Resource Planning'!$C$16:$M$27, 11, FALSE) -> 44
B24: Anoop Mohan | C24: =VLOOKUP($B24, 'Resource Planning'!$C$16:$M$27, 11, FALSE) -> 44
B25: Aravind Syama Unni | C25: =VLOOKUP($B25, 'Resource Planning'!$C$16:$M$27, 11, FALSE) -> 45.6
B26: Dana Fillhart | C26: =VLOOKUP($B26, 'Resource Planning'!$C$16:$M$27, 11, FALSE) -> 26.4
B27: Johnson Robin | C27: =VLOOKUP($B27, 'Resource Planning'!$C$16:$M$27, 11, FALSE) -> 46.4
B28: Krishnaraj Nagarajan | C28: =VLOOKUP($B28, 'Resource Planning'!$C$16:$M$27, 11, FALSE) -> 4.64
B29: Mala Nadar | C29: =VLOOKUP($B29, 'Resource Planning'!$C$16:$M$27, 11, FALSE) -> 44
B30: Rahul Bishnoi | C30: =VLOOKUP($B30, 'Resource Planning'!$C$16:$M$27, 11, FALSE) -> 44.8
B31: Varun Sundar | C31: =VLOOKUP($B31, 'Resource Planning'!$C$16:$M$27, 11, FALSE) -> 37.12
B32: Vilasini Ganesan | C32: =VLOOKUP($B32, 'Resource Planning'!$C$16:$M$27, 11, FALSE) -> 46.4
B33: Ashish Chourey | C33: =VLOOKUP($B33, 'Resource Planning'!$C$16:$M$27, 11, FALSE) -> 46.4
B34: Vijay Amirtharaj | C34: =VLOOKUP($B34, 'Resource Planning'!$C$16:$M$27, 11, FALSE) -> 44
B35: UNASSIGNED | C35: =VLOOKUP($B35, 'Resource Planning'!$C$16:$M$27, 11, FALSE) -> #N/A
AU36: 93,94,95
AU37: lot of work tracking
K38: Tags (Column M) | AU38: Core Data Services
P39: Vilasini/Krishnaraj/Dana to discuss for IDC 2 | S39: (need placeholders for rewiring and GDV) | AU39: Core Data Services\Cloud Services
P40: Core Data Services\Cloud Services | S40: 93,94,95 | W40: 95 | AI40: Krishnaraj to talk to Varun for IDC2 API stories
C41: 0.7 | D41: IDC2 | E41: 93,94 | G41: 0.35 | H41: IDC2 | L41: 93,94 | O41: IDC2 | P41: 0.4 | S41: Core Data Services\Cloud Services | W41: 5% for calls and IDC | AA41: 93,94,95,97 | AE41: 93,94,97 | AI41: 93 | AM41: 93,94,95,97 | AR41: 65 story points | AU41: 154 SP | AY41: 54 Unassigned points
AI42: 0.2 | AJ42: IDC2 | AR42: 93,94,95,96
C43: Abdul Naik | G43: Anoop Mohan | K43: Aravind Syama Unni | O43: Dana Fillhart | S43: Johnson Robin | W43: Krishnaraj Nagarajan | AA43: Mala Nadar | AE43: Rahul Bishnoi | AI43: Varun Sundar | AM43: Vilasini Ganesan | AQ43: Ashish Chourey | AU43: Vijay Amirtharaj | AY43: UNASSIGNED | BD43: Dependency | BE43: Total SP ask | BF43: Total SP assigned | BG43: % complete
B44: Product Releasae | C44: =CONCATENATE("Percentage (", SUM(C$45:C$59)*100, "%)") -> Percentage (30%) | D44: Available | E44: Actual | F44: Diff | G44: =CONCATENATE("Percentage (", SUM(G$45:G$59)*100, "%)") -> Percentage (65%) | H44: Available | I44: Actual | J44: Diff | K44: =CONCATENATE("Percentage (", SUM(K$45:K$59)*100, "%)") -> Percentage (100%) | L44: Available | M44: Actual | N44: Diff | O44: =CONCATENATE("Percentage (", SUM(O$45:O$59)*100, "%)") -> Percentage (60%) | P44: Available | Q44: Actual | R44: Diff | S44: =CONCATENATE("Percentage (", SUM(S$45:S$59)*100, "%)") -> Percentage (100%) | T44: Available | U44: Actual | V44: Diff | W44: =CONCATENATE("Percentage (", SUM(W$45:W$59)*100, "%)") -> Percentage (10%) | X44: Available | Y44: Actual | Z44: Diff | AA44: =CONCATENATE("Percentage (", SUM(AA$45:AA$59)*100, "%)") -> Percentage (100%) | AB44: Available | AC44: Actual | AD44: Diff | AE44: =CONCATENATE("Percentage (", SUM(AE$45:AE$59)*100, "%)") -> Percentage (100%) | AF44: Available | AG44: Actual | AH44: Diff | AI44: =CONCATENATE("Percentage (", SUM(AI$45:AI$59)*100, "%)") -> Percentage (80%) | AJ44: Available | AK44: Actual | AL44: Diff | AM44: =CONCATENATE("Percentage (", SUM(AM$45:AM$59)*100, "%)") -> Percentage (100%) | AN44: Available | AO44: Actual | AP44: Diff | AQ44: =CONCATENATE("Percentage (", SUM(AQ$45:AQ$59)*100, "%)") -> Percentage (100%) | AR44: Available | AS44: Actual | AT44: Diff | AU44: =CONCATENATE("Percentage (", SUM(AU$45:AU$59)*100, "%)") -> Percentage (60%) | AV44: Available | AW44: Actual | AX44: Diff | AY44: Percentage | AZ44: Available | BA44: Actual | BB44: Diff
A45: C o r e D a t a S e r v I c e s (S a m u r a I s) | B45: =M4 -> PROOF | C45: 0 | D45: =VLOOKUP($C$43, $P$3:$Q$15, 2, FALSE)*C45 -> 0 | E45: 0 | F45: =D45-E45 -> 0 | G45: 0 | H45: =VLOOKUP($C$43, $P$3:$Q$15, 2, FALSE)*G45 -> 0 | I45: 0 | J45: =H45-I45 -> 0 | K45: 0 | L45: =VLOOKUP($C$43, $P$3:$Q$15, 2, FALSE)*K45 -> 0 | M45: 0 | N45: =L45-M45 -> 0 | O45: 0 | P45: =VLOOKUP($C$43, $P$3:$Q$15, 2, FALSE)*O45 -> 0 | Q45: 0 | R45: =P45-Q45 -> 0 | S45: 0 | T45: =VLOOKUP($C$43, $P$3:$Q$15, 2, FALSE)*S45 -> 0 | U45: 0 | V45: =T45-U45 -> 0 | W45: 0 | X45: =VLOOKUP($C$43, $P$3:$Q$15, 2, FALSE)*W45 -> 0 | Y45: =VLOOKUP($W$43,$B$22:$S$35,A73,FALSE) -> 0 | Z45: =X45-Y45 -> 0 | AA45: 0 | AB45: =VLOOKUP($C$43, $P$3:$Q$15, 2, FALSE)*AA45 -> 0 | AC45: =VLOOKUP($AA$43,$B$22:$S$35,A73,FALSE) -> 0 | AD45: =AB45-AC45 -> 0 | AE45: 0 | AF45: =VLOOKUP($C$43, $P$3:$Q$15, 2, FALSE)*AE45 -> 0 | AG45: 0 | AH45: =AF45-AG45 -> 0 | AI45: 0 | AJ45: =VLOOKUP($C$43, $P$3:$Q$15, 2, FALSE)*AI45 -> 0 | AK45: =VLOOKUP($AI$43,$B$22:$S$35,A73,FALSE) -> 0 | AL45: =AJ45-AK45 -> 0 | AM45: 0 | AN45: =VLOOKUP($C$43, $P$3:$Q$15, 2, FALSE)*AM45 -> 0 | AO45: =VLOOKUP($AM$43,$B$22:$S$35,A73,FALSE) -> 0 | AP45: =AN45-AO45 -> 0 | AQ45: 0 | AR45: =VLOOKUP($C$43, $P$3:$Q$15, 2, FALSE)*AQ45 -> 0 | AS45: =VLOOKUP($AQ$43,$B$22:$S$35,A73,FALSE) -> 0 | AT45: =AR45-AS45 -> 0 | AU45: 0 | AV45: =VLOOKUP($C$43, $P$3:$Q$15, 2, FALSE)*AU45 -> 0 | AW45: =VLOOKUP($AU$43,$B$22:$S$35,A73,FALSE) -> 0 | AX45: =AV45-AW45 -> 0 | AY45: 0 | AZ45: 0 | BA45: =VLOOKUP($AY$43,$B$22:$S$35,A73,FALSE) -> 0 | BB45: =AZ45-BA45 -> 0 | BC45: =SUM(F45,J45,N45,R45,V45,Z45,AD45,AH45,AL45,AP45,AT45,AX45,BB45) -> 0 | BD45: VG , need scope and story
B46: =M5 -> GRID | C46: 0.1 | D46: =VLOOKUP($C$43, $P$3:$Q$15, 2, FALSE)*C46 -> 4.4 | E46: 0 | F46: =D46-E46 -> 4.4 | G46: 0.15 | H46: =VLOOKUP($C$43, $P$3:$Q$15, 2, FALSE)*G46 -> 6.6 | I46: 0 | J46: =H46-I46 -> 6.6 | K46: 0.15 | L46: =VLOOKUP($C$43, $P$3:$Q$15, 2, FALSE)*K46 -> 6.6 | M46: 0 | N46: =L46-M46 -> 6.6 | O46: 0 | P46: =VLOOKUP($C$43, $P$3:$Q$15, 2, FALSE)*O46 -> 0 | Q46: 0 | R46: =P46-Q46 -> 0 | S46: 0.1 | T46: =VLOOKUP($C$43, $P$3:$Q$15, 2, FALSE)*S46 -> 4.4 | U46: 0 | V46: =T46-U46 -> 4.4 | W46: 0 | X46: =VLOOKUP($C$43, $P$3:$Q$15, 2, FALSE)*W46 -> 0 | Y46: =VLOOKUP($W$43,$B$22:$S$35,A74,FALSE) -> 0 | Z46: =X46-Y46 -> 0 | AA46: 0.1 | AB46: =VLOOKUP($C$43, $P$3:$Q$15, 2, FALSE)*AA46 -> 4.4 | AC46: =VLOOKUP($AA$43,$B$22:$S$35,A74,FALSE) -> 0 | AD46: =AB46-AC46 -> 4.4 | AE46: 0.2 | AF46: =VLOOKUP($C$43, $P$3:$Q$15, 2, FALSE)*AE46 -> 8.8 | AG46: 0 | AH46: =AF46-AG46 -> 8.8 | AI46: 0.15 | AJ46: =VLOOKUP($C$43, $P$3:$Q$15, 2, FALSE)*AI46 -> 6.6 | AK46: =VLOOKUP($AI$43,$B$22:$S$35,A74,FALSE) -> 0 | AL46: =AJ46-AK46 -> 6.6 | AM46: 0.15 | AN46: =VLOOKUP($C$43, $P$3:$Q$15, 2, FALSE)*AM46 -> 6.6 | AO46: =VLOOKUP($AM$43,$B$22:$S$35,A74,FALSE) -> 0 | AP46: =AN46-AO46 -> 6.6 | AQ46: 0.3 | AR46: =VLOOKUP($C$43, $P$3:$Q$15, 2, FALSE)*AQ46 -> 13.2 | AS46: =VLOOKUP($AQ$43,$B$22:$S$35,A74,FALSE) -> 0 | AT46: =AR46-AS46 -> 13.2 | AU46: 0.3 | AV46: =VLOOKUP($C$43, $P$3:$Q$15, 2, FALSE)*AU46 -> 13.2 | AW46: =VLOOKUP($AU$43,$B$22:$S$35,A74,FALSE) -> 0 | AX46: =AV46-AW46 -> 13.2 | AY46: 0 | AZ46: 0 | BA46: =VLOOKUP($AY$43,$B$22:$S$35,A74,FALSE) -> 0 | BB46: =AZ46-BA46 -> 0 | BC46: =SUM(F46,J46,N46,R46,V46,Z46,AD46,AH46,AL46,AP46,AT46,AX46,BB46) -> 74.8
B47: =M6 -> DOS | C47: 0 | D47: =VLOOKUP($C$43, $P$3:$Q$15, 2, FALSE)*C47 -> 0 | E47: 0 | F47: =D47-E47 -> 0 | G47: 0 | H47: =VLOOKUP($C$43, $P$3:$Q$15, 2, FALSE)*G47 -> 0 | I47: 0 | J47: =H47-I47 -> 0 | K47: 0.3 | L47: =VLOOKUP($C$43, $P$3:$Q$15, 2, FALSE)*K47 -> 13.2 | M47: 0 | N47: =L47-M47 -> 13.2 | O47: 0.1 | P47: =VLOOKUP($C$43, $P$3:$Q$15, 2, FALSE)*O47 -> 4.4 | Q47: 0 | R47: =P47-Q47 -> 4.4 | S47: 0.2 | T47: =VLOOKUP($C$43, $P$3:$Q$15, 2, FALSE)*S47 -> 8.8 | U47: 0 | V47: =T47-U47 -> 8.8 | W47: 0.05 | X47: =VLOOKUP($C$43, $P$3:$Q$15, 2, FALSE)*W47 -> 2.2 | Y47: =VLOOKUP($W$43,$B$22:$S$35,A75,FALSE) -> 0 | Z47: =X47-Y47 -> 2.2 | AA47: 0.1 | AB47: =VLOOKUP($C$43, $P$3:$Q$15, 2, FALSE)*AA47 -> 4.4 | AC47: =VLOOKUP($AA$43,$B$22:$S$35,A75,FALSE) -> 0 | AD47: =AB47-AC47 -> 4.4 | AE47: 0 | AF47: =VLOOKUP($C$43, $P$3:$Q$15, 2, FALSE)*AE47 -> 0 | AG47: 0 | AH47: =AF47-AG47 -> 0 | AI47: 0 | AJ47: =VLOOKUP($C$43, $P$3:$Q$15, 2, FALSE)*AI47 -> 0 | AK47: =VLOOKUP($AI$43,$B$22:$S$35,A75,FALSE) -> 0 | AL47: =AJ47-AK47 -> 0 | AM47: 0 | AN47: =VLOOKUP($C$43, $P$3:$Q$15, 2, FALSE)*AM47 -> 0 | AO47: =VLOOKUP($AM$43,$B$22:$S$35,A75,FALSE) -> 0 | AP47: =AN47-AO47 -> 0 | AQ47: 0.1 | AR47: =VLOOKUP($C$43, $P$3:$Q$15, 2, FALSE)*AQ47 -> 4.4 | AS47: =VLOOKUP($AQ$43,$B$22:$S$35,A75,FALSE) -> 0 | AT47: =AR47-AS47 -> 4.4 | AU47: 0 | AV47: =VLOOKUP($C$43, $P$3:$Q$15, 2, FALSE)*AU47 -> 0 | AW47: =VLOOKUP($AU$43,$B$22:$S$35,A75,FALSE) -> 0 | AX47: =AV47-AW47 -> 0 | AY47: 0 | AZ47: 0 | BA47: =VLOOKUP($AY$43,$B$22:$S$35,A75,FALSE) -> 0 | BB47: =AZ47-BA47 -> 0 | BC47: =SUM(F47,J47,N47,R47,V47,Z47,AD47,AH47,AL47,AP47,AT47,AX47,BB47) -> 37.4
B48: =M7 -> IDC | C48: 0.2 | D48: =VLOOKUP($C$43, $P$3:$Q$15, 2, FALSE)*C48 -> 8.8 | E48: 0 | F48: =D48-E48 -> 8.8 | G48: 0.1 | H48: =VLOOKUP($C$43, $P$3:$Q$15, 2, FALSE)*G48 -> 4.4 | I48: 0 | J48: =H48-I48 -> 4.4 | K48: 0.2 | L48: =VLOOKUP($C$43, $P$3:$Q$15, 2, FALSE)*K48 -> 8.8 | M48: 0 | N48: =L48-M48 -> 8.8 | O48: 0 | P48: =VLOOKUP($C$43, $P$3:$Q$15, 2, FALSE)*O48 -> 0 | Q48: 0 | R48: =P48-Q48 -> 0 | S48: 0 | T48: =VLOOKUP($C$43, $P$3:$Q$15, 2, FALSE)*S48 -> 0 | U48: 0 | V48: =T48-U48 -> 0 | W48: 0.05 | X48: =VLOOKUP($C$43, $P$3:$Q$15, 2, FALSE)*W48 -> 2.2 | Y48: =VLOOKUP($W$43,$B$22:$S$35,A76,FALSE) -> 0 | Z48: =X48-Y48 -> 2.2 | AA48: 0.4 | AB48: =VLOOKUP($C$43, $P$3:$Q$15, 2, FALSE)*AA48 -> 17.6 | AC48: =VLOOKUP($AA$43,$B$22:$S$35,A76,FALSE) -> 0 | AD48: =AB48-AC48 -> 17.6 | AE48: 0.3 | AF48: =VLOOKUP($C$43, $P$3:$Q$15, 2, FALSE)*AE48 -> 13.2 | AG48: 0 | AH48: =AF48-AG48 -> 13.2 | AI48: 0 | AJ48: =VLOOKUP($C$43, $P$3:$Q$15, 2, FALSE)*AI48 -> 0 | AK48: =VLOOKUP($AI$43,$B$22:$S$35,A76,FALSE) -> 0 | AL48: =AJ48-AK48 -> 0 | AM48: 0.25 | AN48: =VLOOKUP($C$43, $P$3:$Q$15, 2, FALSE)*AM48 -> 11 | AO48: =VLOOKUP($AM$43,$B$22:$S$35,A76,FALSE) -> 0 | AP48: =AN48-AO48 -> 11 | AQ48: 0.2 | AR48: =VLOOKUP($C$43, $P$3:$Q$15, 2, FALSE)*AQ48 -> 8.8 | AS48: =VLOOKUP($AQ$43,$B$22:$S$35,A76,FALSE) -> 0 | AT48: =AR48-AS48 -> 8.8 | AU48: 0 | AV48: =VLOOKUP($C$43, $P$3:$Q$15, 2, FALSE)*AU48 -> 0 | AW48: =VLOOKUP($AU$43,$B$22:$S$35,A76,FALSE) -> 0 | AX48: =AV48-AW48 -> 0 | AY48: 0 | AZ48: 0 | BA48: =VLOOKUP($AY$43,$B$22:$S$35,A76,FALSE) -> 0 | BB48: =AZ48-BA48 -> 0 | BC48: =SUM(F48,J48,N48,R48,V48,Z48,AD48,AH48,AL48,AP48,AT48,AX48,BB48) -> 74.8
B49: =M8 -> ADJ | C49: 0 | D49: =VLOOKUP($C$43, $P$3:$Q$15, 2, FALSE)*C49 -> 0 | E49: 0 | F49: =D49-E49 -> 0 | G49: 0.1 | H49: =VLOOKUP($C$43, $P$3:$Q$15, 2, FALSE)*G49 -> 4.4 | I49: 0 | J49: =H49-I49 -> 4.4 | K49: 0 | L49: =VLOOKUP($C$43, $P$3:$Q$15, 2, FALSE)*K49 -> 0 | M49: 0 | N49: =L49-M49 -> 0 | O49: 0 | P49: =VLOOKUP($C$43, $P$3:$Q$15, 2, FALSE)*O49 -> 0 | Q49: 0 | R49: =P49-Q49 -> 0 | S49: 0 | T49: =VLOOKUP($C$43, $P$3:$Q$15, 2, FALSE)*S49 -> 0 | U49: 0 | V49: =T49-U49 -> 0 | W49: 0 | X49: =VLOOKUP($C$43, $P$3:$Q$15, 2, FALSE)*W49 -> 0 | Y49: =VLOOKUP($W$43,$B$22:$S$35,A77,FALSE) -> 0 | Z49: =X49-Y49 -> 0 | AA49: 0 | AB49: =VLOOKUP($C$43, $P$3:$Q$15, 2, FALSE)*AA49 -> 0 | AC49: =VLOOKUP($AA$43,$B$22:$S$35,A77,FALSE) -> 0 | AD49: =AB49-AC49 -> 0 | AE49: 0.05 | AF49: =VLOOKUP($C$43, $P$3:$Q$15, 2, FALSE)*AE49 -> 2.2 | AG49: 0 | AH49: =AF49-AG49 -> 2.2 | AI49: 0 | AJ49: =VLOOKUP($C$43, $P$3:$Q$15, 2, FALSE)*AI49 -> 0 | AK49: =VLOOKUP($AI$43,$B$22:$S$35,A77,FALSE) -> 0 | AL49: =AJ49-AK49 -> 0 | AM49: 0.1 | AN49: =VLOOKUP($C$43, $P$3:$Q$15, 2, FALSE)*AM49 -> 4.4 | AO49: =VLOOKUP($AM$43,$B$22:$S$35,A77,FALSE) -> 0 | AP49: =AN49-AO49 -> 4.4 | AQ49: 0.2 | AR49: =VLOOKUP($C$43, $P$3:$Q$15, 2, FALSE)*AQ49 -> 8.8 | AS49: =VLOOKUP($AQ$43,$B$22:$S$35,A77,FALSE) -> 0 | AT49: =AR49-AS49 -> 8.8 | AU49: 0.1 | AV49: =VLOOKUP($C$43, $P$3:$Q$15, 2, FALSE)*AU49 -> 4.4 | AW49: 4 | AX49: =AV49-AW49 -> 0.4 | AY49: 0 | AZ49: 0 | BA49: =VLOOKUP($AY$43,$B$22:$S$35,A77,FALSE) -> 0 | BB49: =AZ49-BA49 -> 0 | BC49: =SUM(F49,J49,N49,R49,V49,Z49,AD49,AH49,AL49,AP49,AT49,AX49,BB49) -> 20.2
B50: =M9 -> Databricks Optimization | C50: 0 | D50: =VLOOKUP($C$43, $P$3:$Q$15, 2, FALSE)*C50 -> 0 | E50: 0 | F50: =D50-E50 -> 0 | G50: 0 | H50: =VLOOKUP($C$43, $P$3:$Q$15, 2, FALSE)*G50 -> 0 | I50: 0 | J50: =H50-I50 -> 0 | K50: 0 | L50: =VLOOKUP($C$43, $P$3:$Q$15, 2, FALSE)*K50 -> 0 | M50: 0 | N50: =L50-M50 -> 0 | O50: 0.1 | P50: =VLOOKUP($C$43, $P$3:$Q$15, 2, FALSE)*O50 -> 4.4 | Q50: 0 | R50: =P50-Q50 -> 4.4 | S50: 0 | T50: =VLOOKUP($C$43, $P$3:$Q$15, 2, FALSE)*S50 -> 0 | U50: 0 | V50: =T50-U50 -> 0 | W50: 0 | X50: =VLOOKUP($C$43, $P$3:$Q$15, 2, FALSE)*W50 -> 0 | Y50: =VLOOKUP($W$43,$B$22:$S$35,A78,FALSE) -> 0 | Z50: =X50-Y50 -> 0 | AA50: 0 | AB50: =VLOOKUP($C$43, $P$3:$Q$15, 2, FALSE)*AA50 -> 0 | AC50: =VLOOKUP($AA$43,$B$22:$S$35,A78,FALSE) -> 0 | AD50: =AB50-AC50 -> 0 | AE50: 0 | AF50: =VLOOKUP($C$43, $P$3:$Q$15, 2, FALSE)*AE50 -> 0 | AG50: 0 | AH50: =AF50-AG50 -> 0 | AI50: 0.5 | AJ50: =VLOOKUP($C$43, $P$3:$Q$15, 2, FALSE)*AI50 -> 22 | AK50: =VLOOKUP($AI$43,$B$22:$S$35,A78,FALSE) -> 0 | AL50: =AJ50-AK50 -> 22 | AM50: 0 | AN50: =VLOOKUP($C$43, $P$3:$Q$15, 2, FALSE)*AM50 -> 0 | AO50: =VLOOKUP($AM$43,$B$22:$S$35,A78,FALSE) -> 0 | AP50: =AN50-AO50 -> 0 | AQ50: 0 | AR50: =VLOOKUP($C$43, $P$3:$Q$15, 2, FALSE)*AQ50 -> 0 | AS50: =VLOOKUP($AQ$43,$B$22:$S$35,A78,FALSE) -> 0 | AT50: =AR50-AS50 -> 0 | AU50: 0 | AV50: =VLOOKUP($C$43, $P$3:$Q$15, 2, FALSE)*AU50 -> 0 | AW50: =VLOOKUP($AU$43,$B$22:$S$35,A78,FALSE) -> 0 | AX50: =AV50-AW50 -> 0 | AY50: 0 | AZ50: 0 | BA50: =VLOOKUP($AY$43,$B$22:$S$35,A78,FALSE) -> 0 | BB50: =AZ50-BA50 -> 0 | BC50: =SUM(F50,J50,N50,R50,V50,Z50,AD50,AH50,AL50,AP50,AT50,AX50,BB50) -> 26.4
B51: =M10 -> IDC2 | C51: 0 | D51: =VLOOKUP($C$43, $P$3:$Q$15, 2, FALSE)*C51 -> 0 | E51: 0 | F51: =D51-E51 -> 0 | G51: 0 | H51: =VLOOKUP($C$43, $P$3:$Q$15, 2, FALSE)*G51 -> 0 | I51: 0 | J51: =H51-I51 -> 0 | K51: 0 | L51: =VLOOKUP($C$43, $P$3:$Q$15, 2, FALSE)*K51 -> 0 | M51: 0 | N51: =L51-M51 -> 0 | O51: 0 | P51: =VLOOKUP($C$43, $P$3:$Q$15, 2, FALSE)*O51 -> 0 | Q51: 0 | R51: =P51-Q51 -> 0 | S51: 0 | T51: =VLOOKUP($C$43, $P$3:$Q$15, 2, FALSE)*S51 -> 0 | U51: 0 | V51: =T51-U51 -> 0 | W51: 0 | X51: =VLOOKUP($C$43, $P$3:$Q$15, 2, FALSE)*W51 -> 0 | Y51: =VLOOKUP($W$43,$B$22:$S$35,A80,FALSE) -> 0 | Z51: =X51-Y51 -> 0 | AA51: 0 | AB51: =VLOOKUP($C$43, $P$3:$Q$15, 2, FALSE)*AA51 -> 0 | AC51: =VLOOKUP($AA$43,$B$22:$S$35,A79,FALSE) -> 0 | AD51: =AB51-AC51 -> 0 | AE51: 0.05 | AF51: =VLOOKUP($C$43, $P$3:$Q$15, 2, FALSE)*AE51 -> 2.2 | AG51: 0 | AH51: =AF51-AG51 -> 2.2 | AI51: 0 | AJ51: =VLOOKUP($C$43, $P$3:$Q$15, 2, FALSE)*AI51 -> 0 | AK51: =VLOOKUP($AI$43,$B$22:$S$35,A79,FALSE) -> 0 | AL51: =AJ51-AK51 -> 0 | AM51: 0.05 | AN51: =VLOOKUP($C$43, $P$3:$Q$15, 2, FALSE)*AM51 -> 2.2 | AO51: =VLOOKUP($AM$43,$B$22:$S$35,A79,FALSE) -> 0 | AP51: =AN51-AO51 -> 2.2 | AQ51: 0 | AR51: =VLOOKUP($C$43, $P$3:$Q$15, 2, FALSE)*AQ51 -> 0 | AS51: =VLOOKUP($AQ$43,$B$22:$S$35,A79,FALSE) -> 0 | AT51: =AR51-AS51 -> 0 | AU51: 0 | AV51: =VLOOKUP($C$43, $P$3:$Q$15, 2, FALSE)*AU51 -> 0 | AW51: 0 | AX51: =AV51-AW51 -> 0 | AY51: 0 | AZ51: 0 | BA51: =VLOOKUP($AY$43,$B$22:$S$35,A80,FALSE) -> 0 | BB51: =AZ51-BA51 -> 0 | BC51: =SUM(F51,J51,N51,R51,V51,Z51,AD51,AH51,AL51,AP51,AT51,AX51,BB51) -> 4.4 | BD51: QA team over allocation in excess of 100, ignore negative capacity. Excluding QA , we have 50+ additional SPs
B52: =M11 -> GDV | C52: 0 | D52: =VLOOKUP($C$43, $P$3:$Q$15, 2, FALSE)*C52 -> 0 | E52: 0 | F52: =D52-E52 -> 0 | G52: 0.3 | H52: =VLOOKUP($C$43, $P$3:$Q$15, 2, FALSE)*G52 -> 13.2 | I52: 0 | J52: =H52-I52 -> 13.2 | K52: 0 | L52: =VLOOKUP($C$43, $P$3:$Q$15, 2, FALSE)*K52 -> 0 | M52: 0 | N52: =L52-M52 -> 0 | O52: 0.1 | P52: =VLOOKUP($C$43, $P$3:$Q$15, 2, FALSE)*O52 -> 4.4 | Q52: 0 | R52: =P52-Q52 -> 4.4 | S52: 0.5 | T52: =VLOOKUP($C$43, $P$3:$Q$15, 2, FALSE)*S52 -> 22 | U52: 0 | V52: =T52-U52 -> 22 | W52: 0 | X52: =VLOOKUP($C$43, $P$3:$Q$15, 2, FALSE)*W52 -> 0 | Y52: =VLOOKUP($W$43,$B$22:$S$35,A81,FALSE) -> 0 | Z52: =X52-Y52 -> 0 | AA52: 0 | AB52: =VLOOKUP($C$43, $P$3:$Q$15, 2, FALSE)*AA52 -> 0 | AC52: =VLOOKUP($AA$43,$B$22:$S$35,A80,FALSE) -> 0 | AD52: =AB52-AC52 -> 0 | AE52: 0.4 | AF52: =VLOOKUP($C$43, $P$3:$Q$15, 2, FALSE)*AE52 -> 17.6 | AG52: 0 | AH52: =AF52-AG52 -> 17.6 | AI52: 0 | AJ52: =VLOOKUP($C$43, $P$3:$Q$15, 2, FALSE)*AI52 -> 0 | AK52: =VLOOKUP($AI$43,$B$22:$S$35,A80,FALSE) -> 0 | AL52: =AJ52-AK52 -> 0 | AM52: 0.25 | AN52: =VLOOKUP($C$43, $P$3:$Q$15, 2, FALSE)*AM52 -> 11 | AO52: =VLOOKUP($AM$43,$B$22:$S$35,A80,FALSE) -> 0 | AP52: =AN52-AO52 -> 11 | AQ52: 0.2 | AR52: =VLOOKUP($C$43, $P$3:$Q$15, 2, FALSE)*AQ52 -> 8.8 | AS52: =VLOOKUP($AQ$43,$B$22:$S$35,A80,FALSE) -> 0 | AT52: =AR52-AS52 -> 8.8 | AU52: 0 | AV52: =VLOOKUP($C$43, $P$3:$Q$15, 2, FALSE)*AU52 -> 0 | AW52: 0 | AX52: =AV52-AW52 -> 0 | AY52: 0 | AZ52: 0 | BA52: =VLOOKUP($AY$43,$B$22:$S$35,A81,FALSE) -> 0 | BB52: =AZ52-BA52 -> 0 | BC52: =SUM(F52,J52,N52,R52,V52,Z52,AD52,AH52,AL52,AP52,AT52,AX52,BB52) -> 77
B53: =M12 -> DOS RESI | C53: 0 | D53: =VLOOKUP($C$43, $P$3:$Q$15, 2, FALSE)*C53 -> 0 | E53: 0 | F53: =D53-E53 -> 0 | G53: 0 | H53: =VLOOKUP($C$43, $P$3:$Q$15, 2, FALSE)*G53 -> 0 | I53: 0 | J53: =H53-I53 -> 0 | K53: 0.05 | L53: =VLOOKUP($C$43, $P$3:$Q$15, 2, FALSE)*K53 -> 2.2 | M53: 0 | N53: =L53-M53 -> 2.2 | O53: 0.05 | P53: =VLOOKUP($C$43, $P$3:$Q$15, 2, FALSE)*O53 -> 2.2 | Q53: 0 | R53: =P53-Q53 -> 2.2 | S53: 0 | T53: =VLOOKUP($C$43, $P$3:$Q$15, 2, FALSE)*S53 -> 0 | U53: 0 | V53: =T53-U53 -> 0 | W53: 0 | X53: =VLOOKUP($C$43, $P$3:$Q$15, 2, FALSE)*W53 -> 0 | Y53: =VLOOKUP($W$43,$B$22:$S$35,A82,FALSE) -> 0 | Z53: =X53-Y53 -> 0 | AA53: 0.1 | AB53: =VLOOKUP($C$43, $P$3:$Q$15, 2, FALSE)*AA53 -> 4.4 | AC53: =VLOOKUP($AA$43,$B$22:$S$35,A81,FALSE) -> 0 | AD53: =AB53-AC53 -> 4.4 | AE53: 0 | AF53: =VLOOKUP($C$43, $P$3:$Q$15, 2, FALSE)*AE53 -> 0 | AG53: 0 | AH53: =AF53-AG53 -> 0 | AI53: 0.05 | AJ53: =VLOOKUP($C$43, $P$3:$Q$15, 2, FALSE)*AI53 -> 2.2 | AK53: =VLOOKUP($AI$43,$B$22:$S$35,A81,FALSE) -> 0 | AL53: =AJ53-AK53 -> 2.2 | AM53: 0 | AN53: =VLOOKUP($C$43, $P$3:$Q$15, 2, FALSE)*AM53 -> 0 | AO53: =VLOOKUP($AM$43,$B$22:$S$35,A81,FALSE) -> 0 | AP53: =AN53-AO53 -> 0 | AQ53: 0 | AR53: =VLOOKUP($C$43, $P$3:$Q$15, 2, FALSE)*AQ53 -> 0 | AS53: =VLOOKUP($AQ$43,$B$22:$S$35,A81,FALSE) -> 0 | AT53: =AR53-AS53 -> 0 | AU53: 0.2 | AV53: =VLOOKUP($C$43, $P$3:$Q$15, 2, FALSE)*AU53 -> 8.8 | AW53: 21 | AX53: =AV53-AW53 -> -12.2 | AY53: 0 | AZ53: 0 | BA53: =VLOOKUP($AY$43,$B$22:$S$35,A82,FALSE) -> 0 | BB53: =AZ53-BA53 -> 0 | BC53: =SUM(F53,J53,N53,R53,V53,Z53,AD53,AH53,AL53,AP53,AT53,AX53,BB53) -> -1.2
B54: =M13 -> DOS QA Automation | C54: 0 | D54: =VLOOKUP($C$43, $P$3:$Q$15, 2, FALSE)*C54 -> 0 | E54: 0 | F54: =D54-E54 -> 0 | G54: 0 | H54: =VLOOKUP($C$43, $P$3:$Q$15, 2, FALSE)*G54 -> 0 | I54: 0 | J54: =H54-I54 -> 0 | K54: 0 | L54: =VLOOKUP($C$43, $P$3:$Q$15, 2, FALSE)*K54 -> 0 | M54: 0 | N54: =L54-M54 -> 0 | O54: 0 | P54: =VLOOKUP($C$43, $P$3:$Q$15, 2, FALSE)*O54 -> 0 | Q54: 0 | R54: =P54-Q54 -> 0 | S54: 0 | T54: =VLOOKUP($C$43, $P$3:$Q$15, 2, FALSE)*S54 -> 0 | U54: 0 | V54: =T54-U54 -> 0 | W54: 0 | X54: =VLOOKUP($C$43, $P$3:$Q$15, 2, FALSE)*W54 -> 0 | Y54: =VLOOKUP($W$43,$B$22:$S$35,A83,FALSE) -> 0 | Z54: =X54-Y54 -> 0 | AA54: 0 | AB54: =VLOOKUP($C$43, $P$3:$Q$15, 2, FALSE)*AA54 -> 0 | AC54: =VLOOKUP($AA$43,$B$22:$S$35,A82,FALSE) -> 0 | AD54: =AB54-AC54 -> 0 | AE54: 0 | AF54: =VLOOKUP($C$43, $P$3:$Q$15, 2, FALSE)*AE54 -> 0 | AG54: 0 | AH54: =AF54-AG54 -> 0 | AI54: 0 | AJ54: =VLOOKUP($C$43, $P$3:$Q$15, 2, FALSE)*AI54 -> 0 | AK54: =VLOOKUP($AI$43,$B$22:$S$35,A82,FALSE) -> 0 | AL54: =AJ54-AK54 -> 0 | AM54: 0 | AN54: =VLOOKUP($C$43, $P$3:$Q$15, 2, FALSE)*AM54 -> 0 | AO54: =VLOOKUP($AM$43,$B$22:$S$35,A82,FALSE) -> 0 | AP54: =AN54-AO54 -> 0 | AQ54: 0 | AR54: =VLOOKUP($C$43, $P$3:$Q$15, 2, FALSE)*AQ54 -> 0 | AS54: =VLOOKUP($AQ$43,$B$22:$S$35,A82,FALSE) -> 0 | AT54: =AR54-AS54 -> 0 | AU54: 0 | AV54: =VLOOKUP($C$43, $P$3:$Q$15, 2, FALSE)*AU54 -> 0 | AW54: 0 | AX54: =AV54-AW54 -> 0 | AY54: 0 | AZ54: 0 | BA54: =VLOOKUP($AY$43,$B$22:$S$35,A83,FALSE) -> 0 | BB54: =AZ54-BA54 -> 0 | BC54: =SUM(F54,J54,N54,R54,V54,Z54,AD54,AH54,AL54,AP54,AT54,AX54,BB54) -> 0 | BD54: Varun/Dana, Create stories to support the buffer
B55: =M14 -> GRID QA Automation | C55: 0 | D55: =VLOOKUP($C$43, $P$3:$Q$15, 2, FALSE)*C55 -> 0 | E55: 0 | F55: =D55-E55 -> 0 | G55: 0 | H55: =VLOOKUP($C$43, $P$3:$Q$15, 2, FALSE)*G55 -> 0 | I55: 0 | J55: =H55-I55 -> 0 | K55: 0 | L55: =VLOOKUP($C$43, $P$3:$Q$15, 2, FALSE)*K55 -> 0 | M55: 0 | N55: =L55-M55 -> 0 | O55: 0.1 | P55: =VLOOKUP($C$43, $P$3:$Q$15, 2, FALSE)*O55 -> 4.4 | Q55: 0 | R55: =P55-Q55 -> 4.4 | S55: 0 | T55: =VLOOKUP($C$43, $P$3:$Q$15, 2, FALSE)*S55 -> 0 | U55: 0 | V55: =T55-U55 -> 0 | W55: 0 | X55: =VLOOKUP($C$43, $P$3:$Q$15, 2, FALSE)*W55 -> 0 | Y55: =VLOOKUP($W$43,$B$22:$S$35,A84,FALSE) -> 0 | Z55: =X55-Y55 -> 0 | AA55: 0 | AB55: =VLOOKUP($C$43, $P$3:$Q$15, 2, FALSE)*AA55 -> 0 | AC55: =VLOOKUP($AA$43,$B$22:$S$35,A83,FALSE) -> 0 | AD55: =AB55-AC55 -> 0 | AE55: 0 | AF55: =VLOOKUP($C$43, $P$3:$Q$15, 2, FALSE)*AE55 -> 0 | AG55: 0 | AH55: =AF55-AG55 -> 0 | AI55: 0 | AJ55: =VLOOKUP($C$43, $P$3:$Q$15, 2, FALSE)*AI55 -> 0 | AK55: =VLOOKUP($AI$43,$B$22:$S$35,A83,FALSE) -> 0 | AL55: =AJ55-AK55 -> 0 | AM55: 0 | AN55: =VLOOKUP($C$43, $P$3:$Q$15, 2, FALSE)*AM55 -> 0 | AO55: =VLOOKUP($AM$43,$B$22:$S$35,A83,FALSE) -> 0 | AP55: =AN55-AO55 -> 0 | AQ55: 0 | AR55: =VLOOKUP($C$43, $P$3:$Q$15, 2, FALSE)*AQ55 -> 0 | AS55: =VLOOKUP($AQ$43,$B$22:$S$35,A83,FALSE) -> 0 | AT55: =AR55-AS55 -> 0 | AU55: 0 | AV55: =VLOOKUP($C$43, $P$3:$Q$15, 2, FALSE)*AU55 -> 0 | AW55: 0 | AX55: =AV55-AW55 -> 0 | AY55: 0 | AZ55: 0 | BA55: =VLOOKUP($AY$43,$B$22:$S$35,A84,FALSE) -> 0 | BB55: =AZ55-BA55 -> 0 | BC55: =SUM(F55,J55,N55,R55,V55,Z55,AD55,AH55,AL55,AP55,AT55,AX55,BB55) -> 4.4 | BD55: VG , need scope and story
B56: =M15 -> Rewiring | C56: 0 | D56: =VLOOKUP($C$43, $P$3:$Q$15, 2, FALSE)*C56 -> 0 | E56: 0 | F56: =D56-E56 -> 0 | G56: 0 | H56: =VLOOKUP($C$43, $P$3:$Q$15, 2, FALSE)*G56 -> 0 | I56: 0 | J56: =H56-I56 -> 0 | K56: 0.1 | L56: =VLOOKUP($C$43, $P$3:$Q$15, 2, FALSE)*K56 -> 4.4 | M56: 0 | N56: =L56-M56 -> 4.4 | O56: 0.05 | P56: =VLOOKUP($C$43, $P$3:$Q$15, 2, FALSE)*O56 -> 2.2 | Q56: 0 | R56: =P56-Q56 -> 2.2 | S56: 0.1 | T56: =VLOOKUP($C$43, $P$3:$Q$15, 2, FALSE)*S56 -> 4.4 | U56: 0 | V56: =T56-U56 -> 4.4 | W56: 0 | X56: =VLOOKUP($C$43, $P$3:$Q$15, 2, FALSE)*W56 -> 0 | Y56: =VLOOKUP($W$43,$B$22:$S$35,A85,FALSE) -> 0 | Z56: =X56-Y56 -> 0 | AA56: 0.1 | AB56: =VLOOKUP($C$43, $P$3:$Q$15, 2, FALSE)*AA56 -> 4.4 | AC56: =VLOOKUP($AA$43,$B$22:$S$35,A84,FALSE) -> 0 | AD56: =AB56-AC56 -> 4.4 | AE56: 0 | AF56: =VLOOKUP($C$43, $P$3:$Q$15, 2, FALSE)*AE56 -> 0 | AG56: 0 | AH56: =AF56-AG56 -> 0 | AI56: 0 | AJ56: =VLOOKUP($C$43, $P$3:$Q$15, 2, FALSE)*AI56 -> 0 | AK56: =VLOOKUP($AI$43,$B$22:$S$35,A84,FALSE) -> 0 | AL56: =AJ56-AK56 -> 0 | AM56: 0.1 | AN56: =VLOOKUP($C$43, $P$3:$Q$15, 2, FALSE)*AM56 -> 4.4 | AO56: =VLOOKUP($AM$43,$B$22:$S$35,A84,FALSE) -> 0 | AP56: =AN56-AO56 -> 4.4 | AQ56: 0 | AR56: =VLOOKUP($C$43, $P$3:$Q$15, 2, FALSE)*AQ56 -> 0 | AS56: =VLOOKUP($AQ$43,$B$22:$S$35,A84,FALSE) -> 0 | AT56: =AR56-AS56 -> 0 | AU56: 0 | AV56: =VLOOKUP($C$43, $P$3:$Q$15, 2, FALSE)*AU56 -> 0 | AW56: 0 | AX56: =AV56-AW56 -> 0 | AY56: 0 | AZ56: 0 | BA56: =VLOOKUP($AY$43,$B$22:$S$35,A85,FALSE) -> 0 | BB56: =AZ56-BA56 -> 0 | BC56: =SUM(F56,J56,N56,R56,V56,Z56,AD56,AH56,AL56,AP56,AT56,AX56,BB56) -> 19.8
B57: =M16 -> Historical Load | C57: 0 | D57: =VLOOKUP($C$43, $P$3:$Q$15, 2, FALSE)*C57 -> 0 | E57: 0 | F57: =D57-E57 -> 0 | G57: 0 | H57: =VLOOKUP($C$43, $P$3:$Q$15, 2, FALSE)*G57 -> 0 | I57: 0 | J57: =H57-I57 -> 0 | K57: 0 | L57: =VLOOKUP($C$43, $P$3:$Q$15, 2, FALSE)*K57 -> 0 | M57: 0 | N57: =L57-M57 -> 0 | O57: 0 | P57: =VLOOKUP($C$43, $P$3:$Q$15, 2, FALSE)*O57 -> 0 | Q57: 0 | R57: =P57-Q57 -> 0 | S57: 0 | T57: =VLOOKUP($C$43, $P$3:$Q$15, 2, FALSE)*S57 -> 0 | U57: 0 | V57: =T57-U57 -> 0 | W57: 0 | X57: =VLOOKUP($C$43, $P$3:$Q$15, 2, FALSE)*W57 -> 0 | Y57: =VLOOKUP($W$43,$B$22:$S$35,A86,FALSE) -> 0 | Z57: =X57-Y57 -> 0 | AA57: 0.1 | AB57: =VLOOKUP($C$43, $P$3:$Q$15, 2, FALSE)*AA57 -> 4.4 | AC57: =VLOOKUP($AA$43,$B$22:$S$35,A85,FALSE) -> 0 | AD57: =AB57-AC57 -> 4.4 | AE57: 0 | AF57: =VLOOKUP($C$43, $P$3:$Q$15, 2, FALSE)*AE57 -> 0 | AG57: 0 | AH57: =AF57-AG57 -> 0 | AI57: 0 | AJ57: =VLOOKUP($C$43, $P$3:$Q$15, 2, FALSE)*AI57 -> 0 | AK57: =VLOOKUP($AI$43,$B$22:$S$35,A85,FALSE) -> 0 | AL57: =AJ57-AK57 -> 0 | AM57: 0.1 | AN57: =VLOOKUP($C$43, $P$3:$Q$15, 2, FALSE)*AM57 -> 4.4 | AO57: =VLOOKUP($AM$43,$B$22:$S$35,A85,FALSE) -> 0 | AP57: =AN57-AO57 -> 4.4 | AQ57: 0 | AR57: =VLOOKUP($C$43, $P$3:$Q$15, 2, FALSE)*AQ57 -> 0 | AS57: =VLOOKUP($AQ$43,$B$22:$S$35,A85,FALSE) -> 0 | AT57: =AR57-AS57 -> 0 | AU57: 0 | AV57: =VLOOKUP($C$43, $P$3:$Q$15, 2, FALSE)*AU57 -> 0 | AW57: 0 | AX57: =AV57-AW57 -> 0 | AY57: 0 | AZ57: 0 | BA57: =VLOOKUP($AY$43,$B$22:$S$35,A86,FALSE) -> 0 | BB57: =AZ57-BA57 -> 0 | BC57: =SUM(F57,J57,N57,R57,V57,Z57,AD57,AH57,AL57,AP57,AT57,AX57,BB57) -> 8.8
B58: =M17 -> Future State Data project | C58: 0 | D58: =VLOOKUP($C$43, $P$3:$Q$15, 2, FALSE)*C58 -> 0 | E58: 0 | F58: =D58-E58 -> 0 | G58: 0 | H58: =VLOOKUP($C$43, $P$3:$Q$15, 2, FALSE)*G58 -> 0 | I58: 0 | J58: =H58-I58 -> 0 | K58: 0.2 | L58: =VLOOKUP($C$43, $P$3:$Q$15, 2, FALSE)*K58 -> 8.8 | M58: 0 | N58: =L58-M58 -> 8.8 | O58: 0.05 | P58: =VLOOKUP($C$43, $P$3:$Q$15, 2, FALSE)*O58 -> 2.2 | Q58: 0 | R58: =P58-Q58 -> 2.2 | S58: 0.1 | T58: =VLOOKUP($C$43, $P$3:$Q$15, 2, FALSE)*S58 -> 4.4 | U58: 0 | V58: =T58-U58 -> 4.4 | W58: 0 | X58: =VLOOKUP($C$43, $P$3:$Q$15, 2, FALSE)*W58 -> 0 | Y58: =VLOOKUP($W$43,$B$22:$S$35,A87,FALSE) -> 0 | Z58: =X58-Y58 -> 0 | AA58: 0.1 | AB58: =VLOOKUP($C$43, $P$3:$Q$15, 2, FALSE)*AA58 -> 4.4 | AC58: =VLOOKUP($AA$43,$B$22:$S$35,A86,FALSE) -> 0 | AD58: =AB58-AC58 -> 4.4 | AE58: 0 | AF58: =VLOOKUP($C$43, $P$3:$Q$15, 2, FALSE)*AE58 -> 0 | AG58: 0 | AH58: =AF58-AG58 -> 0 | AI58: 0.1 | AJ58: =VLOOKUP($C$43, $P$3:$Q$15, 2, FALSE)*AI58 -> 4.4 | AK58: =VLOOKUP($AI$43,$B$22:$S$35,A86,FALSE) -> 0 | AL58: =AJ58-AK58 -> 4.4 | AM58: 0 | AN58: =VLOOKUP($C$43, $P$3:$Q$15, 2, FALSE)*AM58 -> 0 | AO58: =VLOOKUP($AM$43,$B$22:$S$35,A86,FALSE) -> 0 | AP58: =AN58-AO58 -> 0 | AQ58: 0 | AR58: =VLOOKUP($C$43, $P$3:$Q$15, 2, FALSE)*AQ58 -> 0 | AS58: =VLOOKUP($AQ$43,$B$22:$S$35,A86,FALSE) -> 0 | AT58: =AR58-AS58 -> 0 | AU58: 0 | AV58: =VLOOKUP($C$43, $P$3:$Q$15, 2, FALSE)*AU58 -> 0 | AW58: 0 | AX58: =AV58-AW58 -> 0 | AY58: 0 | AZ58: 0 | BA58: =VLOOKUP($AY$43,$B$22:$S$35,A87,FALSE) -> 0 | BB58: =AZ58-BA58 -> 0 | BC58: =SUM(F58,J58,N58,R58,V58,Z58,AD58,AH58,AL58,AP58,AT58,AX58,BB58) -> 24.2
B59: =M18 -> Release on Demand | C59: 0 | D59: =VLOOKUP($C$43, $P$3:$Q$15, 2, FALSE)*C59 -> 0 | E59: 0 | F59: =D59-E59 -> 0 | G59: 0 | H59: =VLOOKUP($C$43, $P$3:$Q$15, 2, FALSE)*G59 -> 0 | I59: 0 | J59: =H59-I59 -> 0 | K59: 0 | L59: =VLOOKUP($C$43, $P$3:$Q$15, 2, FALSE)*K59 -> 0 | M59: 0 | N59: =L59-M59 -> 0 | O59: 0.05 | P59: =VLOOKUP($C$43, $P$3:$Q$15, 2, FALSE)*O59 -> 2.2 | Q59: 0 | R59: =P59-Q59 -> 2.2 | S59: 0 | T59: =VLOOKUP($C$43, $P$3:$Q$15, 2, FALSE)*S59 -> 0 | U59: 0 | V59: =T59-U59 -> 0 | W59: 0 | X59: =VLOOKUP($C$43, $P$3:$Q$15, 2, FALSE)*W59 -> 0 | Y59: =VLOOKUP($W$43,$B$22:$S$35,A88,FALSE) -> 0 | Z59: =X59-Y59 -> 0 | AA59: 0 | AB59: =VLOOKUP($C$43, $P$3:$Q$15, 2, FALSE)*AA59 -> 0 | AC59: =VLOOKUP($AA$43,$B$22:$S$35,A87,FALSE) -> 0 | AD59: =AB59-AC59 -> 0 | AE59: 0 | AF59: =VLOOKUP($C$43, $P$3:$Q$15, 2, FALSE)*AE59 -> 0 | AG59: 0 | AH59: =AF59-AG59 -> 0 | AI59: 0 | AJ59: =VLOOKUP($C$43, $P$3:$Q$15, 2, FALSE)*AI59 -> 0 | AK59: =VLOOKUP($AI$43,$B$22:$S$35,A87,FALSE) -> 0 | AL59: =AJ59-AK59 -> 0 | AM59: 0 | AN59: =VLOOKUP($C$43, $P$3:$Q$15, 2, FALSE)*AM59 -> 0 | AO59: =VLOOKUP($AM$43,$B$22:$S$35,A87,FALSE) -> 0 | AP59: =AN59-AO59 -> 0 | AQ59: 0 | AR59: =VLOOKUP($C$43, $P$3:$Q$15, 2, FALSE)*AQ59 -> 0 | AS59: =VLOOKUP($AQ$43,$B$22:$S$35,A87,FALSE) -> 0 | AT59: =AR59-AS59 -> 0 | AU59: 0 | AV59: =VLOOKUP($C$43, $P$3:$Q$15, 2, FALSE)*AU59 -> 0 | AW59: 0 | AX59: =AV59-AW59 -> 0 | AY59: 0 | AZ59: 0 | BA59: =VLOOKUP($AY$43,$B$22:$S$35,A88,FALSE) -> 0 | BB59: =AZ59-BA59 -> 0 | BC59: =SUM(F59,J59,N59,R59,V59,Z59,AD59,AH59,AL59,AP59,AT59,AX59,BB59) -> 2.2
B60: =M19 -> DOS RE Equity | C60: 0 | D60: =VLOOKUP($C$43, $P$3:$Q$15, 2, FALSE)*C60 -> 0 | E60: 0 | F60: =D60-E60 -> 0 | G60: 0 | H60: =VLOOKUP($C$43, $P$3:$Q$15, 2, FALSE)*G60 -> 0 | I60: 0 | J60: =H60-I60 -> 0 | K60: 0 | L60: =VLOOKUP($C$43, $P$3:$Q$15, 2, FALSE)*K60 -> 0 | M60: 0 | N60: =L60-M60 -> 0 | O60: 0.05 | P60: =VLOOKUP($C$43, $P$3:$Q$15, 2, FALSE)*O60 -> 2.2 | Q60: 0 | R60: =P60-Q60 -> 2.2 | S60: 0 | T60: =VLOOKUP($C$43, $P$3:$Q$15, 2, FALSE)*S60 -> 0 | U60: 0 | V60: =T60-U60 -> 0 | W60: 0 | X60: =VLOOKUP($C$43, $P$3:$Q$15, 2, FALSE)*W60 -> 0 | Y60: =VLOOKUP($W$43,$B$22:$S$35,A89,FALSE) -> #VALUE! | Z60: =X60-Y60 -> #VALUE! | AA60: 0 | AB60: =VLOOKUP($C$43, $P$3:$Q$15, 2, FALSE)*AA60 -> 0 | AC60: =VLOOKUP($AA$43,$B$22:$S$35,A88,FALSE) -> 0 | AD60: =AB60-AC60 -> 0 | AE60: 0 | AF60: =VLOOKUP($C$43, $P$3:$Q$15, 2, FALSE)*AE60 -> 0 | AG60: 0 | AH60: =AF60-AG60 -> 0 | AI60: 0 | AJ60: =VLOOKUP($C$43, $P$3:$Q$15, 2, FALSE)*AI60 -> 0 | AK60: =VLOOKUP($AI$43,$B$22:$S$35,A88,FALSE) -> 0 | AL60: =AJ60-AK60 -> 0 | AM60: 0 | AN60: =VLOOKUP($C$43, $P$3:$Q$15, 2, FALSE)*AM60 -> 0 | AO60: =VLOOKUP($AM$43,$B$22:$S$35,A88,FALSE) -> 0 | AP60: =AN60-AO60 -> 0 | AQ60: 0 | AR60: =VLOOKUP($C$43, $P$3:$Q$15, 2, FALSE)*AQ60 -> 0 | AS60: =VLOOKUP($AQ$43,$B$22:$S$35,A88,FALSE) -> 0 | AT60: =AR60-AS60 -> 0 | AU60: 0 | AV60: =VLOOKUP($C$43, $P$3:$Q$15, 2, FALSE)*AU60 -> 0 | AW60: 0 | AX60: =AV60-AW60 -> 0 | AY60: 0 | AZ60: 0 | BA60: =VLOOKUP($AY$43,$B$22:$S$35,A89,FALSE) -> #VALUE! | BB60: =AZ60-BA60 -> #VALUE! | BC60: =SUM(F60,J60,N60,R60,V60,Z60,AD60,AH60,AL60,AP60,AT60,AX60,BB60) -> #VALUE!
C64: Abhijith Jayakumar | G64: Prasob Nambuthodiyil | K64: Manoj Madhavan | O64: Krishna chandar kandula | S64: Samba siva rao prudhivi | W64: Swapna Madhu | AA64: Jagadeesan Balasubramanian | AE64: Krishnaraj Nagaraj | AI64: Meraj Husen Ansari | AM64: Abdul Naik | AQ64: Anoop Mohan | AU64: Shibu Swaminathan (repl) | AY64: Lokeshwaran Sankar
A65: Shared Services (NINJAs) | B65: Product Releasae | C65: =CONCATENATE("Percentage (", SUM(C$66:C$70)*100, "%)") -> Percentage (100%) | D65: Available | E65: Actual | F65: Diff | G65: =CONCATENATE("Percentage (", SUM(G$66:G$70)*100, "%)") -> Percentage (100%) | H65: Available | I65: Actual | J65: Diff | K65: =CONCATENATE("Percentage (", SUM(K$66:K$70)*100, "%)") -> Percentage (100%) | L65: Available | M65: Actual | N65: Diff | O65: =CONCATENATE("Percentage (", SUM(O$66:O$70)*100, "%)") -> Percentage (100%) | P65: Available | Q65: Actual | R65: Diff | S65: =CONCATENATE("Percentage (", SUM(S$66:S$70)*100, "%)") -> Percentage (100%) | T65: Available | U65: Actual | V65: Diff | W65: =CONCATENATE("Percentage (", SUM(W$66:W$70)*100, "%)") -> Percentage (100%) | X65: Available | Y65: Actual | Z65: Diff | AA65: =CONCATENATE("Percentage (", SUM(AA$66:AA$70)*100, "%)") -> Percentage (100%) | AB65: Available | AC65: Actual | AD65: Diff | AE65: =CONCATENATE("Percentage (", SUM(AE$66:AE$70)*100, "%)") -> Percentage (100%) | AF65: Available | AG65: Actual | AH65: Diff | AI65: =CONCATENATE("Percentage (", SUM(AI$66:AI$70)*100, "%)") -> Percentage (100%) | AJ65: Available | AK65: Actual | AL65: Diff | AM65: =CONCATENATE("Percentage (", SUM(AM$66:AM$70)*100, "%)") -> Percentage (70%) | AN65: Available | AO65: Actual | AP65: Diff | AQ65: =CONCATENATE("Percentage (", SUM(AQ$66:AQ$70)*100, "%)") -> Percentage (35%) | AR65: Available | AS65: Actual | AT65: Diff | AU65: =CONCATENATE("Percentage (", SUM(AU$66:AU$70)*100, "%)") -> Percentage (100%) | AV65: Available | AW65: Actual | AX65: Diff | AY65: Percentage | AZ65: Available | BA65: Actual | BB65: Diff
B66: PROOF BAU | C66: 0.5 | D66: =VLOOKUP($C$64, 'Resource Planning'!$C$3:$M$13, 11, FALSE)*C66 -> 23.2 | F66: =D66-E66 -> 23.2 | G66: 0.3 | H66: =VLOOKUP($G$64, 'Resource Planning'!$C$3:$M$13, 11, FALSE)*G66 -> 13.92 | J66: =H66-I66 -> 13.92 | K66: 0 | L66: =VLOOKUP($K$64, 'Resource Planning'!$C$3:$M$13, 11, FALSE)*K66 -> 0 | N66: =L66-M66 -> 0 | O66: 0 | P66: =VLOOKUP($O$64, 'Resource Planning'!$C$3:$M$13, 11, FALSE)*O66 -> 0 | R66: =P66-Q66 -> 0 | S66: 0 | T66: =VLOOKUP($S$64, 'Resource Planning'!$C$3:$M$13, 11, FALSE)*S66 -> 0 | V66: =T66-U66 -> 0 | W66: 0.2 | X66: =VLOOKUP($W$64, 'Resource Planning'!$C$3:$M$13, 11, FALSE)*W66 -> 9.44 | Z66: =X66-Y66 -> 9.44 | AA66: 0.7 | AB66: =VLOOKUP($AA$64, 'Resource Planning'!$C$3:$M$13, 11, FALSE)*AA66 -> 32.48 | AD66: =AB66-AC66 -> 32.48 | AE66: 0 | AF66: =VLOOKUP($AE$64, 'Resource Planning'!$C$3:$M$13, 11, FALSE)*AE66 -> 0 | AH66: =AF66-AG66 -> 0 | AI66: 0 | AJ66: =VLOOKUP($AI$64, 'Resource Planning'!$C$3:$M$13, 11, FALSE)*AI66 -> 0 | AL66: =AJ66-AK66 -> 0 | AM66: 0 | AN66: =VLOOKUP($AM$64, 'Resource Planning'!$C$16:$M$27, 11, FALSE)*AM66 -> 0 | AP66: =AN66-AO66 -> 0 | AQ66: 0 | AR66: =VLOOKUP($AQ$64, 'Resource Planning'!$C$16:$M$27, 11, FALSE)*AQ66 -> 0 | AT66: =AR66-AS66 -> 0 | AU66: 0.2 | AV66: =VLOOKUP($AU$64, 'Resource Planning'!$C$3:$M$13, 11, FALSE)*AU66 -> 9.44 | AX66: =AV66-AW66 -> 9.44 | AY66: 0.15 | AZ66: =VLOOKUP($AU$64, 'Resource Planning'!$C$3:$M$13, 11, FALSE)*AY66 -> 7.08 | BB66: =AZ66-BA66 -> 7.08 | BC66: =SUM(F66,J66,N66,R66,V66,Z66,AD66,AH66,AL66,AP66,AT66,AX66,BB66) -> 95.56
B67: Adj | C67: 0 | D67: =VLOOKUP($C$64, 'Resource Planning'!$C$3:$M$13, 11, FALSE)*C67 -> 0 | F67: =D67-E67 -> 0 | G67: 0 | H67: =VLOOKUP($G$64, 'Resource Planning'!$C$3:$M$13, 11, FALSE)*G67 -> 0 | J67: =H67-I67 -> 0 | K67: 0.25 | L67: =VLOOKUP($K$64, 'Resource Planning'!$C$3:$M$13, 11, FALSE)*K67 -> 11 | N67: =L67-M67 -> 11 | O67: 0 | P67: =VLOOKUP($O$64, 'Resource Planning'!$C$3:$M$13, 11, FALSE)*O67 -> 0 | R67: =P67-Q67 -> 0 | S67: 0.2 | T67: =VLOOKUP($S$64, 'Resource Planning'!$C$3:$M$13, 11, FALSE)*S67 -> 9.44 | V67: =T67-U67 -> 9.44 | W67: 0 | X67: =VLOOKUP($W$64, 'Resource Planning'!$C$3:$M$13, 11, FALSE)*W67 -> 0 | Z67: =X67-Y67 -> 0 | AA67: 0 | AB67: =VLOOKUP($AA$64, 'Resource Planning'!$C$3:$M$13, 11, FALSE)*AA67 -> 0 | AD67: =AB67-AC67 -> 0 | AE67: 0 | AF67: =VLOOKUP($AE$64, 'Resource Planning'!$C$3:$M$13, 11, FALSE)*AE67 -> 0 | AH67: =AF67-AG67 -> 0 | AI67: 0 | AJ67: =VLOOKUP($AI$64, 'Resource Planning'!$C$3:$M$13, 11, FALSE)*AI67 -> 0 | AL67: =AJ67-AK67 -> 0 | AM67: 0 | AN67: =VLOOKUP($AM$64, 'Resource Planning'!$C$16:$M$27, 11, FALSE)*AM67 -> 0 | AP67: =AN67-AO67 -> 0 | AQ67: 0 | AR67: =VLOOKUP($AQ$64, 'Resource Planning'!$C$16:$M$27, 11, FALSE)*AQ67 -> 0 | AT67: =AR67-AS67 -> 0 | AU67: 0 | AV67: =VLOOKUP($AU$64, 'Resource Planning'!$C$3:$M$13, 11, FALSE)*AU67 -> 0 | AX67: =AV67-AW67 -> 0 | AY67: 0.2 | AZ67: =VLOOKUP($AU$64, 'Resource Planning'!$C$3:$M$13, 11, FALSE)*AY67 -> 9.44 | BB67: =AZ67-BA67 -> 9.44 | BC67: =SUM(F67,J67,N67,R67,V67,Z67,AD67,AH67,AL67,AP67,AT67,AX67,BB67) -> 29.88
B68: IDC | C68: 0.5 | D68: =VLOOKUP($C$64, 'Resource Planning'!$C$3:$M$13, 11, FALSE)*C68 -> 23.2 | F68: =D68-E68 -> 23.2 | G68: 0 | H68: =VLOOKUP($G$64, 'Resource Planning'!$C$3:$M$13, 11, FALSE)*G68 -> 0 | J68: =H68-I68 -> 0 | K68: 0 | L68: =VLOOKUP($K$64, 'Resource Planning'!$C$3:$M$13, 11, FALSE)*K68 -> 0 | N68: =L68-M68 -> 0 | O68: 0 | P68: =VLOOKUP($O$64, 'Resource Planning'!$C$3:$M$13, 11, FALSE)*O68 -> 0 | R68: =P68-Q68 -> 0 | S68: 0 | T68: =VLOOKUP($S$64, 'Resource Planning'!$C$3:$M$13, 11, FALSE)*S68 -> 0 | V68: =T68-U68 -> 0 | W68: 0.2 | X68: =VLOOKUP($W$64, 'Resource Planning'!$C$3:$M$13, 11, FALSE)*W68 -> 9.44 | Z68: =X68-Y68 -> 9.44 | AA68: 0 | AB68: =VLOOKUP($AA$64, 'Resource Planning'!$C$3:$M$13, 11, FALSE)*AA68 -> 0 | AD68: =AB68-AC68 -> 0 | AE68: 0 | AF68: =VLOOKUP($AE$64, 'Resource Planning'!$C$3:$M$13, 11, FALSE)*AE68 -> 0 | AH68: =AF68-AG68 -> 0 | AI68: 0 | AJ68: =VLOOKUP($AI$64, 'Resource Planning'!$C$3:$M$13, 11, FALSE)*AI68 -> 0 | AL68: =AJ68-AK68 -> 0 | AM68: 0 | AN68: =VLOOKUP($AM$64, 'Resource Planning'!$C$16:$M$27, 11, FALSE)*AM68 -> 0 | AP68: =AN68-AO68 -> 0 | AQ68: 0 | AR68: =VLOOKUP($AQ$64, 'Resource Planning'!$C$16:$M$27, 11, FALSE)*AQ68 -> 0 | AT68: =AR68-AS68 -> 0 | AU68: 0 | AV68: =VLOOKUP($AU$64, 'Resource Planning'!$C$3:$M$13, 11, FALSE)*AU68 -> 0 | AX68: =AV68-AW68 -> 0 | AY68: 0.15 | AZ68: =VLOOKUP($AU$64, 'Resource Planning'!$C$3:$M$13, 11, FALSE)*AY68 -> 7.08 | BB68: // | BC68: =SUM(F68,J68,N68,R68,V68,Z68,AD68,AH68,AL68,AP68,AT68,AX68,BB68) -> 32.64
B69: IDC2 | C69: 0 | D69: =VLOOKUP($C$64, 'Resource Planning'!$C$3:$M$13, 11, FALSE)*C69 -> 0 | F69: =D69-E69 -> 0 | G69: 0.7 | H69: =VLOOKUP($G$64, 'Resource Planning'!$C$3:$M$13, 11, FALSE)*G69 -> 32.48 | J69: =H69-I69 -> 32.48 | K69: 0.75 | L69: =VLOOKUP($K$64, 'Resource Planning'!$C$3:$M$13, 11, FALSE)*K69 -> 33 | N69: =L69-M69 -> 33 | O69: 1 | P69: =VLOOKUP($O$64, 'Resource Planning'!$C$3:$M$13, 11, FALSE)*O69 -> 47.2 | R69: =P69-Q69 -> 47.2 | S69: 0.8 | T69: =VLOOKUP($S$64, 'Resource Planning'!$C$3:$M$13, 11, FALSE)*S69 -> 37.76 | V69: =T69-U69 -> 37.76 | W69: 0.6 | X69: =VLOOKUP($W$64, 'Resource Planning'!$C$3:$M$13, 11, FALSE)*W69 -> 28.32 | Z69: =X69-Y69 -> 28.32 | AA69: 0 | AB69: =VLOOKUP($AA$64, 'Resource Planning'!$C$3:$M$13, 11, FALSE)*AA69 -> 0 | AD69: =AB69-AC69 -> 0 | AE69: 1 | AF69: =VLOOKUP($AE$64, 'Resource Planning'!$C$3:$M$13, 11, FALSE)*AE69 -> 43.2 | AH69: =AF69-AG69 -> 43.2 | AI69: 1 | AJ69: =VLOOKUP($AI$64, 'Resource Planning'!$C$3:$M$13, 11, FALSE)*AI69 -> 47.2 | AL69: =AJ69-AK69 -> 47.2 | AM69: 0.7 | AN69: =VLOOKUP($AM$64, 'Resource Planning'!$C$16:$M$27, 11, FALSE)*AM69 -> 30.8 | AP69: =AN69-AO69 -> 30.8 | AQ69: 0.35 | AR69: =VLOOKUP($AQ$64, 'Resource Planning'!$C$16:$M$27, 11, FALSE)*AQ69 -> 15.4 | AT69: =AR69-AS69 -> 15.4 | AU69: 0 | AV69: =VLOOKUP($AU$64, 'Resource Planning'!$C$3:$M$13, 11, FALSE)*AU69 -> 0 | AX69: =AV69-AW69 -> 0 | AY69: 0.5 | AZ69: =VLOOKUP($AU$64, 'Resource Planning'!$C$3:$M$13, 11, FALSE)*AY69 -> 23.6 | BB69: =AZ69-BA69 -> 23.6 | BC69: =SUM(F69,J69,N69,R69,V69,Z69,AD69,AH69,AL69,AP69,AT69,AX69,BB69) -> 338.96
B70: iRIDER | C70: 0 | D70: =VLOOKUP($C$64, 'Resource Planning'!$C$3:$M$13, 11, FALSE)*C70 -> 0 | F70: 0 | H70: =VLOOKUP($G$64, 'Resource Planning'!$C$3:$M$13, 11, FALSE)*G70 -> 0 | L70: =VLOOKUP($K$64, 'Resource Planning'!$C$3:$M$13, 11, FALSE)*K70 -> 0 | P70: =VLOOKUP($O$64, 'Resource Planning'!$C$3:$M$13, 11, FALSE)*O70 -> 0 | T70: =VLOOKUP($S$64, 'Resource Planning'!$C$3:$M$13, 11, FALSE)*S70 -> 0 | W70: 0 | X70: =VLOOKUP($W$64, 'Resource Planning'!$C$3:$M$13, 11, FALSE)*W70 -> 0 | AA70: 0.3 | AB70: =VLOOKUP($AA$64, 'Resource Planning'!$C$3:$M$13, 11, FALSE)*AA70 -> 13.92 | AD70: =AB70-AC70 -> 13.92 | AE70: 0 | AF70: =VLOOKUP($AE$64, 'Resource Planning'!$C$3:$M$13, 11, FALSE)*AE70 -> 0 | AI70: 0 | AJ70: =VLOOKUP($AI$64, 'Resource Planning'!$C$3:$M$13, 11, FALSE)*AI70 -> 0 | AN70: =VLOOKUP($AM$64, 'Resource Planning'!$C$16:$M$27, 11, FALSE)*AM70 -> 0 | AR70: =VLOOKUP($AQ$64, 'Resource Planning'!$C$16:$M$27, 11, FALSE)*AQ70 -> 0 | AU70: 0.8 | AV70: =VLOOKUP($AU$64, 'Resource Planning'!$C$3:$M$13, 11, FALSE)*AU70 -> 37.76 | AX70: =AV70-AW70 -> 37.76 | AY70: 0 | AZ70: =VLOOKUP($AY$64, 'Resource Planning'!$C$3:$M$13, 11, FALSE)*AY70 -> 0 | BB70: =AZ70-BA70 -> 0 | BC70: =SUM(F70,J70,N70,R70,V70,Z70,AD70,AH70,AL70,AP70,AT70,AX70,BB70) -> 51.68
B71: Future State Data project | C71: 0 | D71: =VLOOKUP($C$64, 'Resource Planning'!$C$3:$M$13, 11, FALSE)*C71 -> 0 | H71: =VLOOKUP($G$64, 'Resource Planning'!$C$3:$M$13, 11, FALSE)*G71 -> 0 | L71: =VLOOKUP($K$64, 'Resource Planning'!$C$3:$M$13, 11, FALSE)*K71 -> 0 | P71: =VLOOKUP($O$64, 'Resource Planning'!$C$3:$M$13, 11, FALSE)*O71 -> 0 | T71: =VLOOKUP($S$64, 'Resource Planning'!$C$3:$M$13, 11, FALSE)*S71 -> 0 | W71: 0 | X71: =VLOOKUP($W$64, 'Resource Planning'!$C$3:$M$13, 11, FALSE)*W71 -> 0 | AA71: 0.3 | AB71: =VLOOKUP($AA$64, 'Resource Planning'!$C$3:$M$13, 11, FALSE)*AA71 -> 13.92 | AD71: =AB71-AC71 -> 13.92 | AE71: 0 | AF71: =VLOOKUP($AE$64, 'Resource Planning'!$C$3:$M$13, 11, FALSE)*AE71 -> 0 | AI71: 0 | AJ71: =VLOOKUP($AI$64, 'Resource Planning'!$C$3:$M$13, 11, FALSE)*AI71 -> 0 | AN71: =VLOOKUP($AM$64, 'Resource Planning'!$C$16:$M$27, 11, FALSE)*AM71 -> 0 | AR71: =VLOOKUP($AQ$64, 'Resource Planning'!$C$16:$M$27, 11, FALSE)*AQ71 -> 0 | AU71: 0.8 | AV71: =VLOOKUP($AU$64, 'Resource Planning'!$C$3:$M$13, 11, FALSE)*AU71 -> 37.76 | AX71: =AV71-AW71 -> 37.76 | AY71: 0 | AZ71: =VLOOKUP($AY$64, 'Resource Planning'!$C$3:$M$13, 11, FALSE)*AY71 -> 0 | BB71: =AZ71-BA71 -> 0
A72: DONOT Delete below values
A73: 3
A74: 4
A75: 5
A76: 6
A77: 7
A78: 8
A79: 9
A80: 10
A81: 11
A82: 12
A83: 13
A84: 14
... A88: 18

Sheet Sheet2
E1: Samurais: Proportional Available Hours - Sprints 1-6 | F1: Samurais - Proportional Actual hours - Sprints 1-6 | G1: Difference | M1: Resource | N1: Product Releasae | O1: % | P1: Story points Total Available | Q1: Story points ask upto 4/15 | R1: Prasob update points in this column if changes are needed in F
A2: Core Data Services | B2: Abdul Naik | C2: GRID / GRID Adj. | D2: 0 | E2: =VLOOKUP($B$2, ResourceAllocationByPriority!$B$23:$C34, 2, FALSE)*$D2 -> 0 | F2: {=SUMPRODUCT(--(ResourceAllocationByPriority!$B$23:$B$34=$B$2), ResourceAllocationByPriority!$D$23:$D$34)} -> 0 | G2: =$E2-$F2 -> 0 | L2: Shared Services | M2: Abhijith | N2: PROOF BAU | O2: 0.5 | P2: =ResourceAllocationByPriority!$J$3*O2 -> 23.2 | Q2: 30 | R2: =P2-Q2 -> -6.8
C3: IDC | D3: 0.5 | E3: =VLOOKUP($B$2, ResourceAllocationByPriority!$B$23:$C35, 2, FALSE)*$D3 -> 22 | F3: {=SUMPRODUCT(--(ResourceAllocationByPriority!$B$23:$B$34=$B$2), ResourceAllocationByPriority!$E$23:$E$34)} -> 0 | G3: =$E3-$F3 -> 22 | M3: Abhijith | N3: Adj | O3: 0.4 | P3: =ResourceAllocationByPriority!$J$3*O3 -> 18.56 | Q3: 1 | R3: =P3-Q3 -> 17.56
C4: IDC2 | D4: 0.25 | E4: =VLOOKUP($B$2, ResourceAllocationByPriority!$I$23:$J36, 2, FALSE)*$D4 -> #N/A | F4: {=SUMPRODUCT(--(ResourceAllocationByPriority!$B$23:$B$34=$B$2), ResourceAllocationByPriority!$F$23:$F$34)} -> 0 | G4: =$E4-$F4 -> #N/A | M4: Abhijith | N4: IDC | O4: 0.1 | P4: =ResourceAllocationByPriority!$J$3*O4 -> 4.64 | Q4: 7 | R4: =P4-Q4 -> -2.36
C5: DOS | D5: 0.25 | E5: =VLOOKUP($B$2, ResourceAllocationByPriority!$I$23:$J37, 2, FALSE)*$D5 -> #N/A | F5: {=SUMPRODUCT(--(ResourceAllocationByPriority!$B$23:$B$34=$B$2), ResourceAllocationByPriority!$D$23:$D$34)} -> 0 | G5: =$E5-$F5 -> #N/A | M5: Abhijith | N5: IDC2 | O5: 0 | P5: =ResourceAllocationByPriority!$J$3*O5 -> 0 | R5: =P5-Q5 -> 0
B6: Anoop Mohan | C6: GRID / GRID Adj. | D6: 0.2 | E6: =VLOOKUP($B$6, ResourceAllocationByPriority!$B$23:$C$34, 2, FALSE)*$D6 -> 8.8 | F6: {=SUMPRODUCT(--(ResourceAllocationByPriority!$B$23:$B$34=$B6), ResourceAllocationByPriority!$D$23:$D$34)} -> 0 | G6: =$E6-$F6 -> 8.8 | M6: Prasob | N6: PROOF | O6: 0.4 | P6: =ResourceAllocationByPriority!$J$4*O6 -> 18.56 | Q6: 7 | R6: =P6-Q6 -> 11.56
C7: IDC | D7: 0.5 | E7: =VLOOKUP($B$6, ResourceAllocationByPriority!$B$23:$C$34, 2, FALSE)*$D7 -> 22 | F7: =VLOOKUP($B$6, ResourceAllocationByPriority!$B$22:$K$34, 4, FALSE) -> 0 | G7: =$E7-$F7 -> 22 | M7: Prasob | N7: IDC2 | O7: 0.6 | P7: =ResourceAllocationByPriority!$J$4*O7 -> 27.84 | Q7: 32 | R7: =P7-Q7 -> -4.16
C8: IDC2 | D8: 0.2 | E8: =VLOOKUP($B$6, ResourceAllocationByPriority!$B$23:$C$34, 2, FALSE)*$D8 -> 8.8 | F8: =VLOOKUP($B$6, ResourceAllocationByPriority!$B$22:$K$34, 5, FALSE) -> 0 | G8: =$E8-$F8 -> 8.8 | M8: Manoj | N8: Adj | O8: 0.8 | P8: =ResourceAllocationByPriority!$J$5*O8 -> 37.76 | Q8: 15 | R8: =P8-Q8 -> 22.76
C9: DOS | D9: 0.1 | E9: =VLOOKUP($B$6, ResourceAllocationByPriority!$B$23:$C$34, 2, FALSE)*$D9 -> 4.4 | F9: =VLOOKUP($B$6, ResourceAllocationByPriority!$B$22:$K$34, 6, FALSE) -> 0 | G9: =$E9-$F9 -> 4.4 | M9: Manoj | N9: IDC2 | O9: 0.2 | P9: =ResourceAllocationByPriority!$J$5*O9 -> 9.44 | Q9: 5 | R9: =P9-Q9 -> 4.44
B10: Aravind Syama Unni | C10: GRID / GRID Adj. | D10: 0 | E10: =VLOOKUP($B$10, ResourceAllocationByPriority!$I$22:$J38, 2, FALSE)*$D10 -> #N/A | F10: =VLOOKUP($B$10, ResourceAllocationByPriority!$B$22:$K$34, 3, FALSE) -> 0 | G10: =$E10-$F10 -> #N/A | M10: Manoj | N10: PROOF | O10: 0.8 | P10: =ResourceAllocationByPriority!$J$5*O10 -> 37.76 | Q10: 10 | R10: =P10-Q10 -> 27.76
C11: IDC | D11: 0.5 | E11: =VLOOKUP($B$10, ResourceAllocationByPriority!$I$22:$J38, 2, FALSE)*$D11 -> #N/A | F11: =VLOOKUP($B$10, ResourceAllocationByPriority!$B$22:$K$34, 4, FALSE) -> 0 | G11: =$E11-$F11 -> #N/A | M11: Krishna | N11: ADJ | O11: 0.2 | P11: =ResourceAllocationByPriority!$J$5*O11 -> 9.44 | Q11: 3 | R11: =P11-Q11 -> 6.44
C12: IDC2 | D12: 0 | E12: =VLOOKUP($B$10, ResourceAllocationByPriority!$I$22:$J38, 2, FALSE)*$D12 -> #N/A | F12: =VLOOKUP($B$10, ResourceAllocationByPriority!$B$22:$K$34, 5, FALSE) -> 0 | G12: =$E12-$F12 -> #N/A | M12: Krishna | N12: IDC-2 | O12: 0.8 | P12: =ResourceAllocationByPriority!$J$5*O12 -> 37.76 | Q12: 36 | R12: =P12-Q12 -> 1.76
C13: DOS | D13: 0.5 | E13: =VLOOKUP($B$10, ResourceAllocationByPriority!$I$22:$J38, 2, FALSE)*$D13 -> #N/A | F13: =VLOOKUP($B$10, ResourceAllocationByPriority!$B$22:$K$34, 6, FALSE) -> 0 | G13: =$E13-$F13 -> #N/A | M13: Samba | N13: ADJ | O13: 1 | P13: =ResourceAllocationByPriority!$J$5*O13 -> 47.2 | Q13: 17 | R13: =P13-Q13 -> 30.2
B14: Dana Fillhart | C14: GRID / GRID Adj. | D14: 0.1 | E14: =VLOOKUP($B$14, ResourceAllocationByPriority!$I$22:$J38, 2, FALSE)*$D14 -> #N/A | F14: =VLOOKUP($B$14, ResourceAllocationByPriority!$B$22:$K$34, 3, FALSE) -> 0 | G14: =$E14-$F14 -> #N/A | M14: Swapna | N14: IDC | O14: 0.3 | P14: =ResourceAllocationByPriority!$J$5*O14 -> 14.16 | Q14: 16 | R14: =P14-Q14 -> -1.84
C15: IDC | D15: 0 | E15: =VLOOKUP($B$14, ResourceAllocationByPriority!$I$22:$J38, 2, FALSE)*$D15 -> #N/A | F15: =VLOOKUP($B$14, ResourceAllocationByPriority!$B$22:$K$34, 4, FALSE) -> 0 | G15: =$E15-$F15 -> #N/A | M15: Swapna | N15: IDC-2 | O15: 0.2 | P15: =ResourceAllocationByPriority!$J$5*O15 -> 9.44 | Q15: 10 | R15: =P15-Q15 -> -0.56
C16: IDC2 | D16: 0 | E16: =VLOOKUP($B$14, ResourceAllocationByPriority!$I$22:$J38, 2, FALSE)*$D16 -> #N/A | F16: =VLOOKUP($B$14, ResourceAllocationByPriority!$B$22:$K$34, 5, FALSE) -> 0 | G16: =$E16-$F16 -> #N/A | M16: Swapna | N16: PROOF | O16: 0.5 | P16: =ResourceAllocationByPriority!$J$5*O16 -> 23.6 | Q16: 16 | R16: =P16-Q16 -> 7.6
C17: DOS | D17: 0.9 | E17: =VLOOKUP($B$14, ResourceAllocationByPriority!$I$22:$J38, 2, FALSE)*$D17 -> #N/A | F17: =VLOOKUP($B$14, ResourceAllocationByPriority!$B$22:$K$34,6, FALSE) -> 0 | G17: =$E17-$F17 -> #N/A | M17: Shiju | N17: PROOF BAU | O17: 0.2 | P17: =ResourceAllocationByPriority!$J$5*O17 -> 9.44 | Q17: 6 | R17: =P17-Q17 -> 3.44
B18: Johnson Robin | C18: GRID / GRID Adj. | D18: 0.25 | E18: =VLOOKUP($B$18, ResourceAllocationByPriority!$I$22:$J38, 2, FALSE)*$D18 -> #N/A | F18: =VLOOKUP($B$18, ResourceAllocationByPriority!$B$22:$K$34, 3, FALSE) -> 0 | G18: =$E18-$F18 -> #N/A | M18: Shiju | N18: IDC-2 | O18: 0.8 | P18: =ResourceAllocationByPriority!$J$5*O18 -> 37.76 | Q18: 30 | R18: =P18-Q18 -> 7.76
C19: IDC | D19: 0.25 | E19: =VLOOKUP($B$18, ResourceAllocationByPriority!$I$22:$J38, 2, FALSE)*$D19 -> #N/A | F19: =VLOOKUP($B$18, ResourceAllocationByPriority!$B$22:$K$34,4, FALSE) -> 0 | G19: =$E19-$F19 -> #N/A | M19: Jagan | N19: iRIDER | O19: 0.2 | P19: =ResourceAllocationByPriority!$J$5*O19 -> 9.44 | Q19: 4 | R19: =P19-Q19 -> 5.44
C20: IDC 2 | D20: 0 | E20: =VLOOKUP($B$18, ResourceAllocationByPriority!$I$22:$J38, 2, FALSE)*$D20 -> #N/A | F20: =VLOOKUP($B$18, ResourceAllocationByPriority!$B$22:$K$34,5, FALSE) -> 0 | G20: =$E20-$F20 -> #N/A | M20: Jagan | N20: PROOF | O20: 0.8 | P20: =ResourceAllocationByPriority!$J$5*O20 -> 37.76 | Q20: 33 | R20: =P20-Q20 -> 4.76
C21: DOS | D21: 0.5 | E21: =VLOOKUP($B$18, ResourceAllocationByPriority!$I$22:$J38, 2, FALSE)*$D21 -> #N/A | F21: =VLOOKUP($B$18, ResourceAllocationByPriority!$B$22:$K$34, 6, FALSE) -> 0 | G21: =$E21-$F21 -> #N/A | M21: Krishnaraj | N21: IDC-2 | O21: 0.7 | P21: =ResourceAllocationByPriority!$J$5*O21 -> 33.04 | Q21: 20 | R21: =P21-Q21 -> 13.04
B22: Krishnaraj Nagarajan | C22: GRID / GRID Adj. | D22: 0.5 | E22: =ResourceAllocationByPriority!$C$26*D22 -> 13.2 | F22: =VLOOKUP($B$22, ResourceAllocationByPriority!$B$22:$K$34, 3, FALSE) -> 0 | G22: =$E22-$F22 -> 13.2 | M22: Meraj | N22: IDC | O22: 0.4 | P22: =ResourceAllocationByPriority!$J$5*O22 -> 18.88 | Q22: 13 | R22: =P22-Q22 -> 5.88
C23: IDC | D23: 0 | E23: =ResourceAllocationByPriority!$C$26*D23 -> 0 | F23: =VLOOKUP($B$22, ResourceAllocationByPriority!$B$22:$K$34, 4, FALSE) -> 0 | G23: =$E23-$F23 -> 0 | M23: Meraj | N23: IDC-2 | O23: 0.2 | P23: =ResourceAllocationByPriority!$J$5*O23 -> 9.44 | Q23: 9 | R23: =P23-Q23 -> 0.44
C24: IDC 2 | D24: 0.5 | E24: =ResourceAllocationByPriority!$C$26*D24 -> 13.2 | F24: =VLOOKUP($B$22, ResourceAllocationByPriority!$B$22:$K$34,5, FALSE) -> 0 | G24: =$E24-$F24 -> 13.2 | M24: Meraj | N24: PROOF | O24: 0.4 | P24: =ResourceAllocationByPriority!$J$5*O24 -> 18.88 | Q24: 15 | R24: =P24-Q24 -> 3.88
C25: DOS | D25: 0 | E25: =ResourceAllocationByPriority!$C$26*D25 -> 0 | F25: =VLOOKUP($B$22, ResourceAllocationByPriority!$B$22:$K$34, 6, FALSE) -> 0 | G25: =$E25-$F25 -> 0
B26: Mala Nadar | C26: GRID | D26: 0 | E26: =ResourceAllocationByPriority!$C$26*D26 -> 0 | F26: =VLOOKUP($B$26, ResourceAllocationByPriority!$B$22:$K$34, 3, FALSE) -> 0 | G26: =$E26-$F26 -> 0
C27: IDC | D27: 0.5 | E27: =ResourceAllocationByPriority!$C$26*D27 -> 13.2 | F27: =VLOOKUP($B$26, ResourceAllocationByPriority!$B$22:$K$34, 4, FALSE) -> 0 | G27: =$E27-$F27 -> 13.2
C28: IDC2 | D28: 0 | E28: =ResourceAllocationByPriority!$C$26*D28 -> 0 | F28: =VLOOKUP($B$26, ResourceAllocationByPriority!$B$22:$K$34, 5, FALSE) -> 0 | G28: =$E28-$F28 -> 0
C29: DOS | D29: 0.5 | E29: =ResourceAllocationByPriority!$C$26*D29 -> 13.2 | F29: =VLOOKUP($B$26, ResourceAllocationByPriority!$B$22:$K$34,6, FALSE) -> 0 | G29: =$E29-$F29 -> 13.2
B30: Rahul Bishnoi | C30: GRID | D30: 0.25 | E30: =ResourceAllocationByPriority!$C$26*D30 -> 6.6 | F30: =VLOOKUP($B$30, ResourceAllocationByPriority!$B$22:$K$34, 3, FALSE) -> 0 | G30: =$E30-$F30 -> 6.6
C31: IDC | D31: 0.5 | E31: =ResourceAllocationByPriority!$C$26*D31 -> 13.2 | F31: =VLOOKUP($B$30, ResourceAllocationByPriority!$B$22:$K$34, 4, FALSE) -> 0 | G31: =$E31-$F31 -> 13.2
C32: IDC 2 | D32: 0 | E32: =ResourceAllocationByPriority!$C$26*D32 -> 0 | F32: =VLOOKUP($B$30, ResourceAllocationByPriority!$B$22:$K$34, 5, FALSE) -> 0 | G32: =$E32-$F32 -> 0
C33: DOS | D33: 0.25 | E33: =ResourceAllocationByPriority!$C$26*D33 -> 6.6 | F33: =VLOOKUP($B$30, ResourceAllocationByPriority!$B$22:$K$34, 6, FALSE) -> 0 | G33: =$E33-$F33 -> 6.6
B34: Varun Sundar | C34: GRID | D34: 0 | E34: =ResourceAllocationByPriority!$C$26*D34 -> 0 | F34: =VLOOKUP($B$34, ResourceAllocationByPriority!$B$22:$K$34, 3, FALSE) -> 0 | G34: =$E34-$F34 -> 0
C35: IDC | D35: 0.2 | E35: =ResourceAllocationByPriority!$C$26*D35 -> 5.28 | F35: =VLOOKUP($B$34, ResourceAllocationByPriority!$B$22:$K$34, 4, FALSE) -> 0 | G35: =$E35-$F35 -> 5.28
C36: IDC 2 | D36: 0 | E36: =ResourceAllocationByPriority!$C$26*D36 -> 0 | F36: =VLOOKUP($B$34, ResourceAllocationByPriority!$B$22:$K$34, 5, FALSE) -> 0 | G36: =$E36-$F36 -> 0
C37: DOS | D37: 0.8 | E37: =ResourceAllocationByPriority!$C$26*D37 -> 21.12 | F37: =VLOOKUP($B$34, ResourceAllocationByPriority!$B$22:$K$34, 6, FALSE) -> 0 | G37: =$E37-$F37 -> 21.12
B38: Vilasini Ganesan | C38: GRID | D38: 0.5 | E38: =ResourceAllocationByPriority!$C$26*D38 -> 13.2 | F38: =VLOOKUP($B$38, ResourceAllocationByPriority!$B$22:$K$34, 3, FALSE) -> 0 | G38: =$E38-$F38 -> 13.2
C39: IDC | D39: 0.4 | E39: =ResourceAllocationByPriority!$C$26*D39 -> 10.56 | F39: =VLOOKUP($B$38, ResourceAllocationByPriority!$B$22:$K$34, 4, FALSE) -> 0 | G39: =$E39-$F39 -> 10.56
C40: IDC 2 | D40: 0 | E40: =ResourceAllocationByPriority!$C$26*D40 -> 0 | F40: =VLOOKUP($B$38, ResourceAllocationByPriority!$B$22:$K$34, 5, FALSE) -> 0 | G40: =$E40-$F40 -> 0
C41: DOS | D41: 0.1 | E41: =ResourceAllocationByPriority!$C$26*D41 -> 2.64 | F41: =VLOOKUP($B$38, ResourceAllocationByPriority!$B$22:$K$34,6, FALSE) -> 0 | G41: =$E41-$F41 -> 2.64
B42: Ashish Chourey | C42: GRID | D42: 0.25 | E42: =ResourceAllocationByPriority!$C$26*D42 -> 6.6 | F42: =VLOOKUP($B$42, ResourceAllocationByPriority!$B$22:$K$34, 3, FALSE) -> 0 | G42: =$E42-$F42 -> 6.6
C43: IDC | D43: 0.5 | E43: =ResourceAllocationByPriority!$C$26*D43 -> 13.2 | F43: =VLOOKUP($B$42, ResourceAllocationByPriority!$B$22:$K$34, 4, FALSE) -> 0 | G43: =$E43-$F43 -> 13.2
C44: IDC 2 | D44: 0.25 | E44: =ResourceAllocationByPriority!$C$26*D44 -> 6.6 | F44: =VLOOKUP($B$42, ResourceAllocationByPriority!$B$22:$K$34, 5, FALSE) -> 0 | G44: =$E44-$F44 -> 6.6
C45: DOS | D45: 0 | E45: =ResourceAllocationByPriority!$C$26*D45 -> 0 | F45: =VLOOKUP($B$42, ResourceAllocationByPriority!$B$22:$K$34, 6, FALSE) -> 0 | G45: =$E45-$F45 -> 0
B46: Vijay Amirtharaj | C46: GRID | D46: 0.4 | E46: =ResourceAllocationByPriority!$C$26*D46 -> 10.56 | F46: =VLOOKUP($B$46, ResourceAllocationByPriority!$B$22:$K$34, 3, FALSE) -> 0 | G46: =$E46-$F46 -> 10.56
C47: IDC | D47: 0 | E47: =ResourceAllocationByPriority!$C$26*D47 -> 0 | F47: =VLOOKUP($B$46, ResourceAllocationByPriority!$B$22:$K$34, 4, FALSE) -> 0 | G47: =$E47-$F47 -> 0
C48: IDC 2 | D48: 0 | E48: =ResourceAllocationByPriority!$C$26*D48 -> 0 | F48: =VLOOKUP($B$46, ResourceAllocationByPriority!$B$22:$K$34, 5, FALSE) -> 0 | G48: =$E48-$F48 -> 0
C49: DOS | D49: 0.6 | E49: =ResourceAllocationByPriority!$C$26*D49 -> 15.84 | F49: =VLOOKUP($B$46, ResourceAllocationByPriority!$B$22:$K$34, 6, FALSE) -> 0 | G49: =$E49-$F49 -> 15.84
A56: Sum of Story Points | B56: Column Labels
A57: Row Labels | B57: Abdul Nathik Abdul Hanan Najjar <abdulnathik.abdulhanannajjar@metlife.com> | C57: Abhijith Jayakumar <abhijith.jayakumar@metlife.com> | D57: Anoop Mohandas Sheelarani <anoop.mohandas-sheelarani@metlife.com> | E57: Jagadeesan Balasubramanian <jbalasubramanian1@metlife.com> | F57: Krishna Chandar Kandula <krishna-chandar.kandula@metlife.com> | G57: Krishnaraj Nagarajan <krishnaraj.nagarajan@metlife.com> | H57: Lokeshwaran Sankar <lokeshwaran.sankar@metlife.com> | I57: Manoj Madhavan <manoj.madhavan@metlife.com> | J57: Meraj Husen Ansari <merajhusen.ansari@metlife.com> | K57: Prasob Nambuthodiyil <prasob.nambuthodiyil@metlife.com> | L57: Samba siva Rao Prudhivi <sambasivarao.prudhivi@metlife.com> | M57: Shibu Swaminathan <shibu.swaminathan@metlife.com> | N57: Shiju Mathew <shiju.mathew@metlife.com> | O57: Swapna Madhu <swapna.madhu@metlife.com> | P57: (blank) | Q57: Grand Total
A58: ADJUI | C58: 3 | F58: 3 | I58: 15 | L58: 12 | M58: 3 | Q58: 31
A59: IDC | C59: 7 | J59: 18 | O59: 3 | Q59: 28
A60: IDC-2 | B60: 25 | D60: 7 | F60: 38 | G60: 25 | I60: 5 | J60: 9 | K60: 37 | L60: 5 | N60: 35 | O60: 10 | Q60: 196
A61: IRIDER | E61: 4 | M61: 5 | Q61: 4
A62: PROOF | C62: 25 | E62: 25 | H62: 42 | I62: 10 | J62: 15 | K62: 8 | M62: 7 | O62: 22 | Q62: 127
A63: Grand Total | B63: 25 | C63: 35 | D63: 7 | E63: 29 | F63: 41 | G63: 25 | H63: 42 | I63: 30 | J63: 42 | K63: 45 | L63: 17 | M63: 15 | N63: 35 | O63: 35 | Q63: 423

Sheet HistorySP
D1: DOS | E1: GRID | K1: The Ninjas
C2: Sprint | D2: Delivered Story Points | E2: Delivered Story Points | F2: Total Story Points | L2: Sprint | N2: velocity | O2: capacity in hrs
C3: 74 | D3: 70 | E3: 51 | F3: =SUM(D3:E3) -> 121 | L3: 39 | O3: 445
C4: 75 | D4: 102 | E4: 66 | F4: =SUM(D4:E4) -> 168 | L4: 40
C5: 76 | D5: 150 | E5: 68 | F5: =SUM(D5:E5) -> 218 | L5: 41
C6: 77 | D6: 148 | E6: 88 | F6: =SUM(D6:E6) -> 236 | K6: PI6 | L6: 42 | N6: 67 | O6: 480
C7: 78 | D7: 104 | E7: 105 | F7: =SUM(D7:E7) -> 209 | L7: 43 | N7: 56 | O7: 480
C8: 79 | D8: 134 | E8: 84 | F8: =SUM(D8:E8) -> 218 | L8: 44 | N8: 57 | O8: 480 | S8: Resource | T8: Avg Story points per resource
C9: 80 | D9: 136 | E9: =61+27 -> 88 | F9: =SUM(D9:E9) -> 224 | L9: 45 | N9: 60 | O9: 480 | R9: =AVERAGE(N3:N8) -> 60 | S9: 8 | T9: =R9/S9 -> 7.5
L10: 46 | N10: 54 | O10: 480
F11: Resource | G11: Avg Story points per resource | L11: 47 | N11: 57 | O11: 480
E12: =AVERAGE(F3:F9) -> 199.14286 | F12: 9 | G12: =E12/F12 -> 22.126984 | K12: PI7 | L12: 48 | N12: 75 | O12: 680
L13: 49 | N13: 74 | O13: 666
E14: Considering holidays, timeoff, team story point capacity/sprint: | F14: 185 | L14: 50 | N14: 73 | O14: 617
L15: 51 | N15: 76 | O15: 638 | S15: Resource | T15: Avg Story points per resource
L16: 52 | N16: 75 | O16: 680 | R16: =AVERAGE(N12:N16) -> 74.6 | S16: 10 | T16: =R16/S16 -> 7.46
E17: GRID Allocation | F17: 120
E18: DOS Allocation | F18: 65 | K18: PI 8 | L18: 53 | O18: 796
L19: 54 | O19: 789
L20: 55 | O20: 810
L21: 56 | O21: 810
L22: 57 | O22: 782
L23: 58 | O23: 810

Sheet ProgramPriorityFeatures
B1: From Brian
B2: 1 | C2: Testing and Deploying Master Data Synch
B3: 2 | C3: Complete changes for Privates Placement Multi-Currency
B4: 3 | C4: Complete UI and begin IT testing for Private Structured Credit
B5: 4 | C5: Entitlement enhancements for Data and Documents separation
B6: 5 | C6: Development for Residential Loans
B7: 6 | C7: Implement Document Streaming
B8: 7 | C8: Automate MIM Relationship Portal contacts
B9: 8 | C9: Screen design for RE Equity (No Development)
A14: SAMURAI | D14: 6 sprints
C15: GRID IDC - BAU 2022.05 Release (May 2022) | D15: 8
C16: GRID IDC - BAU 2022.06 Release (June 2022) | D16: 8
C17: GRID IDC - BAU 2022.07 Release (July 2022) | D17: 8
C18: GRID IDC - BAU 2022.08 Release (August 2022) | D18: 5
C19: GRID - BAU 2022.05 Release (May 2022) | D19: 8
C20: GRID - BAU 2022.06 Release (June 2022) | D20: 8
C21: GRID - BAU 2022.07 Release (July 2022) | D21: 8
C22: GRID - BAU 2022.08 Release (August 2022) | D22: 5
B23: Feature | C23: GRID Automated Data Validations - May 2022 | D23: 35
C24: GRID Automated Data Validations - June 2022 | D24: 15 | P24: story | Q24: DOS - BAU 2022.05 Release (May 2022) - COML
C25: GRID Automated Data Validations - July 2022 | D25: 15 | P25: Task | Q25: Task1
C26: GRID Automated Data Validations - August 2022 | D26: 5 | P26: Task | Q26: Task2
C27: GRID QA Automation | D27: 15 | Q27: DOS - BAU 2022.05 Release (May 2022) - AGRI
C28: GRID: Reserve capacity for Next PI Planning, System Demo and Innovation | D28: 8 | Q28: DOS - BAU 2022.05 Release (May 2022) - Privates/PABS
C29: GRID/IDC Rewiring | D29: 15 | Q29: DOS - BAU 2022.05 Release (May 2022) - SIT
C30: GRID REI Historical Load | D30: 8 | Q30: DOS - BAU 2022.05 Release (May 2022) - UAT
C31: GRID/DOS/GRID Adj AM KT | D31: 8
C32: GRID IDC AllVue | D32: 10
C33: GRID ESG Star | D33: 3
C34: GRID-Future State Data Project | D34: 55
C35: GRID - IDC Data Project - Client Reporting | D35: 15
C36: DOS - BAU 2022.05 Release (May 2022) | D36: 15
C37: DOS - BAU 2022.06 Release (June 2022) | D37: 20
C38: DOS - BAU 2022.07 Release (July 2022) | D38: 20
C39: DOS - BAU 2022.08 Release (August 2022) | D39: 20
C40: DOS Databricks Optimization | D40: 8
C41: DOS Residential | D41: 8
C42: DOS RE Equity | D42: 8
... C44: DOS Release On Demand | D44: 8
B45: Future State data project | C45: DOS: Reserve capacity for Next PI Planning, System Demo and Innovation | D45: 8
C46: DOS IDC Rewiring | D46: 8
C47: DOS ESG Star | D47: 3
C52: PROOF-Future State Data Project | D52: 105 | E52: 2nd sprint | F52: 6th sprint
A54: NINJA | C54: PROOF: Reserve capacity for Next PI Planning, System Demo and Innovation | D54: 8
C55: IDC: Phase 2 : Design part 1 | D55: 7
C56: IDC: Phase 2: Implementation - Part 1 | D56: 7 | G56: =1.6*5 -> 8
C57: IDC: Phase 2 -Implementation API for query designer | D57: 21
C58: IDC: Phase 2 -Implementation of query designer db | D58: 20
C59: IDC: Phase 2 -Implementation of Validation of Query Definition | D59: 11
C60: IDC: Phase 2 - Implementation of query builder Wizard | D60: 46
C61: IDC: Phase 2 - Implementation of Orchestration Automation | D61: 42
C62: PROOF - BAU 2022.05 Release (May 2022) | D62: 32
C63: PROOF - BAU 2022.06 Release (June 2022) | D63: 27
C64: PROOF - BAU 2022.07 Release (July 2022) | D64: 32
C65: PROOF - BAU 2022.08 Release (August 2022) | D65: 15
C66: iRIDER - BAU 2022.05 Release (May 2022) | D66: 8
C67: iRIDER - BAU 2022.06 Release (June 2022) | D67: 8
C68: iRIDER - BAU 2022.07 Release (July 2022) | D68: 8 | G68: =11*48 -> 528 | H68: =G68*20% -> 105.6
C69: iRIDER - BAU 2022.08 Release (August 2022) | D69: 8
C70: GRID Adjustments - BAU 2022.05 Release (May 2022) | D70: 8
C71: GRID Adjustments - BAU 2022.06 Release (June 2022) | D71: 8
C72: GRID Adjustments - BAU 2022.07 Release (July 2022) | D72: 8
C73: GRID Adjustments - BAU 2022.08 Release (August 2022) | D73: 8
C74: PROOF/IDC/iRIDER AM KT | D74: 8
C75: PROOF QA Automation | D75: 20
B76: Future State data project | C76: PROOF-Future State Data Project | D76: 105 | E76: 2nd sprint | F76: 6th sprint
C77: Proof - historical | D77: 5
C78: Proof -allvue | D78: 13
C79: PROOF - ESG Star | D79: 8
C80: Data Project - Client Reporting | D80: 0

Sheet PI Commitments
G1: manual | H1: manual | I1: (auto populate) | J1: manual ( H= J for beginning). Periodically(SOS) manually reduce | K1: auto | L1: manual | Q1: manual | R1: manual | S1: auto | T1: auto (equally distributing) | Z1: manual | AA1: manual | AB1: manual | AC1: << not being used>> | AD1: << not being used>>
B2: ID | C2: Title | D2: Work Item Type | E2: Assigned To | F2: WSJF | G2: Business Value | H2: Effort | I2: Size | J2: Rem Effort | K2: Remaining Size | L2: Target Date | M2: State | N2: Commit | O2: Category | P2: Team | Q2: Start in | R2: Deliver in | S2: Duration | T2: S1 | U2: S2 | V2: S3 | W2: S4 | X2: S5 | Y2: s6 | Z2: INT | AA2: QA | AB2: Prod | AC2: % Complete | AD2: Actual Business Value
C3: GRID IDC - BAU 2022.05 Release (May 2022) | G3: 8 | H3: 1.6 | I3: =VLOOKUP(H3,$AF$3:$AG$156,2,FALSE) -> 8 | J3: 1.6 | K3: =IF(J3 > 0, VLOOKUP(J3,$AF$3:$AG$103,2,FALSE),0) -> 8 | M3: New | N3: Commit | O3: BAU | P3: S | Q3: 1 | R3: 2 | S3: =(R3+1) - 1 -> 2 | T3: =IF(AND(R3>=1, $A$1 <=1,Q3<=1), (K3/ ((R3 +1) - 1))*(Team!$H$25/10), 0) -> 4 | U3: =IF(AND(R3>=2, $A$1 <=2, Q3<=2), ((K3-T3)/ ((R3 +1) - 2))*(Team!$H$26/10), 0) -> 4 | V3: =IF(AND(R3>=3, $A$1 <=3, Q3<=3), ((K3-(T3+U3))/ ((R3 +1) - 3))*(Team!$H$27/10), 0) -> 0 | W3: =IF(AND(R3>=4, $A$1 <=4, Q3<=4), ((K3-(T3+U3+V3))/ ((R3 +1) - 4))*(Team!$H$28/10), 0) -> 0 | X3: =IF(AND(R3>=5, $A$1 <5, Q3<=5), ((K3-(T3+U3+V3+W3))/ ((R3 +1) - 5))*(Team!$H$29/10), 0) -> 0 | Y3: =IF(AND(R3>=6, $A$1 <6, Q3<=6), ((K3-(T3+U3+V3+W3+X3))/ ((R3 +1) - 6))*(Team!$H$30/10), 0) -> 0 | AC3: =(H3-J3)/H3 -> 0 | AD3: =IF(AC3=1, G3,0) -> 0
C4: GRID IDC - BAU 2022.06 Release (June 2022) | G4: 8 | H4: 1.6 | I4: =VLOOKUP(H4,$AF$3:$AG$156,2,FALSE) -> 8 | J4: 1.6 | K4: =IF(J4 > 0, VLOOKUP(J4,$AF$3:$AG$103,2,FALSE),0) -> 8 | M4: New | N4: Commit | O4: BAU | P4: S | Q4: 1 | R4: 4 | S4: =(R4+1) - 1 -> 4 | T4: =IF(AND(R4>=1, $A$1 <=1,Q4<=1), (K4/ ((R4 +1) - 1))*(Team!$H$25/10), 0) -> 2 | U4: =IF(AND(R4>=2, $A$1 <=2, Q4<=2), ((K4-T4)/ ((R4 +1) - 2))*(Team!$H$26/10), 0) -> 2 | V4: =IF(AND(R4>=3, $A$1 <=3, Q4<=3), ((K4-(T4+U4))/ ((R4 +1) - 3))*(Team!$H$27/10), 0) -> 2 | W4: =IF(AND(R4>=4, $A$1 <=4, Q4<=4), ((K4-(T4+U4+V4))/ ((R4 +1) - 4))*(Team!$H$28/10), 0) -> 2 | X4: =IF(AND(R4>=5, $A$1 <5, Q4<=5), ((K4-(T4+U4+V4+W4))/ ((R4 +1) - 5))*(Team!$H$29/10), 0) -> 0 | Y4: =IF(AND(R4>=6, $A$1 <6, Q4<=6), ((K4-(T4+U4+V4+W4+X4))/ ((R4 +1) - 6))*(Team!$H$30/10), 0) -> 0 | AC4: =(H4-J4)/H4 -> 0 | AD4: =IF(AC4=1, G4,0) -> 0
C5: GRID IDC - BAU 2022.07 Release (July 2022) | G5: 8 | H5: 1.6 | I5: =VLOOKUP(H5,$AF$3:$AG$156,2,FALSE) -> 8 | J5: 1.6 | K5: =IF(J5 > 0, VLOOKUP(J5,$AF$3:$AG$103,2,FALSE),0) -> 8 | M5: New | N5: Commit | O5: BAU | P5: S | Q5: 3 | R5: 6 | S5: =(R5+1) - 1 -> 6 | T5: =IF(AND(R5>=1, $A$1 <=1,Q5<=1), (K5/ ((R5 +1) - 1))*(Team!$H$25/10), 0) -> 0 | U5: =IF(AND(R5>=2, $A$1 <=2, Q5<=2), ((K5-T5)/ ((R5 +1) - 2))*(Team!$H$26/10), 0) -> 0 | V5: =IF(AND(R5>=3, $A$1 <=3, Q5<=3), ((K5-(T5+U5))/ ((R5 +1) - 3))*(Team!$H$27/10), 0) -> 2 | W5: =IF(AND(R5>=4, $A$1 <=4, Q5<=4), ((K5-(T5+U5+V5))/ ((R5 +1) - 4))*(Team!$H$28/10), 0) -> 2 | X5: =IF(AND(R5>=5, $A$1 <5, Q5<=5), ((K5-(T5+U5+V5+W5))/ ((R5 +1) - 5))*(Team!$H$29/10), 0) -> 2 | Y5: =IF(AND(R5>=6, $A$1 <6, Q5<=6), ((K5-(T5+U5+V5+W5+X5))/ ((R5 +1) - 6))*(Team!$H$30/10), 0) -> 2 | AC5: =(H5-J5)/H5 -> 0 | AD5: =IF(AC5=1, G5,0) -> 0
C6: GRID IDC - BAU 2022.08 Release (August 2022) | G6: 8 | H6: 1 | I6: =VLOOKUP(H6,$AF$3:$AG$156,2,FALSE) -> 5 | J6: 1 | K6: =IF(J6 > 0, VLOOKUP(J6,$AF$3:$AG$103,2,FALSE),0) -> 5 | M6: New | N6: Commit | O6: BAU | P6: S | Q6: 5 | R6: 5 | S6: =(R6+1) - 1 -> 5 | T6: =IF(AND(R6>=1, $A$1 <=1,Q6<=1), (K6/ ((R6 +1) - 1))*(Team!$H$25/10), 0) -> 0 | U6: =IF(AND(R6>=2, $A$1 <=2, Q6<=2), ((K6-T6)/ ((R6 +1) - 2))*(Team!$H$26/10), 0) -> 0 | V6: =IF(AND(R6>=3, $A$1 <=3, Q6<=3), ((K6-(T6+U6))/ ((R6 +1) - 3))*(Team!$H$27/10), 0) -> 0 | W6: =IF(AND(R6>=4, $A$1 <=4, Q6<=4), ((K6-(T6+U6+V6))/ ((R6 +1) - 4))*(Team!$H$28/10), 0) -> 0 | X6: =IF(AND(R6>=5, $A$1 <5, Q6<=5), ((K6-(T6+U6+V6+W6))/ ((R6 +1) - 5))*(Team!$H$29/10), 0) -> 5 | Y6: =IF(AND(R6>=6, $A$1 <6, Q6<=6), ((K6-(T6+U6+V6+W6+X6))/ ((R6 +1) - 6))*(Team!$H$30/10), 0) -> 0 | AC6: =(H6-J6)/H6 -> 0 | AD6: =IF(AC6=1, G6,0) -> 0
C7: GRID - BAU 2022.05 Release (May 2022) | G7: 9 | H7: 1.6 | I7: =VLOOKUP(H7,$AF$3:$AG$156,2,FALSE) -> 8 | J7: 1.6 | K7: =IF(J7 > 0, VLOOKUP(J7,$AF$3:$AG$103,2,FALSE),0) -> 8 | M7: New | N7: Commit | O7: BAU | P7: S | Q7: 1 | R7: 2 | S7: =(R7+1) - 1 -> 2 | T7: =IF(AND(R7>=1, $A$1 <=1,Q7<=1), (K7/ ((R7 +1) - 1))*(Team!$H$25/10), 0) -> 4 | U7: =IF(AND(R7>=2, $A$1 <=2, Q7<=2), ((K7-T7)/ ((R7 +1) - 2))*(Team!$H$26/10), 0) -> 4 | V7: =IF(AND(R7>=3, $A$1 <=3, Q7<=3), ((K7-(T7+U7))/ ((R7 +1) - 3))*(Team!$H$27/10), 0) -> 0 | W7: =IF(AND(R7>=4, $A$1 <=4, Q7<=4), ((K7-(T7+U7+V7))/ ((R7 +1) - 4))*(Team!$H$28/10), 0) -> 0 | X7: =IF(AND(R7>=5, $A$1 <5, Q7<=5), ((K7-(T7+U7+V7+W7))/ ((R7 +1) - 5))*(Team!$H$29/10), 0) -> 0 | Y7: =IF(AND(R7>=6, $A$1 <6, Q7<=6), ((K7-(T7+U7+V7+W7+X7))/ ((R7 +1) - 6))*(Team!$H$30/10), 0) -> 0 | AC7: =(H7-J7)/H7 -> 0
C8: GRID - BAU 2022.06 Release (June 2022) | G8: 9 | H8: 1.6 | I8: =VLOOKUP(H8,$AF$3:$AG$156,2,FALSE) -> 8 | J8: 1.6 | K8: =IF(J8 > 0, VLOOKUP(J8,$AF$3:$AG$103,2,FALSE),0) -> 8 | M8: New | N8: Commit | O8: BAU | P8: S | Q8: 1 | R8: 4 | S8: =(R8+1) - 1 -> 4 | T8: =IF(AND(R8>=1, $A$1 <=1,Q8<=1), (K8/ ((R8 +1) - 1))*(Team!$H$25/10), 0) -> 2 | U8: =IF(AND(R8>=2, $A$1 <=2, Q8<=2), ((K8-T8)/ ((R8 +1) - 2))*(Team!$H$26/10), 0) -> 2 | V8: =IF(AND(R8>=3, $A$1 <=3, Q8<=3), ((K8-(T8+U8))/ ((R8 +1) - 3))*(Team!$H$27/10), 0) -> 2 | W8: =IF(AND(R8>=4, $A$1 <=4, Q8<=4), ((K8-(T8+U8+V8))/ ((R8 +1) - 4))*(Team!$H$28/10), 0) -> 2 | X8: =IF(AND(R8>=5, $A$1 <5, Q8<=5), ((K8-(T8+U8+V8+W8))/ ((R8 +1) - 5))*(Team!$H$29/10), 0) -> 0 | Y8: =IF(AND(R8>=6, $A$1 <6, Q8<=6), ((K8-(T8+U8+V8+W8+X8))/ ((R8 +1) - 6))*(Team!$H$30/10), 0) -> 0 | AC8: =(H8-J8)/H8 -> 0
C9: GRID - BAU 2022.07 Release (July 2022) | G9: 9 | H9: 1.6 | I9: =VLOOKUP(H9,$AF$3:$AG$156,2,FALSE) -> 8 | J9: 1.6 | K9: =IF(J9 > 0, VLOOKUP(J9,$AF$3:$AG$103,2,FALSE),0) -> 8 | M9: New | N9: Commit | O9: BAU | P9: S | Q9: 3 | R9: 6 | S9: =(R9+1) - 1 -> 6 | T9: =IF(AND(R9>=1, $A$1 <=1,Q9<=1), (K9/ ((R9 +1) - 1))*(Team!$H$25/10), 0) -> 0 | U9: =IF(AND(R9>=2, $A$1 <=2, Q9<=2), ((K9-T9)/ ((R9 +1) - 2))*(Team!$H$26/10), 0) -> 0 | V9: =IF(AND(R9>=3, $A$1 <=3, Q9<=3), ((K9-(T9+U9))/ ((R9 +1) - 3))*(Team!$H$27/10), 0) -> 2 | W9: =IF(AND(R9>=4, $A$1 <=4, Q9<=4), ((K9-(T9+U9+V9))/ ((R9 +1) - 4))*(Team!$H$28/10), 0) -> 2 | X9: =IF(AND(R9>=5, $A$1 <5, Q9<=5), ((K9-(T9+U9+V9+W9))/ ((R9 +1) - 5))*(Team!$H$29/10), 0) -> 2 | Y9: =IF(AND(R9>=6, $A$1 <6, Q9<=6), ((K9-(T9+U9+V9+W9+X9))/ ((R9 +1) - 6))*(Team!$H$30/10), 0) -> 2 | AC9: =(H9-J9)/H9 -> 0 | AD9: =IF(AC9=1, G9,0) -> 0
C10: GRID - BAU 2022.08 Release (August 2022) | G10: 9 | H10: 1 | I10: =VLOOKUP(H10,$AF$3:$AG$156,2,FALSE) -> 5 | J10: 1 | K10: =IF(J10 > 0, VLOOKUP(J10,$AF$3:$AG$103,2,FALSE),0) -> 5 | M10: New | N10: Commit | O10: BAU | P10: S | Q10: 5 | R10: 6 | S10: =(R10+1) - 1 -> 6 | T10: =IF(AND(R10>=1, $A$1 <=1,Q10<=1), (K10/ ((R10 +1) - 1))*(Team!$H$25/10), 0) -> 0 | U10: =IF(AND(R10>=2, $A$1 <=2, Q10<=2), ((K10-T10)/ ((R10 +1) - 2))*(Team!$H$26/10), 0) -> 0 | V10: =IF(AND(R10>=3, $A$1 <=3, Q10<=3), ((K10-(T10+U10))/ ((R10 +1) - 3))*(Team!$H$27/10), 0) -> 0 | W10: =IF(AND(R10>=4, $A$1 <=4, Q10<=4), ((K10-(T10+U10+V10))/ ((R10 +1) - 4))*(Team!$H$28/10), 0) -> 0 | X10: =IF(AND(R10>=5, $A$1 <5, Q10<=5), ((K10-(T10+U10+V10+W10))/ ((R10 +1) - 5))*(Team!$H$29/10), 0) -> 2.5 | Y10: =IF(AND(R10>=6, $A$1 <6, Q10<=6), ((K10-(T10+U10+V10+W10+X10))/ ((R10 +1) - 6))*(Team!$H$30/10), 0) -> 2.5 | AC10: =(H10-J10)/H10 -> 0 | AD10: =IF(AC10=1, G10,0) -> 0
C11: GRID Automated Data Validations - May 2022 | G11: 9 | H11: 6 | I11: =VLOOKUP(H11,$AF$3:$AG$156,2,FALSE) -> 30 | J11: 6 | K11: =IF(J11 > 0, VLOOKUP(J11,$AF$3:$AG$103,2,FALSE),0) -> 30 | M11: New | N11: Commit | O11: BAU | P11: S | Q11: 1 | R11: 2 | S11: =(R11+1) - 1 -> 2 | T11: =IF(AND(R11>=1, $A$1 <=1,Q11<=1), (K11/ ((R11 +1) - 1))*(Team!$H$25/10), 0) -> 15 | U11: =IF(AND(R11>=2, $A$1 <=2, Q11<=2), ((K11-T11)/ ((R11 +1) - 2))*(Team!$H$26/10), 0) -> 15 | V11: =IF(AND(R11>=3, $A$1 <=3, Q11<=3), ((K11-(T11+U11))/ ((R11 +1) - 3))*(Team!$H$27/10), 0) -> 0 | W11: =IF(AND(R11>=4, $A$1 <=4, Q11<=4), ((K11-(T11+U11+V11))/ ((R11 +1) - 4))*(Team!$H$28/10), 0) -> 0 | X11: =IF(AND(R11>=5, $A$1 <5, Q11<=5), ((K11-(T11+U11+V11+W11))/ ((R11 +1) - 5))*(Team!$H$29/10), 0) -> 0 | Y11: =IF(AND(R11>=6, $A$1 <6, Q11<=6), ((K11-(T11+U11+V11+W11+X11))/ ((R11 +1) - 6))*(Team!$H$30/10), 0) -> 0 | AC11: =(H11-J11)/H11 -> 0 | AD11: =IF(AC11=1, G11,0) -> 0
C12: GRID Automated Data Validations - June 2022 | G12: 8 | H12: 3 | I12: =VLOOKUP(H12,$AF$3:$AG$156,2,FALSE) -> 15 | J12: 3 | K12: =IF(J12 > 0, VLOOKUP(J12,$AF$3:$AG$103,2,FALSE),0) -> 15 | M12: New | N12: Commit | O12: Tenant Onboarding | P12: S | Q12: 2 | R12: 4 | S12: =(R12+1) - 1 -> 4 | T12: =IF(AND(R12>=1, $A$1 <=1,Q12<=1), (K12/ ((R12 +1) - 1))*(Team!$H$25/10), 0) -> 0 | U12: =IF(AND(R12>=2, $A$1 <=2, Q12<=2), ((K12-T12)/ ((R12 +1) - 2))*(Team!$H$26/10), 0) -> 5 | V12: =IF(AND(R12>=3, $A$1 <=3, Q12<=3), ((K12-(T12+U12))/ ((R12 +1) - 3))*(Team!$H$27/10), 0) -> 5 | W12: =IF(AND(R12>=4, $A$1 <=4, Q12<=4), ((K12-(T12+U12+V12))/ ((R12 +1) - 4))*(Team!$H$28/10), 0) -> 5 | X12: =IF(AND(R12>=5, $A$1 <5, Q12<=5), ((K12-(T12+U12+V12+W12))/ ((R12 +1) - 5))*(Team!$H$29/10), 0) -> 0 | Y12: =IF(AND(R12>=6, $A$1 <6, Q12<=6), ((K12-(T12+U12+V12+W12+X12))/ ((R12 +1) - 6))*(Team!$H$30/10), 0) -> 0 | AC12: =(H12-J12)/H12 -> 0 | AD12: =IF(AC12=1, G12,0) -> 0
C13: GRID Automated Data Validations - July 2022 | G13: 8 | H13: 3 | I13: =VLOOKUP(H13,$AF$3:$AG$156,2,FALSE) -> 15 | J13: 3 | K13: =IF(J13 > 0, VLOOKUP(J13,$AF$3:$AG$103,2,FALSE),0) -> 15 | M13: New | N13: Commit | O13: Tenant Onboarding | P13: S | Q13: 3 | R13: 6 | S13: =(R13+1) - 1 -> 6 | T13: =IF(AND(R13>=1, $A$1 <=1,Q13<=1), (K13/ ((R13 +1) - 1))*(Team!$H$25/10), 0) -> 0 | U13: =IF(AND(R13>=2, $A$1 <=2, Q13<=2), ((K13-T13)/ ((R13 +1) - 2))*(Team!$H$26/10), 0) -> 0 | V13: =IF(AND(R13>=3, $A$1 <=3, Q13<=3), ((K13-(T13+U13))/ ((R13 +1) - 3))*(Team!$H$27/10), 0) -> 3.75 | W13: =IF(AND(R13>=4, $A$1 <=4, Q13<=4), ((K13-(T13+U13+V13))/ ((R13 +1) - 4))*(Team!$H$28/10), 0) -> 3.75 | X13: =IF(AND(R13>=5, $A$1 <5, Q13<=5), ((K13-(T13+U13+V13+W13))/ ((R13 +1) - 5))*(Team!$H$29/10), 0) -> 3.75 | Y13: =IF(AND(R13>=6, $A$1 <6, Q13<=6), ((K13-(T13+U13+V13+W13+X13))/ ((R13 +1) - 6))*(Team!$H$30/10), 0) -> 3.75 | AC13: =(H13-J13)/H13 -> 0 | AD13: =IF(AC13=1, G13,0) -> 0
C14: GRID Automated Data Validations - August 2022 | G14: 6 | H14: 1 | I14: =VLOOKUP(H14,$AF$3:$AG$156,2,FALSE) -> 5 | J14: 1 | K14: =IF(J14 > 0, VLOOKUP(J14,$AF$3:$AG$103,2,FALSE),0) -> 5 | M14: New | N14: Commit | O14: Framework | P14: S | Q14: 5 | R14: 5 | S14: =(R14+1) - 1 -> 5 | T14: =IF(AND(R14>=1, $A$1 <=1,Q14<=1), (K14/ ((R14 +1) - 1))*(Team!$H$25/10), 0) -> 0 | U14: =IF(AND(R14>=2, $A$1 <=2, Q14<=2), ((K14-T14)/ ((R14 +1) - 2))*(Team!$H$26/10), 0) -> 0 | V14: =IF(AND(R14>=3, $A$1 <=3, Q14<=3), ((K14-(T14+U14))/ ((R14 +1) - 3))*(Team!$H$27/10), 0) -> 0 | W14: =IF(AND(R14>=4, $A$1 <=4, Q14<=4), ((K14-(T14+U14+V14))/ ((R14 +1) - 4))*(Team!$H$28/10), 0) -> 0 | X14: =IF(AND(R14>=5, $A$1 <5, Q14<=5), ((K14-(T14+U14+V14+W14))/ ((R14 +1) - 5))*(Team!$H$29/10), 0) -> 5 | Y14: =IF(AND(R14>=6, $A$1 <6, Q14<=6), ((K14-(T14+U14+V14+W14+X14))/ ((R14 +1) - 6))*(Team!$H$30/10), 0) -> 0 | AC14: =(H14-J14)/H14 -> 0 | AD14: =IF(AC14=1, G14,0) -> 0
C15: GRID QA Automation | G15: 8 | H15: 3 | I15: =VLOOKUP(H15,$AF$3:$AG$156,2,FALSE) -> 15 | J15: 3 | K15: =IF(J15 > 0, VLOOKUP(J15,$AF$3:$AG$103,2,FALSE),0) -> 15 | M15: New | N15: Commit | O15: Tenant Onboarding | P15: S | Q15: 3 | R15: 6 | S15: =(R15+1) - 1 -> 6 | T15: =IF(AND(R15>=1, $A$1 <=1,Q15<=1), (K15/ ((R15 +1) - 1))*(Team!$H$25/10), 0) -> 0 | U15: =IF(AND(R15>=2, $A$1 <=2, Q15<=2), ((K15-T15)/ ((R15 +1) - 2))*(Team!$H$26/10), 0) -> 0 | V15: =IF(AND(R15>=3, $A$1 <=3, Q15<=3), ((K15-(T15+U15))/ ((R15 +1) - 3))*(Team!$H$27/10), 0) -> 3.75 | W15: =IF(AND(R15>=4, $A$1 <=4, Q15<=4), ((K15-(T15+U15+V15))/ ((R15 +1) - 4))*(Team!$H$28/10), 0) -> 3.75 | X15: =IF(AND(R15>=5, $A$1 <5, Q15<=5), ((K15-(T15+U15+V15+W15))/ ((R15 +1) - 5))*(Team!$H$29/10), 0) -> 3.75 | Y15: =IF(AND(R15>=6, $A$1 <6, Q15<=6), ((K15-(T15+U15+V15+W15+X15))/ ((R15 +1) - 6))*(Team!$H$30/10), 0) -> 3.75 | AC15: =(H15-J15)/H15 -> 0 | AD15: =IF(AC15=1, G15,0) -> 0
C16: GRID: Reserve capacity for Next PI Planning, System Demo and Innovation | G16: 8 | H16: 1.6 | I16: =VLOOKUP(H16,$AF$3:$AG$156,2,FALSE) -> 8 | J16: 1.6 | K16: =IF(J16 > 0, VLOOKUP(J16,$AF$3:$AG$103,2,FALSE),0) -> 8 | M16: New | N16: Commit | O16: Framework | P16: S | Q16: 5 | R16: 6 | S16: =(R16+1) - 1 -> 6 | T16: =IF(AND(R16>=1, $A$1 <=1,Q16<=1), (K16/ ((R16 +1) - 1))*(Team!$H$25/10), 0) -> 0 | U16: =IF(AND(R16>=2, $A$1 <=2, Q16<=2), ((K16-T16)/ ((R16 +1) - 2))*(Team!$H$26/10), 0) -> 0 | V16: =IF(AND(R16>=3, $A$1 <=3, Q16<=3), ((K16-(T16+U16))/ ((R16 +1) - 3))*(Team!$H$27/10), 0) -> 0 | W16: =IF(AND(R16>=4, $A$1 <=4, Q16<=4), ((K16-(T16+U16+V16))/ ((R16 +1) - 4))*(Team!$H$28/10), 0) -> 0 | X16: =IF(AND(R16>=5, $A$1 <5, Q16<=5), ((K16-(T16+U16+V16+W16))/ ((R16 +1) - 5))*(Team!$H$29/10), 0) -> 4 | Y16: =IF(AND(R16>=6, $A$1 <6, Q16<=6), ((K16-(T16+U16+V16+W16+X16))/ ((R16 +1) - 6))*(Team!$H$30/10), 0) -> 4 | AC16: =(H16-J16)/H16 -> 0 | AD16: =IF(AC16=1, G16,0) -> 0
C17: GRID/IDC Rewiring | G17: 7 | H17: 3 | I17: =VLOOKUP(H17,$AF$3:$AG$156,2,FALSE) -> 15 | J17: 3 | K17: =IF(J17 > 0, VLOOKUP(J17,$AF$3:$AG$103,2,FALSE),0) -> 15 | M17: New | N17: Commit | O17: Framework | P17: S | Q17: 1 | R17: 6 | S17: =(R17+1) - 1 -> 6 | T17: =IF(AND(R17>=1, $A$1 <=1,Q17<=1), (K17/ ((R17 +1) - 1))*(Team!$H$25/10), 0) -> 2.5 | U17: =IF(AND(R17>=2, $A$1 <=2, Q17<=2), ((K17-T17)/ ((R17 +1) - 2))*(Team!$H$26/10), 0) -> 2.5 | V17: =IF(AND(R17>=3, $A$1 <=3, Q17<=3), ((K17-(T17+U17))/ ((R17 +1) - 3))*(Team!$H$27/10), 0) -> 2.5 | W17: =IF(AND(R17>=4, $A$1 <=4, Q17<=4), ((K17-(T17+U17+V17))/ ((R17 +1) - 4))*(Team!$H$28/10), 0) -> 2.5 | X17: =IF(AND(R17>=5, $A$1 <5, Q17<=5), ((K17-(T17+U17+V17+W17))/ ((R17 +1) - 5))*(Team!$H$29/10), 0) -> 2.5 | Y17: =IF(AND(R17>=6, $A$1 <6, Q17<=6), ((K17-(T17+U17+V17+W17+X17))/ ((R17 +1) - 6))*(Team!$H$30/10), 0) -> 2.5 | AC17: =(H17-J17)/H17 -> 0 | AD17: =IF(AC17=1, G17,0) -> 0
C18: GRID REI Historical Load | G18: 7 | H18: 1.6 | I18: =VLOOKUP(H18,$AF$3:$AG$156,2,FALSE) -> 8 | J18: 1.6 | K18: =IF(J18 > 0, VLOOKUP(J18,$AF$3:$AG$103,2,FALSE),0) -> 8 | M18: New | N18: Commit | O18: Framework | P18: S | Q18: 1 | R18: 4 | S18: =(R18+1) - 1 -> 4 | T18: =IF(AND(R18>=1, $A$1 <=1,Q18<=1), (K18/ ((R18 +1) - 1))*(Team!$H$25/10), 0) -> 2 | U18: =IF(AND(R18>=2, $A$1 <=2, Q18<=2), ((K18-T18)/ ((R18 +1) - 2))*(Team!$H$26/10), 0) -> 2 | V18: =IF(AND(R18>=3, $A$1 <=3, Q18<=3), ((K18-(T18+U18))/ ((R18 +1) - 3))*(Team!$H$27/10), 0) -> 2 | W18: =IF(AND(R18>=4, $A$1 <=4, Q18<=4), ((K18-(T18+U18+V18))/ ((R18 +1) - 4))*(Team!$H$28/10), 0) -> 2 | X18: =IF(AND(R18>=5, $A$1 <5, Q18<=5), ((K18-(T18+U18+V18+W18))/ ((R18 +1) - 5))*(Team!$H$29/10), 0) -> 0 | Y18: =IF(AND(R18>=6, $A$1 <6, Q18<=6), ((K18-(T18+U18+V18+W18+X18))/ ((R18 +1) - 6))*(Team!$H$30/10), 0) -> 0 | AC18: =(H18-J18)/H18 -> 0 | AD18: =IF(AC18=1, G18,0) -> 0
C19: GRID/DOS/GRID Adj AM KT | G19: 7 | H19: 1.6 | I19: =VLOOKUP(H19,$AF$3:$AG$156,2,FALSE) -> 8 | J19: 1.6 | K19: =IF(J19 > 0, VLOOKUP(J19,$AF$3:$AG$103,2,FALSE),0) -> 8 | M19: New | N19: Commit | O19: BCP | P19: S | Q19: 1 | R19: 4 | S19: =(R19+1) - 1 -> 4 | T19: =IF(AND(R19>=1, $A$1 <=1,Q19<=1), (K19/ ((R19 +1) - 1))*(Team!$H$25/10), 0) -> 2 | U19: =IF(AND(R19>=2, $A$1 <=2, Q19<=2), ((K19-T19)/ ((R19 +1) - 2))*(Team!$H$26/10), 0) -> 2 | V19: =IF(AND(R19>=3, $A$1 <=3, Q19<=3), ((K19-(T19+U19))/ ((R19 +1) - 3))*(Team!$H$27/10), 0) -> 2 | W19: =IF(AND(R19>=4, $A$1 <=4, Q19<=4), ((K19-(T19+U19+V19))/ ((R19 +1) - 4))*(Team!$H$28/10), 0) -> 2 | X19: =IF(AND(R19>=5, $A$1 <5, Q19<=5), ((K19-(T19+U19+V19+W19))/ ((R19 +1) - 5))*(Team!$H$29/10), 0) -> 0 | Y19: =IF(AND(R19>=6, $A$1 <6, Q19<=6), ((K19-(T19+U19+V19+W19+X19))/ ((R19 +1) - 6))*(Team!$H$30/10), 0) -> 0 | AC19: =(H19-J19)/H19 -> 0 | AD19: =IF(AC19=1, G19,0) -> 0
C20: GRID IDC AllVue | G20: 7 | H20: 2 | I20: =VLOOKUP(H20,$AF$3:$AG$156,2,FALSE) -> 10 | J20: 2 | K20: =IF(J20 > 0, VLOOKUP(J20,$AF$3:$AG$103,2,FALSE),0) -> 10 | M20: New | N20: Commit | O20: Framework | P20: S | Q20: 1 | R20: 4 | S20: 2 | T20: =IF(AND(R20>=1, $A$1 <=1,Q20<=1), (K20/ ((R20 +1) - 1))*(Team!$H$25/10), 0) -> 2.5 | U20: =IF(AND(R20>=2, $A$1 <=2, Q20<=2), ((K20-T20)/ ((R20 +1) - 2))*(Team!$H$26/10), 0) -> 2.5 | V20: =IF(AND(R20>=3, $A$1 <=3, Q20<=3), ((K20-(T20+U20))/ ((R20 +1) - 3))*(Team!$H$27/10), 0) -> 2.5 | W20: =IF(AND(R20>=4, $A$1 <=4, Q20<=4), ((K20-(T20+U20+V20))/ ((R20 +1) - 4))*(Team!$H$28/10), 0) -> 2.5 | X20: =IF(AND(R20>=5, $A$1 <5, Q20<=5), ((K20-(T20+U20+V20+W20))/ ((R20 +1) - 5))*(Team!$H$29/10), 0) -> 0 | Y20: =IF(AND(R20>=6, $A$1 <6, Q20<=6), ((K20-(T20+U20+V20+W20+X20))/ ((R20 +1) - 6))*(Team!$H$30/10), 0) -> 0 | AC20: =(H20-J20)/H20 -> 0 | AD20: =IF(AC20=1, G20,0) -> 0
C21: GRID ESG Star | G21: 7 | H21: 0.6 | I21: =VLOOKUP(H21,$AF$3:$AG$156,2,FALSE) -> 3 | J21: 0.6 | K21: =IF(J21 > 0, VLOOKUP(J21,$AF$3:$AG$103,2,FALSE),0) -> 3 | M21: New | N21: Commit | O21: Framework | P21: S | Q21: 1 | R21: 4 | S21: =(R21+1) - 1 -> 4 | T21: =IF(AND(R21>=1, $A$1 <=1,Q21<=1), (K21/ ((R21 +1) - 1))*(Team!$H$25/10), 0) -> 0.75 | U21: =IF(AND(R21>=2, $A$1 <=2, Q21<=2), ((K21-T21)/ ((R21 +1) - 2))*(Team!$H$26/10), 0) -> 0.75 | V21: =IF(AND(R21>=3, $A$1 <=3, Q21<=3), ((K21-(T21+U21))/ ((R21 +1) - 3))*(Team!$H$27/10), 0) -> 0.75 | W21: =IF(AND(R21>=4, $A$1 <=4, Q21<=4), ((K21-(T21+U21+V21))/ ((R21 +1) - 4))*(Team!$H$28/10), 0) -> 0.75 | X21: =IF(AND(R21>=5, $A$1 <5, Q21<=5), ((K21-(T21+U21+V21+W21))/ ((R21 +1) - 5))*(Team!$H$29/10), 0) -> 0 | Y21: =IF(AND(R21>=6, $A$1 <6, Q21<=6), ((K21-(T21+U21+V21+W21+X21))/ ((R21 +1) - 6))*(Team!$H$30/10), 0) -> 0 | AC21: =(H21-J21)/H21 -> 0 | AD21: =IF(AC21=1, G21,0) -> 0
C22: GRID-Future State Data Project-1 | G22: 9 | H22: 10 | I22: =VLOOKUP(H22,$AF$3:$AG$156,2,FALSE) -> 55 | J22: 10 | K22: =IF(J22 > 0, VLOOKUP(J22,$AF$3:$AG$103,2,FALSE),0) -> 55 | M22: New | N22: Commit | O22: Innovation | P22: S | Q22: 2 | R22: 5 | S22: =(R22+1) - 1 -> 5 | T22: =IF(AND(R22>=1, $A$1 <=1,Q22<=1), (K22/ ((R22 +1) - 1))*(Team!$H$25/10), 0) -> 0 | U22: =IF(AND(R22>=2, $A$1 <=2, Q22<=2), ((K22-T22)/ ((R22 +1) - 2))*(Team!$H$26/10), 0) -> 13.75 | V22: =IF(AND(R22>=3, $A$1 <=3, Q22<=3), ((K22-(T22+U22))/ ((R22 +1) - 3))*(Team!$H$27/10), 0) -> 13.75 | W22: =IF(AND(R22>=4, $A$1 <=4, Q22<=4), ((K22-(T22+U22+V22))/ ((R22 +1) - 4))*(Team!$H$28/10), 0) -> 13.75 | X22: =IF(AND(R22>=5, $A$1 <5, Q22<=5), ((K22-(T22+U22+V22+W22))/ ((R22 +1) - 5))*(Team!$H$29/10), 0) -> 13.75 | Y22: =IF(AND(R22>=6, $A$1 <6, Q22<=6), ((K22-(T22+U22+V22+W22+X22))/ ((R22 +1) - 6))*(Team!$H$30/10), 0) -> 0
C23: GRID-Future State Data Project - 2 | G23: 9 | H23: 4 | I23: =VLOOKUP(H23,$AF$3:$AG$156,2,FALSE) -> 20 | J23: 4 | K23: =IF(J23 > 0, VLOOKUP(J23,$AF$3:$AG$103,2,FALSE),0) -> 20 | M23: New | N23: Commit | O23: Innovation | P23: S | Q23: 6 | R23: 6 | S23: =(R23+1) - 1 -> 6 | T23: =IF(AND(R23>=1, $A$1 <=1,Q23<=1), (K23/ ((R23 +1) - 1))*(Team!$H$25/10), 0) -> 0 | U23: =IF(AND(R23>=2, $A$1 <=2, Q23<=2), ((K23-T23)/ ((R23 +1) - 2))*(Team!$H$26/10), 0) -> 0 | V23: =IF(AND(R23>=3, $A$1 <=3, Q23<=3), ((K23-(T23+U23))/ ((R23 +1) - 3))*(Team!$H$27/10), 0) -> 0 | W23: =IF(AND(R23>=4, $A$1 <=4, Q23<=4), ((K23-(T23+U23+V23))/ ((R23 +1) - 4))*(Team!$H$28/10), 0) -> 0 | X23: =IF(AND(R23>=5, $A$1 <5, Q23<=5), ((K23-(T23+U23+V23+W23))/ ((R23 +1) - 5))*(Team!$H$29/10), 0) -> 0 | Y23: =IF(AND(R23>=6, $A$1 <6, Q23<=6), ((K23-(T23+U23+V23+W23+X23))/ ((R23 +1) - 6))*(Team!$H$30/10), 0) -> 20
C24: GRID - IDC Data Project - Client Reporting | G24: 7 | H24: 3 | I24: =VLOOKUP(H24,$AF$3:$AG$156,2,FALSE) -> 15 | J24: 3 | K24: =IF(J24 > 0, VLOOKUP(J24,$AF$3:$AG$103,2,FALSE),0) -> 15 | M24: New | N24: Commit | O24: BAU | P24: S | Q24: 4 | R24: 6 | S24: =(R24-Q24) + 1 -> 3 | T24: =IF(AND(R24>=1, $A$1 <=1,Q24<=1), (K24/ ((R24 +1) - 1))*(Team!$H$25/10), 0) -> 0 | U24: =IF(AND(R24>=2, $A$1 <=2, Q24<=2), ((K24-T24)/ ((R24 +1) - 2))*(Team!$H$26/10), 0) -> 0 | V24: =IF(AND(R24>=3, $A$1 <=3, Q24<=3), ((K24-(T24+U24))/ ((R24 +1) - 3))*(Team!$H$27/10), 0) -> 0 | W24: =IF(AND(R24>=4, $A$1 <=4, Q24<=4), ((K24-(T24+U24+V24))/ ((R24 +1) - 4))*(Team!$H$28/10), 0) -> 5 | X24: =IF(AND(R24>=5, $A$1 <5, Q24<=5), ((K24-(T24+U24+V24+W24))/ ((R24 +1) - 5))*(Team!$H$29/10), 0) -> 5 | Y24: =IF(AND(R24>=6, $A$1 <6, Q24<=6), ((K24-(T24+U24+V24+W24+X24))/ ((R24 +1) - 6))*(Team!$H$30/10), 0) -> 5 | AC24: =(H24-J24)/H24 -> 0 | AD24: =IF(AC24=1, G24,0) -> 0
C25: DOS - BAU 2022.05 Release (May 2022) | G25: 8 | H25: 3 | I25: =VLOOKUP(H25,$AF$3:$AG$156,2,FALSE) -> 15 | J25: 3 | K25: =IF(J25 > 0, VLOOKUP(J25,$AF$3:$AG$103,2,FALSE),0) -> 15 | M25: New | N25: Commit | O25: BAU | P25: S | Q25: 1 | R25: 2 | S25: =(R25+1) - 1 -> 2 | T25: =IF(AND(R25>=1, $A$1 <=1,Q25<=1), (K25/ ((R25 +1) - 1))*(Team!$H$25/10), 0) -> 7.5 | U25: =IF(AND(R25>=2, $A$1 <=2, Q25<=2), ((K25-T25)/ ((R25 +1) - 2))*(Team!$H$26/10), 0) -> 7.5 | V25: =IF(AND(R25>=3, $A$1 <=3, Q25<=3), ((K25-(T25+U25))/ ((R25 +1) - 3))*(Team!$H$27/10), 0) -> 0 | W25: =IF(AND(R25>=4, $A$1 <=4, Q25<=4), ((K25-(T25+U25+V25))/ ((R25 +1) - 4))*(Team!$H$28/10), 0) -> 0 | X25: =IF(AND(R25>=5, $A$1 <5, Q25<=5), ((K25-(T25+U25+V25+W25))/ ((R25 +1) - 5))*(Team!$H$29/10), 0) -> 0 | Y25: =IF(AND(R25>=6, $A$1 <6, Q25<=6), ((K25-(T25+U25+V25+W25+X25))/ ((R25 +1) - 6))*(Team!$H$30/10), 0) -> 0 | AC25: =(H25-J25)/H25 -> 0 | AD25: =IF(AC25=1, G25,0) -> 0
C26: DOS - BAU 2022.06 Release (June 2022) | G26: 8 | H26: 4 | I26: =VLOOKUP(H26,$AF$3:$AG$156,2,FALSE) -> 20 | J26: 4 | K26: =IF(J26 > 0, VLOOKUP(J26,$AF$3:$AG$103,2,FALSE),0) -> 20 | M26: New | N26: Commit | O26: BAU | P26: S | Q26: 1 | R26: 4 | S26: =(R26+1) - 1 -> 4 | T26: =IF(AND(R26>=1, $A$1 <=1,Q26<=1), (K26/ ((R26 +1) - 1))*(Team!$H$25/10), 0) -> 5 | U26: =IF(AND(R26>=2, $A$1 <=2, Q26<=2), ((K26-T26)/ ((R26 +1) - 2))*(Team!$H$26/10), 0) -> 5 | V26: =IF(AND(R26>=3, $A$1 <=3, Q26<=3), ((K26-(T26+U26))/ ((R26 +1) - 3))*(Team!$H$27/10), 0) -> 5 | W26: =IF(AND(R26>=4, $A$1 <=4, Q26<=4), ((K26-(T26+U26+V26))/ ((R26 +1) - 4))*(Team!$H$28/10), 0) -> 5 | X26: =IF(AND(R26>=5, $A$1 <5, Q26<=5), ((K26-(T26+U26+V26+W26))/ ((R26 +1) - 5))*(Team!$H$29/10), 0) -> 0 | Y26: =IF(AND(R26>=6, $A$1 <6, Q26<=6), ((K26-(T26+U26+V26+W26+X26))/ ((R26 +1) - 6))*(Team!$H$30/10), 0) -> 0 | AC26: =(H26-J26)/H26 -> 0 | AD26: =IF(AC26=1, G26,0) -> 0
C27: DOS - BAU 2022.07 Release (July 2022) | G27: 8 | H27: 4 | I27: =VLOOKUP(H27,$AF$3:$AG$156,2,FALSE) -> 20 | J27: 4 | K27: =IF(J27 > 0, VLOOKUP(J27,$AF$3:$AG$103,2,FALSE),0) -> 20 | M27: New | N27: Commit | O27: BAU | P27: S | Q27: 3 | R27: 6 | S27: =(R27+1) - 1 -> 6 | T27: =IF(AND(R27>=1, $A$1 <=1,Q27<=1), (K27/ ((R27 +1) - 1))*(Team!$H$25/10), 0) -> 0 | U27: =IF(AND(R27>=2, $A$1 <=2, Q27<=2), ((K27-T27)/ ((R27 +1) - 2))*(Team!$H$26/10), 0) -> 0 | V27: =IF(AND(R27>=3, $A$1 <=3, Q27<=3), ((K27-(T27+U27))/ ((R27 +1) - 3))*(Team!$H$27/10), 0) -> 5 | W27: =IF(AND(R27>=4, $A$1 <=4, Q27<=4), ((K27-(T27+U27+V27))/ ((R27 +1) - 4))*(Team!$H$28/10), 0) -> 5 | X27: =IF(AND(R27>=5, $A$1 <5, Q27<=5), ((K27-(T27+U27+V27+W27))/ ((R27 +1) - 5))*(Team!$H$29/10), 0) -> 5 | Y27: =IF(AND(R27>=6, $A$1 <6, Q27<=6), ((K27-(T27+U27+V27+W27+X27))/ ((R27 +1) - 6))*(Team!$H$30/10), 0) -> 5 | AC27: =(H27-J27)/H27 -> 0 | AD27: =IF(AC27=1, G27,0) -> 0
C28: DOS - BAU 2022.08 Release (August 2022) | G28: 7 | H28: 4 | I28: =VLOOKUP(H28,$AF$3:$AG$156,2,FALSE) -> 20 | J28: 4 | K28: =IF(J28 > 0, VLOOKUP(J28,$AF$3:$AG$103,2,FALSE),0) -> 20 | M28: New | N28: Commit | O28: Framework | P28: S | Q28: 5 | R28: 5 | S28: =(R28-Q28) + 1 -> 1 | T28: =IF(AND(R28>=1, $A$1 <=1,Q28<=1), (K28/ ((R28 +1) - 1))*(Team!$H$25/10), 0) -> 0 | U28: =IF(AND(R28>=2, $A$1 <=2, Q28<=2), ((K28-T28)/ ((R28 +1) - 2))*(Team!$H$26/10), 0) -> 0 | V28: =IF(AND(R28>=3, $A$1 <=3, Q28<=3), ((K28-(T28+U28))/ ((R28 +1) - 3))*(Team!$H$27/10), 0) -> 0 | W28: =IF(AND(R28>=4, $A$1 <=4, Q28<=4), ((K28-(T28+U28+V28))/ ((R28 +1) - 4))*(Team!$H$28/10), 0) -> 0 | X28: =IF(AND(R28>=5, $A$1 <5, Q28<=5), ((K28-(T28+U28+V28+W28))/ ((R28 +1) - 5))*(Team!$H$29/10), 0) -> 20 | Y28: =IF(AND(R28>=6, $A$1 <6, Q28<=6), ((K28-(T28+U28+V28+W28+X28))/ ((R28 +1) - 6))*(Team!$H$30/10), 0) -> 0 | AC28: =(H28-J28)/H28 -> 0 | AD28: =IF(AC28=1, G28,0) -> 0
C29: DOS Databricks Optimization | G29: 7 | H29: 1.6 | I29: =VLOOKUP(H29,$AF$3:$AG$156,2,FALSE) -> 8 | J29: 1.6 | K29: =IF(J29 > 0, VLOOKUP(J29,$AF$3:$AG$103,2,FALSE),0) -> 8 | M29: New | N29: Commit | O29: Framework | P29: S | Q29: 1 | R29: 4 | S29: =(R29-Q29) + 1 -> 4 | T29: =IF(AND(R29>=1, $A$1 <=1,Q29<=1), (K29/ ((R29 +1) - 1))*(Team!$H$25/10), 0) -> 2 | U29: =IF(AND(R29>=2, $A$1 <=2, Q29<=2), ((K29-T29)/ ((R29 +1) - 2))*(Team!$H$26/10), 0) -> 2 | V29: =IF(AND(R29>=3, $A$1 <=3, Q29<=3), ((K29-(T29+U29))/ ((R29 +1) - 3))*(Team!$H$27/10), 0) -> 2 | W29: =IF(AND(R29>=4, $A$1 <=4, Q29<=4), ((K29-(T29+U29+V29))/ ((R29 +1) - 4))*(Team!$H$28/10), 0) -> 2 | X29: =IF(AND(R29>=5, $A$1 <5, Q29<=5), ((K29-(T29+U29+V29+W29))/ ((R29 +1) - 5))*(Team!$H$29/10), 0) -> 0 | Y29: =IF(AND(R29>=6, $A$1 <6, Q29<=6), ((K29-(T29+U29+V29+W29+X29))/ ((R29 +1) - 6))*(Team!$H$30/10), 0) -> 0 | AC29: =(H29-J29)/H29 -> 0 | AD29: =IF(AC29=1, G29,0) -> 0
C30: DOS Residential | G30: 8 | H30: 1.6 | I30: =VLOOKUP(H30,$AF$3:$AG$156,2,FALSE) -> 8 | J30: 1.6 | K30: =IF(J30 > 0, VLOOKUP(J30,$AF$3:$AG$103,2,FALSE),0) -> 8 | M30: New | N30: Commit | O30: Framework | P30: S | Q30: 1 | R30: 3 | S30: =(R30-Q30) + 1 -> 3 | T30: =IF(AND(R30>=1, $A$1 <=1,Q30<=1), (K30/ ((R30 +1) - 1))*(Team!$H$25/10), 0) -> 2.6666667 | U30: =IF(AND(R30>=2, $A$1 <=2, Q30<=2), ((K30-T30)/ ((R30 +1) - 2))*(Team!$H$26/10), 0) -> 2.6666667 | V30: =IF(AND(R30>=3, $A$1 <=3, Q30<=3), ((K30-(T30+U30))/ ((R30 +1) - 3))*(Team!$H$27/10), 0) -> 2.6666667 | W30: =IF(AND(R30>=4, $A$1 <=4, Q30<=4), ((K30-(T30+U30+V30))/ ((R30 +1) - 4))*(Team!$H$28/10), 0) -> 0 | X30: =IF(AND(R30>=5, $A$1 <5, Q30<=5), ((K30-(T30+U30+V30+W30))/ ((R30 +1) - 5))*(Team!$H$29/10), 0) -> 0 | Y30: =IF(AND(R30>=6, $A$1 <6, Q30<=6), ((K30-(T30+U30+V30+W30+X30))/ ((R30 +1) - 6))*(Team!$H$30/10), 0) -> 0
C31: DOS RE Equity | G31: 8 | H31: 1.6 | I31: =VLOOKUP(H31,$AF$3:$AG$156,2,FALSE) -> 8 | J31: 1.6 | K31: =IF(J31 > 0, VLOOKUP(J31,$AF$3:$AG$103,2,FALSE),0) -> 8 | M31: New | N31: Commit | O31: Framework | P31: S | Q31: 5 | R31: 6 | S31: =(R31-Q31) + 1 -> 2 | T31: =IF(AND(R31>=1, $A$1 <=1,Q31<=1), (K31/ ((R31 +1) - 1))*(Team!$H$25/10), 0) -> 0 | U31: =IF(AND(R31>=2, $A$1 <=2, Q31<=2), ((K31-T31)/ ((R31 +1) - 2))*(Team!$H$26/10), 0) -> 0 | V31: =IF(AND(R31>=3, $A$1 <=3, Q31<=3), ((K31-(T31+U31))/ ((R31 +1) - 3))*(Team!$H$27/10), 0) -> 0 | W31: =IF(AND(R31>=4, $A$1 <=4, Q31<=4), ((K31-(T31+U31+V31))/ ((R31 +1) - 4))*(Team!$H$28/10), 0) -> 0 | X31: =IF(AND(R31>=5, $A$1 <5, Q31<=5), ((K31-(T31+U31+V31+W31))/ ((R31 +1) - 5))*(Team!$H$29/10), 0) -> 4 | Y31: =IF(AND(R31>=6, $A$1 <6, Q31<=6), ((K31-(T31+U31+V31+W31+X31))/ ((R31 +1) - 6))*(Team!$H$30/10), 0) -> 4
C32: DOS QA Automation | G32: 9 | H32: 3 | I32: =VLOOKUP(H32,$AF$3:$AG$156,2,FALSE) -> 15 | J32: 3 | K32: =IF(J32 > 0, VLOOKUP(J32,$AF$3:$AG$103,2,FALSE),0) -> 15 | M32: New | N32: Commit | O32: Framework | P32: S | Q32: 1 | R32: 6 | S32: =(R32-Q32) + 1 -> 6 | T32: =IF(AND(R32>=1, $A$1 <=1,Q32<=1), (K32/ ((R32 +1) - 1))*(Team!$H$25/10), 0) -> 2.5 | U32: =IF(AND(R32>=2, $A$1 <=2, Q32<=2), ((K32-T32)/ ((R32 +1) - 2))*(Team!$H$26/10), 0) -> 2.5 | V32: =IF(AND(R32>=3, $A$1 <=3, Q32<=3), ((K32-(T32+U32))/ ((R32 +1) - 3))*(Team!$H$27/10), 0) -> 2.5 | W32: =IF(AND(R32>=4, $A$1 <=4, Q32<=4), ((K32-(T32+U32+V32))/ ((R32 +1) - 4))*(Team!$H$28/10), 0) -> 2.5 | X32: =IF(AND(R32>=5, $A$1 <5, Q32<=5), ((K32-(T32+U32+V32+W32))/ ((R32 +1) - 5))*(Team!$H$29/10), 0) -> 2.5 | Y32: =IF(AND(R32>=6, $A$1 <6, Q32<=6), ((K32-(T32+U32+V32+W32+X32))/ ((R32 +1) - 6))*(Team!$H$30/10), 0) -> 2.5
C33: DOS Release On Demand | G33: 8 | H33: 1.6 | I33: =VLOOKUP(H33,$AF$3:$AG$156,2,FALSE) -> 8 | J33: 1.6 | K33: =IF(J33 > 0, VLOOKUP(J33,$AF$3:$AG$103,2,FALSE),0) -> 8 | M33: New | N33: Commit | O33: Framework | P33: S | Q33: 5 | R33: 6 | S33: =(R33-Q33) + 1 -> 2 | T33: =IF(AND(R33>=1, $A$1 <=1,Q33<=1), (K33/ ((R33 +1) - 1))*(Team!$H$25/10), 0) -> 0 | U33: =IF(AND(R33>=2, $A$1 <=2, Q33<=2), ((K33-T33)/ ((R33 +1) - 2))*(Team!$H$26/10), 0) -> 0 | V33: =IF(AND(R33>=3, $A$1 <=3, Q33<=3), ((K33-(T33+U33))/ ((R33 +1) - 3))*(Team!$H$27/10), 0) -> 0 | W33: =IF(AND(R33>=4, $A$1 <=4, Q33<=4), ((K33-(T33+U33+V33))/ ((R33 +1) - 4))*(Team!$H$28/10), 0) -> 0 | X33: =IF(AND(R33>=5, $A$1 <5, Q33<=5), ((K33-(T33+U33+V33+W33))/ ((R33 +1) - 5))*(Team!$H$29/10), 0) -> 4 | Y33: =IF(AND(R33>=6, $A$1 <6, Q33<=6), ((K33-(T33+U33+V33+W33+X33))/ ((R33 +1) - 6))*(Team!$H$30/10), 0) -> 4
C34: DOS: Reserve capacity for Next PI Planning, System Demo and Innovation | G34: 6 | H34: 1.6 | I34: =VLOOKUP(H34,$AF$3:$AG$156,2,FALSE) -> 8 | J34: 1.6 | K34: =IF(J34 > 0, VLOOKUP(J34,$AF$3:$AG$103,2,FALSE),0) -> 8 | M34: New | N34: Commit | O34: BAU | P34: S | Q34: 5 | R34: 6 | S34: =(R34-Q34) + 1 -> 2 | T34: =IF(AND(R34>=1, $A$1 <=1,Q34<=1), (K34/ ((R34 +1) - 1))*(Team!$H$25/10), 0) -> 0 | U34: =IF(AND(R34>=2, $A$1 <=2, Q34<=2), ((K34-T34)/ ((R34 +1) - 2))*(Team!$H$26/10), 0) -> 0 | V34: =IF(AND(R34>=3, $A$1 <=3, Q34<=3), ((K34-(T34+U34))/ ((R34 +1) - 3))*(Team!$H$27/10), 0) -> 0 | W34: =IF(AND(R34>=4, $A$1 <=4, Q34<=4), ((K34-(T34+U34+V34))/ ((R34 +1) - 4))*(Team!$H$28/10), 0) -> 0 | X34: =IF(AND(R34>=5, $A$1 <5, Q34<=5), ((K34-(T34+U34+V34+W34))/ ((R34 +1) - 5))*(Team!$H$29/10), 0) -> 4 | Y34: =IF(AND(R34>=6, $A$1 <6, Q34<=6), ((K34-(T34+U34+V34+W34+X34))/ ((R34 +1) - 6))*(Team!$H$30/10), 0) -> 4 | AC34: =(H34-J34)/H34 -> 0 | AD34: =IF(AC34=1, G34,0) -> 0
C35: DOS IDC Rewiring | G35: 7 | H35: 1.6 | I35: =VLOOKUP(H35,$AF$3:$AG$156,2,FALSE) -> 8 | J35: 1.6 | K35: =IF(J35 > 0, VLOOKUP(J35,$AF$3:$AG$103,2,FALSE),0) -> 8 | M35: New | N35: Commit | O35: BAU | P35: S | Q35: 5 | R35: 6 | S35: =(R35-Q35) + 1 -> 2 | T35: =IF(AND(R35>=1, $A$1 <=1,Q35<=1), (K35/ ((R35 +1) - 1))*(Team!$H$25/10), 0) -> 0 | U35: =IF(AND(R35>=2, $A$1 <=2, Q35<=2), ((K35-T35)/ ((R35 +1) - 2))*(Team!$H$26/10), 0) -> 0 | V35: =IF(AND(R35>=3, $A$1 <=3, Q35<=3), ((K35-(T35+U35))/ ((R35 +1) - 3))*(Team!$H$27/10), 0) -> 0 | W35: =IF(AND(R35>=4, $A$1 <=4, Q35<=4), ((K35-(T35+U35+V35))/ ((R35 +1) - 4))*(Team!$H$28/10), 0) -> 0 | X35: =IF(AND(R35>=5, $A$1 <5, Q35<=5), ((K35-(T35+U35+V35+W35))/ ((R35 +1) - 5))*(Team!$H$29/10), 0) -> 4 | Y35: =IF(AND(R35>=6, $A$1 <6, Q35<=6), ((K35-(T35+U35+V35+W35+X35))/ ((R35 +1) - 6))*(Team!$H$30/10), 0) -> 4 | AC35: =(H35-J35)/H35 -> 0 | AD35: =IF(AC35=1, G35,0) -> 0
C36: DOS ESG Star | G36: 7 | H36: 0.6 | I36: =VLOOKUP(H36,$AF$3:$AG$156,2,FALSE) -> 3 | J36: 0.6 | K36: =IF(J36 > 0, VLOOKUP(J36,$AF$3:$AG$103,2,FALSE),0) -> 3 | M36: New | N36: Commit | O36: Framework | P36: S | Q36: 2 | R36: 4 | S36: =(R36-Q36) + 1 -> 3 | T36: =IF(AND(R36>=1, $A$1 <=1,Q36<=1), (K36/ ((R36 +1) - 1))*(Team!$H$25/10), 0) -> 0 | U36: =IF(AND(R36>=2, $A$1 <=2, Q36<=2), ((K36-T36)/ ((R36 +1) - 2))*(Team!$H$26/10), 0) -> 1 | V36: =IF(AND(R36>=3, $A$1 <=3, Q36<=3), ((K36-(T36+U36))/ ((R36 +1) - 3))*(Team!$H$27/10), 0) -> 1 | W36: =IF(AND(R36>=4, $A$1 <=4, Q36<=4), ((K36-(T36+U36+V36))/ ((R36 +1) - 4))*(Team!$H$28/10), 0) -> 1 | X36: =IF(AND(R36>=5, $A$1 <5, Q36<=5), ((K36-(T36+U36+V36+W36))/ ((R36 +1) - 5))*(Team!$H$29/10), 0) -> 0 | Y36: =IF(AND(R36>=6, $A$1 <6, Q36<=6), ((K36-(T36+U36+V36+W36+X36))/ ((R36 +1) - 6))*(Team!$H$30/10), 0) -> 0
C37: PROOF: Reserve capacity for Next PI Planning, System Demo and Innovation | G37: 7 | H37: 1.6 | I37: =VLOOKUP(H37,$AF$3:$AG$156,2,FALSE) -> 8 | J37: 1.6 | K37: =IF(J37 > 0, VLOOKUP(J37,$AF$3:$AG$103,2,FALSE),0) -> 8 | M37: New | N37: Commit | O37: Framework | P37: N | Q37: 2 | R37: 3 | S37: =(R37-Q37) + 1 -> 2 | T37: =IF(AND(R37>=1, $A$1 <=1,Q37<=1), (K37/ ((R37 +1) - 1))*(Team!$H$25/10), 0) -> 0 | U37: =IF(AND(R37>=2, $A$1 <=2, Q37<=2), ((K37-T37)/ ((R37 +1) - 2))*(Team!$H$26/10), 0) -> 4 | V37: =IF(AND(R37>=3, $A$1 <=3, Q37<=3), ((K37-(T37+U37))/ ((R37 +1) - 3))*(Team!$H$27/10), 0) -> 4 | W37: =IF(AND(R37>=4, $A$1 <=4, Q37<=4), ((K37-(T37+U37+V37))/ ((R37 +1) - 4))*(Team!$H$28/10), 0) -> 0 | X37: =IF(AND(R37>=5, $A$1 <5, Q37<=5), ((K37-(T37+U37+V37+W37))/ ((R37 +1) - 5))*(Team!$H$29/10), 0) -> 0 | Y37: =IF(AND(R37>=6, $A$1 <6, Q37<=6), ((K37-(T37+U37+V37+W37+X37))/ ((R37 +1) - 6))*(Team!$H$30/10), 0) -> 0
C38: IDC: Phase 2 : Design part 1 | G38: 6 | H38: 1 | I38: =VLOOKUP(H38,$AF$3:$AG$156,2,FALSE) -> 5 | J38: 1 | K38: =IF(J38 > 0, VLOOKUP(J38,$AF$3:$AG$103,2,FALSE),0) -> 5 | M38: New | N38: Commit | O38: Framework | P38: N | Q38: 1 | R38: 6 | S38: =(R38-Q38) + 1 -> 6 | T38: =IF(AND(R38>=1, $A$1 <=1,Q38<=1), (K38/ ((R38 +1) - 1))*(Team!$H$25/10), 0) -> 0.83333333 | U38: =IF(AND(R38>=2, $A$1 <=2, Q38<=2), ((K38-T38)/ ((R38 +1) - 2))*(Team!$H$26/10), 0) -> 0.83333333 | V38: =IF(AND(R38>=3, $A$1 <=3, Q38<=3), ((K38-(T38+U38))/ ((R38 +1) - 3))*(Team!$H$27/10), 0) -> 0.83333333 | W38: =IF(AND(R38>=4, $A$1 <=4, Q38<=4), ((K38-(T38+U38+V38))/ ((R38 +1) - 4))*(Team!$H$28/10), 0) -> 0.83333333 | X38: =IF(AND(R38>=5, $A$1 <5, Q38<=5), ((K38-(T38+U38+V38+W38))/ ((R38 +1) - 5))*(Team!$H$29/10), 0) -> 0.83333333 | Y38: =IF(AND(R38>=6, $A$1 <6, Q38<=6), ((K38-(T38+U38+V38+W38+X38))/ ((R38 +1) - 6))*(Team!$H$30/10), 0) -> 0.83333333
C39: IDC: Phase 2: Implementation - Part 1 | G39: 6 | H39: 1 | I39: =VLOOKUP(H39,$AF$3:$AG$156,2,FALSE) -> 5 | J39: 1 | K39: =IF(J39 > 0, VLOOKUP(J39,$AF$3:$AG$103,2,FALSE),0) -> 5 | M39: New | N39: Commit | O39: Framework | P39: N | Q39: 1 | R39: 6 | S39: =(R39-Q39) + 1 -> 6 | T39: =IF(AND(R39>=1, $A$1 <=1,Q39<=1), (K39/ ((R39 +1) - 1))*(Team!$H$25/10), 0) -> 0.83333333 | U39: =IF(AND(R39>=2, $A$1 <=2, Q39<=2), ((K39-T39)/ ((R39 +1) - 2))*(Team!$H$26/10), 0) -> 0.83333333 | V39: =IF(AND(R39>=3, $A$1 <=3, Q39<=3), ((K39-(T39+U39))/ ((R39 +1) - 3))*(Team!$H$27/10), 0) -> 0.83333333 | W39: =IF(AND(R39>=4, $A$1 <=4, Q39<=4), ((K39-(T39+U39+V39))/ ((R39 +1) - 4))*(Team!$H$28/10), 0) -> 0.83333333 | X39: =IF(AND(R39>=5, $A$1 <5, Q39<=5), ((K39-(T39+U39+V39+W39))/ ((R39 +1) - 5))*(Team!$H$29/10), 0) -> 0.83333333 | Y39: =IF(AND(R39>=6, $A$1 <6, Q39<=6), ((K39-(T39+U39+V39+W39+X39))/ ((R39 +1) - 6))*(Team!$H$30/10), 0) -> 0.83333333
C40: IDC: Phase 2 -Implementation API for query designer | G40: 9 | H40: 4 | I40: =VLOOKUP(H40,$AF$3:$AG$156,2,FALSE) -> 20 | J40: 4 | K40: =IF(J40 > 0, VLOOKUP(J40,$AF$3:$AG$103,2,FALSE),0) -> 20 | M40: New | N40: Commit | O40: Framework | P40: N | Q40: 1 | R40: 6 | S40: =(R40-Q40) + 1 -> 6 | T40: =IF(AND(R40>=1, $A$1 <=1,Q40<=1), (K40/ ((R40 +1) - 1))*(Team!$H$25/10), 0) -> 3.3333333 | U40: =IF(AND(R40>=2, $A$1 <=2, Q40<=2), ((K40-T40)/ ((R40 +1) - 2))*(Team!$H$26/10), 0) -> 3.3333333 | V40: =IF(AND(R40>=3, $A$1 <=3, Q40<=3), ((K40-(T40+U40))/ ((R40 +1) - 3))*(Team!$H$27/10), 0) -> 3.3333333 | W40: =IF(AND(R40>=4, $A$1 <=4, Q40<=4), ((K40-(T40+U40+V40))/ ((R40 +1) - 4))*(Team!$H$28/10), 0) -> 3.3333333 | X40: =IF(AND(R40>=5, $A$1 <5, Q40<=5), ((K40-(T40+U40+V40+W40))/ ((R40 +1) - 5))*(Team!$H$29/10), 0) -> 3.3333333 | Y40: =IF(AND(R40>=6, $A$1 <6, Q40<=6), ((K40-(T40+U40+V40+W40+X40))/ ((R40 +1) - 6))*(Team!$H$30/10), 0) -> 3.3333333
C41: IDC: Phase 2 -Implementation of query designer db | G41: 9 | H41: 4 | I41: =VLOOKUP(H41,$AF$3:$AG$156,2,FALSE) -> 20 | J41: 4 | K41: =IF(J41 > 0, VLOOKUP(J41,$AF$3:$AG$103,2,FALSE),0) -> 20 | M41: New | N41: Commit | O41: Framework | P41: N | Q41: 1 | R41: 6 | S41: =(R41-Q41) + 1 -> 6 | T41: =IF(AND(R41>=1, $A$1 <=1,Q41<=1), (K41/ ((R41 +1) - 1))*(Team!$H$25/10), 0) -> 3.3333333 | U41: =IF(AND(R41>=2, $A$1 <=2, Q41<=2), ((K41-T41)/ ((R41 +1) - 2))*(Team!$H$26/10), 0) -> 3.3333333 | V41: =IF(AND(R41>=3, $A$1 <=3, Q41<=3), ((K41-(T41+U41))/ ((R41 +1) - 3))*(Team!$H$27/10), 0) -> 3.3333333 | W41: =IF(AND(R41>=4, $A$1 <=4, Q41<=4), ((K41-(T41+U41+V41))/ ((R41 +1) - 4))*(Team!$H$28/10), 0) -> 3.3333333 | X41: =IF(AND(R41>=5, $A$1 <5, Q41<=5), ((K41-(T41+U41+V41+W41))/ ((R41 +1) - 5))*(Team!$H$29/10), 0) -> 3.3333333 | Y41: =IF(AND(R41>=6, $A$1 <6, Q41<=6), ((K41-(T41+U41+V41+W41+X41))/ ((R41 +1) - 6))*(Team!$H$30/10), 0) -> 3.3333333
C42: IDC: Phase 2 -Implementation of Validation of Query Definition | G42: 7 | H42: 1.6 | I42: =VLOOKUP(H42,$AF$3:$AG$156,2,FALSE) -> 8 | J42: 1.6 | K42: =IF(J42 > 0, VLOOKUP(J42,$AF$3:$AG$103,2,FALSE),0) -> 8 | M42: New | N42: Commit | O42: Framework | P42: N | Q42: 1 | R42: 6 | S42: =(R42-Q42) + 1 -> 6 | T42: =IF(AND(R42>=1, $A$1 <=1,Q42<=1), (K42/ ((R42 +1) - 1))*(Team!$H$25/10), 0) -> 1.3333333 | U42: =IF(AND(R42>=2, $A$1 <=2, Q42<=2), ((K42-T42)/ ((R42 +1) - 2))*(Team!$H$26/10), 0) -> 1.3333333 | V42: =IF(AND(R42>=3, $A$1 <=3, Q42<=3), ((K42-(T42+U42))/ ((R42 +1) - 3))*(Team!$H$27/10), 0) -> 1.3333333 | W42: =IF(AND(R42>=4, $A$1 <=4, Q42<=4), ((K42-(T42+U42+V42))/ ((R42 +1) - 4))*(Team!$H$28/10), 0) -> 1.3333333 | X42: =IF(AND(R42>=5, $A$1 <5, Q42<=5), ((K42-(T42+U42+V42+W42))/ ((R42 +1) - 5))*(Team!$H$29/10), 0) -> 1.3333333 | Y42: =IF(AND(R42>=6, $A$1 <6, Q42<=6), ((K42-(T42+U42+V42+W42+X42))/ ((R42 +1) - 6))*(Team!$H$30/10), 0) -> 1.3333333
C43: IDC: Phase 2 - Implementation of query builder Wizard | G43: 9 | H43: 9 | I43: =VLOOKUP(H43,$AF$3:$AG$156,2,FALSE) -> 45 | J43: 9 | K43: =IF(J43 > 0, VLOOKUP(J43,$AF$3:$AG$103,2,FALSE),0) -> 45 | M43: New | N43: Commit | O43: Framework | P43: N | Q43: 1 | R43: 6 | S43: =(R43+1) - 1 -> 6 | T43: =IF(AND(R43>=1, $A$1 <=1,Q43<=1), (K43/ ((R43 +1) - 1))*(Team!$H$25/10), 0) -> 7.5 | U43: =IF(AND(R43>=2, $A$1 <=2, Q43<=2), ((K43-T43)/ ((R43 +1) - 2))*(Team!$H$26/10), 0) -> 7.5 | V43: =IF(AND(R43>=3, $A$1 <=3, Q43<=3), ((K43-(T43+U43))/ ((R43 +1) - 3))*(Team!$H$27/10), 0) -> 7.5 | W43: =IF(AND(R43>=4, $A$1 <=4, Q43<=4), ((K43-(T43+U43+V43))/ ((R43 +1) - 4))*(Team!$H$28/10), 0) -> 7.5 | X43: =IF(AND(R43>=5, $A$1 <5, Q43<=5), ((K43-(T43+U43+V43+W43))/ ((R43 +1) - 5))*(Team!$H$29/10), 0) -> 7.5 | Y43: =IF(AND(R43>=6, $A$1 <6, Q43<=6), ((K43-(T43+U43+V43+W43+X43))/ ((R43 +1) - 6))*(Team!$H$30/10), 0) -> 7.5 | AC43: =(H43-J43)/H43 -> 0 | AD43: =IF(AC43=1, G43,0) -> 0
C44: IDC: Phase 2 - Implementation of Orchestration Automation | G44: 9 | H44: 8 | I44: =VLOOKUP(H44,$AF$3:$AG$156,2,FALSE) -> 40 | J44: 8 | K44: =IF(J44 > 0, VLOOKUP(J44,$AF$3:$AG$103,2,FALSE),0) -> 40 | M44: New | N44: Commit | O44: Framework | P44: N | Q44: 1 | R44: 6 | S44: =(R44+1) - 1 -> 6 | T44: =IF(AND(R44>=1, $A$1 <=1,Q44<=1), (K44/ ((R44 +1) - 1))*(Team!$H$25/10), 0) -> 6.6666667 | U44: =IF(AND(R44>=2, $A$1 <=2, Q44<=2), ((K44-T44)/ ((R44 +1) - 2))*(Team!$H$26/10), 0) -> 6.6666667 | V44: =IF(AND(R44>=3, $A$1 <=3, Q44<=3), ((K44-(T44+U44))/ ((R44 +1) - 3))*(Team!$H$27/10), 0) -> 6.6666667 | W44: =IF(AND(R44>=4, $A$1 <=4, Q44<=4), ((K44-(T44+U44+V44))/ ((R44 +1) - 4))*(Team!$H$28/10), 0) -> 6.6666667 | X44: =IF(AND(R44>=5, $A$1 <5, Q44<=5), ((K44-(T44+U44+V44+W44))/ ((R44 +1) - 5))*(Team!$H$29/10), 0) -> 6.6666667 | Y44: =IF(AND(R44>=6, $A$1 <6, Q44<=6), ((K44-(T44+U44+V44+W44+X44))/ ((R44 +1) - 6))*(Team!$H$30/10), 0) -> 6.6666667
C45: PROOF - BAU 2022.05 Release (May 2022) | G45: 9 | H45: 6 | I45: =VLOOKUP(H45,$AF$3:$AG$156,2,FALSE) -> 30 | J45: 6 | K45: =IF(J45 > 0, VLOOKUP(J45,$AF$3:$AG$103,2,FALSE),0) -> 30 | M45: New | N45: Commit | O45: BAU | P45: N | Q45: 1 | R45: 2 | S45: =(R45+1) - 1 -> 2 | T45: =IF(AND(R45>=1, $A$1 <=1,Q45<=1), (K45/ ((R45 +1) - 1))*(Team!$H$25/10), 0) -> 15 | U45: =IF(AND(R45>=2, $A$1 <=2, Q45<=2), ((K45-T45)/ ((R45 +1) - 2))*(Team!$H$26/10), 0) -> 15 | V45: =IF(AND(R45>=3, $A$1 <=3, Q45<=3), ((K45-(T45+U45))/ ((R45 +1) - 3))*(Team!$H$27/10), 0) -> 0 | W45: =IF(AND(R45>=4, $A$1 <=4, Q45<=4), ((K45-(T45+U45+V45))/ ((R45 +1) - 4))*(Team!$H$28/10), 0) -> 0 | X45: =IF(AND(R45>=5, $A$1 <5, Q45<=5), ((K45-(T45+U45+V45+W45))/ ((R45 +1) - 5))*(Team!$H$29/10), 0) -> 0 | Y45: =IF(AND(R45>=6, $A$1 <6, Q45<=6), ((K45-(T45+U45+V45+W45+X45))/ ((R45 +1) - 6))*(Team!$H$30/10), 0) -> 0 | AB45: 44702
C46: PROOF - BAU 2022.06 Release (June 2022) | G46: 9 | H46: 5 | I46: =VLOOKUP(H46,$AF$3:$AG$156,2,FALSE) -> 25 | J46: 5 | K46: =IF(J46 > 0, VLOOKUP(J46,$AF$3:$AG$103,2,FALSE),0) -> 25 | M46: New | N46: Commit | O46: BAU | P46: N | Q46: 1 | R46: 4 | S46: =(R46+1) - 1 -> 4 | T46: =IF(AND(R46>=1, $A$1 <=1,Q46<=1), (K46/ ((R46 +1) - 1))*(Team!$H$25/10), 0) -> 6.25 | U46: =IF(AND(R46>=2, $A$1 <=2, Q46<=2), ((K46-T46)/ ((R46 +1) - 2))*(Team!$H$26/10), 0) -> 6.25 | V46: =IF(AND(R46>=3, $A$1 <=3, Q46<=3), ((K46-(T46+U46))/ ((R46 +1) - 3))*(Team!$H$27/10), 0) -> 6.25 | W46: =IF(AND(R46>=4, $A$1 <=4, Q46<=4), ((K46-(T46+U46+V46))/ ((R46 +1) - 4))*(Team!$H$28/10), 0) -> 6.25 | X46: =IF(AND(R46>=5, $A$1 <5, Q46<=5), ((K46-(T46+U46+V46+W46))/ ((R46 +1) - 5))*(Team!$H$29/10), 0) -> 0 | Y46: =IF(AND(R46>=6, $A$1 <6, Q46<=6), ((K46-(T46+U46+V46+W46+X46))/ ((R46 +1) - 6))*(Team!$H$30/10), 0) -> 0 | AB46: 44730
C47: PROOF - BAU 2022.07 Release (July 2022) | G47: 9 | H47: 6 | I47: =VLOOKUP(H47,$AF$3:$AG$156,2,FALSE) -> 30 | J47: 6 | K47: =IF(J47 > 0, VLOOKUP(J47,$AF$3:$AG$103,2,FALSE),0) -> 30 | M47: New | N47: Commit | O47: BAU | P47: N | Q47: 3 | R47: 6 | S47: =(R47+1) - 1 -> 6 | T47: =IF(AND(R47>=1, $A$1 <=1,Q47<=1), (K47/ ((R47 +1) - 1))*(Team!$H$25/10), 0) -> 0 | U47: =IF(AND(R47>=2, $A$1 <=2, Q47<=2), ((K47-T47)/ ((R47 +1) - 2))*(Team!$H$26/10), 0) -> 0 | V47: =IF(AND(R47>=3, $A$1 <=3, Q47<=3), ((K47-(T47+U47))/ ((R47 +1) - 3))*(Team!$H$27/10), 0) -> 7.5 | W47: =IF(AND(R47>=4, $A$1 <=4, Q47<=4), ((K47-(T47+U47+V47))/ ((R47 +1) - 4))*(Team!$H$28/10), 0) -> 7.5 | X47: =IF(AND(R47>=5, $A$1 <5, Q47<=5), ((K47-(T47+U47+V47+W47))/ ((R47 +1) - 5))*(Team!$H$29/10), 0) -> 7.5 | Y47: =IF(AND(R47>=6, $A$1 <6, Q47<=6), ((K47-(T47+U47+V47+W47+X47))/ ((R47 +1) - 6))*(Team!$H$30/10), 0) -> 7.5 | AB47: 44758
C48: PROOF - BAU 2022.08 Release (August 2022) | G48: 9 | H48: 3 | I48: =VLOOKUP(H48,$AF$3:$AG$156,2,FALSE) -> 15 | J48: 3 | K48: =IF(J48 > 0, VLOOKUP(J48,$AF$3:$AG$103,2,FALSE),0) -> 15 | M48: New | N48: Commit | O48: BAU | P48: N | Q48: 5 | R48: 5 | S48: =(R48+1) - 1 -> 5 | T48: =IF(AND(R48>=1, $A$1 <=1,Q48<=1), (K48/ ((R48 +1) - 1))*(Team!$H$25/10), 0) -> 0 | U48: =IF(AND(R48>=2, $A$1 <=2, Q48<=2), ((K48-T48)/ ((R48 +1) - 2))*(Team!$H$26/10), 0) -> 0 | V48: =IF(AND(R48>=3, $A$1 <=3, Q48<=3), ((K48-(T48+U48))/ ((R48 +1) - 3))*(Team!$H$27/10), 0) -> 0 | W48: =IF(AND(R48>=4, $A$1 <=4, Q48<=4), ((K48-(T48+U48+V48))/ ((R48 +1) - 4))*(Team!$H$28/10), 0) -> 0 | X48: =IF(AND(R48>=5, $A$1 <5, Q48<=5), ((K48-(T48+U48+V48+W48))/ ((R48 +1) - 5))*(Team!$H$29/10), 0) -> 15 | Y48: =IF(AND(R48>=6, $A$1 <6, Q48<=6), ((K48-(T48+U48+V48+W48+X48))/ ((R48 +1) - 6))*(Team!$H$30/10), 0) -> 0 | AB48: 44793
C49: GRID Adjustments - BAU 2022.05 Release (May 2022) | G49: 9 | H49: 1.6 | I49: =VLOOKUP(H49,$AF$3:$AG$156,2,FALSE) -> 8 | J49: 1.6 | K49: =IF(J49 > 0, VLOOKUP(J49,$AF$3:$AG$103,2,FALSE),0) -> 8 | M49: New | N49: Commit | O49: BAU | P49: N | Q49: 1 | R49: 2 | S49: =(R49+1) - 1 -> 2 | T49: =IF(AND(R49>=1, $A$1 <=1,Q49<=1), (K49/ ((R49 +1) - 1))*(Team!$H$25/10), 0) -> 4 | U49: =IF(AND(R49>=2, $A$1 <=2, Q49<=2), ((K49-T49)/ ((R49 +1) - 2))*(Team!$H$26/10), 0) -> 4 | V49: =IF(AND(R49>=3, $A$1 <=3, Q49<=3), ((K49-(T49+U49))/ ((R49 +1) - 3))*(Team!$H$27/10), 0) -> 0 | W49: =IF(AND(R49>=4, $A$1 <=4, Q49<=4), ((K49-(T49+U49+V49))/ ((R49 +1) - 4))*(Team!$H$28/10), 0) -> 0 | X49: =IF(AND(R49>=5, $A$1 <5, Q49<=5), ((K49-(T49+U49+V49+W49))/ ((R49 +1) - 5))*(Team!$H$29/10), 0) -> 0 | Y49: =IF(AND(R49>=6, $A$1 <6, Q49<=6), ((K49-(T49+U49+V49+W49+X49))/ ((R49 +1) - 6))*(Team!$H$30/10), 0) -> 0 | AB49: 44702
C50: GRID Adjustments - BAU 2022.06 Release (June 2022) | G50: 9 | H50: 1.6 | I50: =VLOOKUP(H50,$AF$3:$AG$156,2,FALSE) -> 8 | J50: 1.6 | K50: =IF(J50 > 0, VLOOKUP(J50,$AF$3:$AG$103,2,FALSE),0) -> 8 | M50: New | N50: Commit | O50: BAU | P50: N | Q50: 1 | R50: 4 | S50: =(R50+1) - 1 -> 4 | T50: =IF(AND(R50>=1, $A$1 <=1,Q50<=1), (K50/ ((R50 +1) - 1))*(Team!$H$25/10), 0) -> 2 | U50: =IF(AND(R50>=2, $A$1 <=2, Q50<=2), ((K50-T50)/ ((R50 +1) - 2))*(Team!$H$26/10), 0) -> 2 | V50: =IF(AND(R50>=3, $A$1 <=3, Q50<=3), ((K50-(T50+U50))/ ((R50 +1) - 3))*(Team!$H$27/10), 0) -> 2 | W50: =IF(AND(R50>=4, $A$1 <=4, Q50<=4), ((K50-(T50+U50+V50))/ ((R50 +1) - 4))*(Team!$H$28/10), 0) -> 2 | X50: =IF(AND(R50>=5, $A$1 <5, Q50<=5), ((K50-(T50+U50+V50+W50))/ ((R50 +1) - 5))*(Team!$H$29/10), 0) -> 0 | Y50: =IF(AND(R50>=6, $A$1 <6, Q50<=6), ((K50-(T50+U50+V50+W50+X50))/ ((R50 +1) - 6))*(Team!$H$30/10), 0) -> 0 | AB50: 44730
C51: GRID Adjustments - BAU 2022.07 Release (July 2022) | G51: 5 | H51: 1.6 | I51: =VLOOKUP(H51,$AF$3:$AG$156,2,FALSE) -> 8 | J51: 1.6 | K51: =IF(J51 > 0, VLOOKUP(J51,$AF$3:$AG$103,2,FALSE),0) -> 8 | M51: New | N51: Commit | O51: BAU | P51: N | Q51: 3 | R51: 6 | S51: =(R51+1) - 1 -> 6 | T51: =IF(AND(R51>=1, $A$1 <=1,Q51<=1), (K51/ ((R51 +1) - 1))*(Team!$H$25/10), 0) -> 0 | U51: =IF(AND(R51>=2, $A$1 <=2, Q51<=2), ((K51-T51)/ ((R51 +1) - 2))*(Team!$H$26/10), 0) -> 0 | V51: =IF(AND(R51>=3, $A$1 <=3, Q51<=3), ((K51-(T51+U51))/ ((R51 +1) - 3))*(Team!$H$27/10), 0) -> 2 | W51: =IF(AND(R51>=4, $A$1 <=4, Q51<=4), ((K51-(T51+U51+V51))/ ((R51 +1) - 4))*(Team!$H$28/10), 0) -> 2 | X51: =IF(AND(R51>=5, $A$1 <5, Q51<=5), ((K51-(T51+U51+V51+W51))/ ((R51 +1) - 5))*(Team!$H$29/10), 0) -> 2 | Y51: =IF(AND(R51>=6, $A$1 <6, Q51<=6), ((K51-(T51+U51+V51+W51+X51))/ ((R51 +1) - 6))*(Team!$H$30/10), 0) -> 2 | AB51: 44758
C52: GRID Adjustments - BAU 2022.08 Release (August 2022) | G52: 6 | H52: 1.6 | I52: =VLOOKUP(H52,$AF$3:$AG$156,2,FALSE) -> 8 | J52: 1.6 | K52: =IF(J52 > 0, VLOOKUP(J52,$AF$3:$AG$103,2,FALSE),0) -> 8 | M52: New | N52: Commit | O52: BAU | P52: N | Q52: 5 | R52: 5 | S52: =(R52+1) - 1 -> 5 | T52: =IF(AND(R52>=1, $A$1 <=1,Q52<=1), (K52/ ((R52 +1) - 1))*(Team!$H$25/10), 0) -> 0 | U52: =IF(AND(R52>=2, $A$1 <=2, Q52<=2), ((K52-T52)/ ((R52 +1) - 2))*(Team!$H$26/10), 0) -> 0 | V52: =IF(AND(R52>=3, $A$1 <=3, Q52<=3), ((K52-(T52+U52))/ ((R52 +1) - 3))*(Team!$H$27/10), 0) -> 0 | W52: =IF(AND(R52>=4, $A$1 <=4, Q52<=4), ((K52-(T52+U52+V52))/ ((R52 +1) - 4))*(Team!$H$28/10), 0) -> 0 | X52: =IF(AND(R52>=5, $A$1 <5, Q52<=5), ((K52-(T52+U52+V52+W52))/ ((R52 +1) - 5))*(Team!$H$29/10), 0) -> 8 | Y52: =IF(AND(R52>=6, $A$1 <6, Q52<=6), ((K52-(T52+U52+V52+W52+X52))/ ((R52 +1) - 6))*(Team!$H$30/10), 0) -> 0 | AB52: 44793
C53: PROOF/IDC/iRIDER AM KT | G53: 7 | H53: 1.6 | I53: =VLOOKUP(H53,$AF$3:$AG$156,2,FALSE) -> 8 | J53: 1.6 | K53: =IF(J53 > 0, VLOOKUP(J53,$AF$3:$AG$103,2,FALSE),0) -> 8 | M53: New | N53: Commit | O53: BCP | P53: N | Q53: 1 | R53: 4 | S53: =(R53+1) - 1 -> 4 | T53: =IF(AND(R53>=1, $A$1 <=1,Q53<=1), (K53/ ((R53 +1) - 1))*(Team!$H$25/10), 0) -> 2 | U53: =IF(AND(R53>=2, $A$1 <=2, Q53<=2), ((K53-T53)/ ((R53 +1) - 2))*(Team!$H$26/10), 0) -> 2 | V53: =IF(AND(R53>=3, $A$1 <=3, Q53<=3), ((K53-(T53+U53))/ ((R53 +1) - 3))*(Team!$H$27/10), 0) -> 2 | W53: =IF(AND(R53>=4, $A$1 <=4, Q53<=4), ((K53-(T53+U53+V53))/ ((R53 +1) - 4))*(Team!$H$28/10), 0) -> 2 | X53: =IF(AND(R53>=5, $A$1 <5, Q53<=5), ((K53-(T53+U53+V53+W53))/ ((R53 +1) - 5))*(Team!$H$29/10), 0) -> 0 | Y53: =IF(AND(R53>=6, $A$1 <6, Q53<=6), ((K53-(T53+U53+V53+W53+X53))/ ((R53 +1) - 6))*(Team!$H$30/10), 0) -> 0
C54: PROOF QA Automation | G54: 9 | H54: 6 | I54: =VLOOKUP(H54,$AF$3:$AG$156,2,FALSE) -> 30 | J54: 6 | K54: =IF(J54 > 0, VLOOKUP(J54,$AF$3:$AG$103,2,FALSE),0) -> 30 | M54: New | N54: Commit | O54: Framework | P54: N | Q54: 1 | R54: 6 | S54: =(R54+1) - 1 -> 6 | T54: =IF(AND(R54>=1, $A$1 <=1,Q54<=1), (K54/ ((R54 +1) - 1))*(Team!$H$25/10), 0) -> 5 | U54: =IF(AND(R54>=2, $A$1 <=2, Q54<=2), ((K54-T54)/ ((R54 +1) - 2))*(Team!$H$26/10), 0) -> 5 | V54: =IF(AND(R54>=3, $A$1 <=3, Q54<=3), ((K54-(T54+U54))/ ((R54 +1) - 3))*(Team!$H$27/10), 0) -> 5 | W54: =IF(AND(R54>=4, $A$1 <=4, Q54<=4), ((K54-(T54+U54+V54))/ ((R54 +1) - 4))*(Team!$H$28/10), 0) -> 5 | X54: =IF(AND(R54>=5, $A$1 <5, Q54<=5), ((K54-(T54+U54+V54+W54))/ ((R54 +1) - 5))*(Team!$H$29/10), 0) -> 5 | Y54: =IF(AND(R54>=6, $A$1 <6, Q54<=6), ((K54-(T54+U54+V54+W54+X54))/ ((R54 +1) - 6))*(Team!$H$30/10), 0) -> 5
C55: PROOF-Future State Data Project - Part 1 | G55: 9 | H55: 9 | I55: =VLOOKUP(H55,$AF$3:$AG$156,2,FALSE) -> 45 | J55: 9 | K55: =IF(J55 > 0, VLOOKUP(J55,$AF$3:$AG$103,2,FALSE),0) -> 45 | M55: New | N55: Commit | O55: Business | P55: N | Q55: 1 | R55: 3 | S55: =(R55+1) - 1 -> 3 | T55: =IF(AND(R55>=1, $A$1 <=1,Q55<=1), (K55/ ((R55 +1) - 1))*(Team!$H$25/10), 0) -> 15 | U55: =IF(AND(R55>=2, $A$1 <=2, Q55<=2), ((K55-T55)/ ((R55 +1) - 2))*(Team!$H$26/10), 0) -> 15 | V55: =IF(AND(R55>=3, $A$1 <=3, Q55<=3), ((K55-(T55+U55))/ ((R55 +1) - 3))*(Team!$H$27/10), 0) -> 15 | W55: =IF(AND(R55>=4, $A$1 <=4, Q55<=4), ((K55-(T55+U55+V55))/ ((R55 +1) - 4))*(Team!$H$28/10), 0) -> 0 | X55: =IF(AND(R55>=5, $A$1 <5, Q55<=5), ((K55-(T55+U55+V55+W55))/ ((R55 +1) - 5))*(Team!$H$29/10), 0) -> 0 | Y55: =IF(AND(R55>=6, $A$1 <6, Q55<=6), ((K55-(T55+U55+V55+W55+X55))/ ((R55 +1) - 6))*(Team!$H$30/10), 0) -> 0
C56: PROOF-Future State Data Project - Part 2 | G56: 9 | H56: 8 | I56: =VLOOKUP(H56,$AF$3:$AG$156,2,FALSE) -> 40 | J56: 8 | K56: =IF(J56 > 0, VLOOKUP(J56,$AF$3:$AG$103,2,FALSE),0) -> 40 | M56: New | N56: Commit | O56: Business | P56: N | Q56: 3 | R56: 4 | S56: =(R56+1) - 1 -> 4 | T56: =IF(AND(R56>=1, $A$1 <=1,Q56<=1), (K56/ ((R56 +1) - 1))*(Team!$H$25/10), 0) -> 0 | U56: =IF(AND(R56>=2, $A$1 <=2, Q56<=2), ((K56-T56)/ ((R56 +1) - 2))*(Team!$H$26/10), 0) -> 0 | V56: =IF(AND(R56>=3, $A$1 <=3, Q56<=3), ((K56-(T56+U56))/ ((R56 +1) - 3))*(Team!$H$27/10), 0) -> 20 | W56: =IF(AND(R56>=4, $A$1 <=4, Q56<=4), ((K56-(T56+U56+V56))/ ((R56 +1) - 4))*(Team!$H$28/10), 0) -> 20 | X56: =IF(AND(R56>=5, $A$1 <5, Q56<=5), ((K56-(T56+U56+V56+W56))/ ((R56 +1) - 5))*(Team!$H$29/10), 0) -> 0 | Y56: =IF(AND(R56>=6, $A$1 <6, Q56<=6), ((K56-(T56+U56+V56+W56+X56))/ ((R56 +1) - 6))*(Team!$H$30/10), 0) -> 0
C57: Proof - historical | G57: 9 | H57: 1 | I57: =VLOOKUP(H57,$AF$3:$AG$156,2,FALSE) -> 5 | J57: 1 | K57: =IF(J57 > 0, VLOOKUP(J57,$AF$3:$AG$103,2,FALSE),0) -> 5 | M57: New | N57: Commit | O57: Business | P57: N | Q57: 1 | R57: 5 | S57: =(R57+1) - 1 -> 5 | T57: =IF(AND(R57>=1, $A$1 <=1,Q57<=1), (K57/ ((R57 +1) - 1))*(Team!$H$25/10), 0) -> 1 | U57: =IF(AND(R57>=2, $A$1 <=2, Q57<=2), ((K57-T57)/ ((R57 +1) - 2))*(Team!$H$26/10), 0) -> 1 | V57: =IF(AND(R57>=3, $A$1 <=3, Q57<=3), ((K57-(T57+U57))/ ((R57 +1) - 3))*(Team!$H$27/10), 0) -> 1 | W57: =IF(AND(R57>=4, $A$1 <=4, Q57<=4), ((K57-(T57+U57+V57))/ ((R57 +1) - 4))*(Team!$H$28/10), 0) -> 1 | X57: =IF(AND(R57>=5, $A$1 <5, Q57<=5), ((K57-(T57+U57+V57+W57))/ ((R57 +1) - 5))*(Team!$H$29/10), 0) -> 1 | Y57: =IF(AND(R57>=6, $A$1 <6, Q57<=6), ((K57-(T57+U57+V57+W57+X57))/ ((R57 +1) - 6))*(Team!$H$30/10), 0) -> 0
C58: Proof -allvue | G58: 9 | H58: 3 | I58: =VLOOKUP(H58,$AF$3:$AG$156,2,FALSE) -> 15 | J58: 3 | K58: =IF(J58 > 0, VLOOKUP(J58,$AF$3:$AG$103,2,FALSE),0) -> 15 | M58: New | N58: Commit | O58: Business | P58: N | Q58: 1 | R58: 6 | S58: =(R58+1) - 1 -> 6 | T58: =IF(AND(R58>=1, $A$1 <=1,Q58<=1), (K58/ ((R58 +1) - 1))*(Team!$H$25/10), 0) -> 2.5 | U58: =IF(AND(R58>=2, $A$1 <=2, Q58<=2), ((K58-T58)/ ((R58 +1) - 2))*(Team!$H$26/10), 0) -> 2.5 | V58: =IF(AND(R58>=3, $A$1 <=3, Q58<=3), ((K58-(T58+U58))/ ((R58 +1) - 3))*(Team!$H$27/10), 0) -> 2.5 | W58: =IF(AND(R58>=4, $A$1 <=4, Q58<=4), ((K58-(T58+U58+V58))/ ((R58 +1) - 4))*(Team!$H$28/10), 0) -> 2.5 | X58: =IF(AND(R58>=5, $A$1 <5, Q58<=5), ((K58-(T58+U58+V58+W58))/ ((R58 +1) - 5))*(Team!$H$29/10), 0) -> 2.5 | Y58: =IF(AND(R58>=6, $A$1 <6, Q58<=6), ((K58-(T58+U58+V58+W58+X58))/ ((R58 +1) - 6))*(Team!$H$30/10), 0) -> 2.5
C59: PROOF - ESG Star | G59: 8 | H59: 1 | I59: =VLOOKUP(H59,$AF$3:$AG$156,2,FALSE) -> 5 | J59: 1 | K59: =IF(J59 > 0, VLOOKUP(J59,$AF$3:$AG$103,2,FALSE),0) -> 5 | M59: New | N59: Commit | O59: Business | P59: N | Q59: 0 | R59: 0 | S59: =(R59+1) - 1 -> 0 | T59: =IF(AND(R59>=1, $A$1 <=1,Q59<=1), (K59/ ((R59 +1) - 1))*(Team!$H$25/10), 0) -> 0 | U59: =IF(AND(R59>=2, $A$1 <=2, Q59<=2), ((K59-T59)/ ((R59 +1) - 2))*(Team!$H$26/10), 0) -> 0 | V59: =IF(AND(R59>=3, $A$1 <=3, Q59<=3), ((K59-(T59+U59))/ ((R59 +1) - 3))*(Team!$H$27/10), 0) -> 0 | W59: =IF(AND(R59>=4, $A$1 <=4, Q59<=4), ((K59-(T59+U59+V59))/ ((R59 +1) - 4))*(Team!$H$28/10), 0) -> 0 | X59: =IF(AND(R59>=5, $A$1 <5, Q59<=5), ((K59-(T59+U59+V59+W59))/ ((R59 +1) - 5))*(Team!$H$29/10), 0) -> 0 | Y59: =IF(AND(R59>=6, $A$1 <6, Q59<=6), ((K59-(T59+U59+V59+W59+X59))/ ((R59 +1) - 6))*(Team!$H$30/10), 0) -> 0
C60: iRIDER - BAU 2022.05 Release (May 2022) | G60: 8 | H60: 1.6 | I60: =VLOOKUP(H60,$AF$3:$AG$156,2,FALSE) -> 8 | J60: 1.6 | K60: =IF(J60 > 0, VLOOKUP(J60,$AF$3:$AG$103,2,FALSE),0) -> 8 | M60: New | N60: Commit | O60: BAU | P60: N | Q60: 1 | R60: 2 | S60: =(R60+1) - 1 -> 2 | T60: =IF(AND(R60>=1, $A$1 <=1,Q60<=1), (K60/ ((R60 +1) - 1))*(Team!$H$25/10), 0) -> 4 | U60: =IF(AND(R60>=2, $A$1 <=2, Q60<=2), ((K60-T60)/ ((R60 +1) - 2))*(Team!$H$26/10), 0) -> 4 | V60: =IF(AND(R60>=3, $A$1 <=3, Q60<=3), ((K60-(T60+U60))/ ((R60 +1) - 3))*(Team!$H$27/10), 0) -> 0 | W60: =IF(AND(R60>=4, $A$1 <=4, Q60<=4), ((K60-(T60+U60+V60))/ ((R60 +1) - 4))*(Team!$H$28/10), 0) -> 0 | X60: =IF(AND(R60>=5, $A$1 <5, Q60<=5), ((K60-(T60+U60+V60+W60))/ ((R60 +1) - 5))*(Team!$H$29/10), 0) -> 0 | Y60: =IF(AND(R60>=6, $A$1 <6, Q60<=6), ((K60-(T60+U60+V60+W60+X60))/ ((R60 +1) - 6))*(Team!$H$30/10), 0) -> 0 | AB60: 44702
C61: iRIDER - BAU 2022.06 Release (June 2022) | G61: 8 | H61: 1.6 | I61: =VLOOKUP(H61,$AF$3:$AG$156,2,FALSE) -> 8 | J61: 1.6 | K61: =IF(J61 > 0, VLOOKUP(J61,$AF$3:$AG$103,2,FALSE),0) -> 8 | M61: New | N61: Commit | O61: BAU | P61: N | Q61: 1 | R61: 4 | S61: =(R61+1) - 1 -> 4 | T61: =IF(AND(R61>=1, $A$1 <=1,Q61<=1), (K61/ ((R61 +1) - 1))*(Team!$H$25/10), 0) -> 2 | U61: =IF(AND(R61>=2, $A$1 <=2, Q61<=2), ((K61-T61)/ ((R61 +1) - 2))*(Team!$H$26/10), 0) -> 2 | V61: =IF(AND(R61>=3, $A$1 <=3, Q61<=3), ((K61-(T61+U61))/ ((R61 +1) - 3))*(Team!$H$27/10), 0) -> 2 | W61: =IF(AND(R61>=4, $A$1 <=4, Q61<=4), ((K61-(T61+U61+V61))/ ((R61 +1) - 4))*(Team!$H$28/10), 0) -> 2 | X61: =IF(AND(R61>=5, $A$1 <5, Q61<=5), ((K61-(T61+U61+V61+W61))/ ((R61 +1) - 5))*(Team!$H$29/10), 0) -> 0 | Y61: =IF(AND(R61>=6, $A$1 <6, Q61<=6), ((K61-(T61+U61+V61+W61+X61))/ ((R61 +1) - 6))*(Team!$H$30/10), 0) -> 0 | AB61: 44730
C62: iRIDER - BAU 2022.07 Release (July 2022) | G62: 8 | H62: 1.6 | I62: =VLOOKUP(H62,$AF$3:$AG$156,2,FALSE) -> 8 | J62: 1.6 | K62: =IF(J62 > 0, VLOOKUP(J62,$AF$3:$AG$103,2,FALSE),0) -> 8 | M62: New | N62: Commit | O62: BAU | P62: N | Q62: 3 | R62: 6 | S62: =(R62+1) - 1 -> 6 | T62: =IF(AND(R62>=1, $A$1 <=1,Q62<=1), (K62/ ((R62 +1) - 1))*(Team!$H$25/10), 0) -> 0 | U62: =IF(AND(R62>=2, $A$1 <=2, Q62<=2), ((K62-T62)/ ((R62 +1) - 2))*(Team!$H$26/10), 0) -> 0 | V62: =IF(AND(R62>=3, $A$1 <=3, Q62<=3), ((K62-(T62+U62))/ ((R62 +1) - 3))*(Team!$H$27/10), 0) -> 2 | W62: =IF(AND(R62>=4, $A$1 <=4, Q62<=4), ((K62-(T62+U62+V62))/ ((R62 +1) - 4))*(Team!$H$28/10), 0) -> 2 | X62: =IF(AND(R62>=5, $A$1 <5, Q62<=5), ((K62-(T62+U62+V62+W62))/ ((R62 +1) - 5))*(Team!$H$29/10), 0) -> 2 | Y62: =IF(AND(R62>=6, $A$1 <6, Q62<=6), ((K62-(T62+U62+V62+W62+X62))/ ((R62 +1) - 6))*(Team!$H$30/10), 0) -> 2 | AB62: 44758
C63: iRIDER - BAU 2022.08 Release (August 2022) | G63: 8 | H63: 1.6 | I63: =VLOOKUP(H63,$AF$3:$AG$156,2,FALSE) -> 8 | J63: 1.6 | K63: =IF(J63 > 0, VLOOKUP(J63,$AF$3:$AG$103,2,FALSE),0) -> 8 | M63: New | N63: Commit | O63: BAU | P63: N | Q63: 5 | R63: 5 | S63: =(R63+1) - 1 -> 5 | T63: =IF(AND(R63>=1, $A$1 <=1,Q63<=1), (K63/ ((R63 +1) - 1))*(Team!$H$25/10), 0) -> 0 | U63: =IF(AND(R63>=2, $A$1 <=2, Q63<=2), ((K63-T63)/ ((R63 +1) - 2))*(Team!$H$26/10), 0) -> 0 | V63: =IF(AND(R63>=3, $A$1 <=3, Q63<=3), ((K63-(T63+U63))/ ((R63 +1) - 3))*(Team!$H$27/10), 0) -> 0 | W63: =IF(AND(R63>=4, $A$1 <=4, Q63<=4), ((K63-(T63+U63+V63))/ ((R63 +1) - 4))*(Team!$H$28/10), 0) -> 0 | X63: =IF(AND(R63>=5, $A$1 <5, Q63<=5), ((K63-(T63+U63+V63+W63))/ ((R63 +1) - 5))*(Team!$H$29/10), 0) -> 8 | Y63: =IF(AND(R63>=6, $A$1 <6, Q63<=6), ((K63-(T63+U63+V63+W63+X63))/ ((R63 +1) - 6))*(Team!$H$30/10), 0) -> 0 | AB63: 44793
F64: Orig Effort Needed: | I64: =Team!C12 -> 0 | J64: Current | K64: =Team!C23 -> 884 | L64: Committed: | M64: =COUNTIF(N3:N63,"Commit") -> 61 | N64: Stretch/vendor: | O64: {=SUM(COUNTIFS(N3:N63,{"Stretch","Vendor"})) - COUNTIFS(N3:N63,"Vendor", M3:M63,"Resolved")} -> 0 | T64: =IF(AND(R64>=1, $A$1 <=1,Q64<=1), (K64/ ((R64 +1) - 1))*(Team!$H$25/10), 0) -> 0 | U64: =IF(AND(S64>=1, $A$1 <=1,R64<=1), (L64/ ((S64 +1) - 1))*(Team!$H$25/10), 0) -> 0 | V64: =IF(AND(T64>=1, $A$1 <=1,S64<=1), (M64/ ((T64 +1) - 1))*(Team!$H$25/10), 0) -> 0 | W64: =IF(AND(U64>=1, $A$1 <=1,T64<=1), (N64/ ((U64 +1) - 1))*(Team!$H$25/10), 0) -> 0 | X64: =IF(AND(R64>=5, $A$1 <5, Q64<=5), ((K64-(T64+U64+V64+W64))/ ((R64 +1) - 5))*(Team!$H$29/10), 0) -> 0 | Y64: =IF(AND(R64>=6, $A$1 <6, Q64<=6), ((K64-(T64+U64+V64+W64+X64))/ ((R64 +1) - 6))*(Team!$H$30/10), 0) -> 0 | AC64: =(H64-J64)/H64 -> #VALUE! | AD64: =IF(AC64=1, G64,0) -> #VALUE!
F65: Orig Effort Available | I65: =Team!D12 -> 837.52 | J65: =IF(I66=0,"Over Committed", IF(I66=1, "High Risk", IF(I66=2, "Some Risk", "Fully Committed"))) -> Fully Committed | K65: =Team!D23 -> 837.52 | L65: =IF(K66=0,"Over Committed", IF(K66=1, "High Risk", IF(K66=2, "Some Risk", "Fully Committed"))) -> Over Committed | M65: Delivered | O65: Total Items | Y65: =IF(AND(R65>=6, $A$1 <6, Q65<=6), ((K65-(T65+U65+V65+W65+X65))/ ((R65 +1) - 6))*(Team!$H$30/10), 0) -> 0 | AC65: =(H65-J65)/H65 -> #VALUE! | AD65: =IF(AC65=1, G65,0) -> #VALUE!
F66: Trend: | I66: =IF(I64 > I65, IF((1-(I65/I64)) <= 0.03, 2,IF(AND((1-(I65/I64)) > 0.03, (1-(I65/I64)) <= 0.05), 1,0)),3) -> 3 | K66: =IF(K64 > K65, IF((1-(K65/K64)) <= 0.03, 2,IF(AND((1-(K65/K64)) > 0.03, (1-(K65/K64)) <= 0.05), 1,0)),3) -> 0 | M66: {=SUM(COUNTIFS(M3:M63,{"Resolved","Closed"}))} -> 0 | O66: =COUNT(B3:B63) -> 0
O71: `
AF89: 0.2 | AG89: 1
AF90: 0.4 | AG90: 2
AF91: 0.6 | AG91: 3
AF92: 0.8 | AG92: 4
AF93: 1.6 | AG93: 8
AF94: 1 | AG94: 5 | AH94: T
AF95: 2 | AG95: 10 | AH95: CA
AF96: 3 | AG96: 15 | AH96: H
AF97: 4 | AG97: 20 | AH97: IM
AF98: 5 | AG98: 25 | AH98: N
AF99: 6 | AG99: 30 | AH99: S
AF100: 7 | AG100: 35 | AH100: TB
AF101: 8 | AG101: 40 | AH101: N
AF102: 9 | AG102: 45 | AH102: S
AF103: 10 | AG103: 55

Sheet Team
C1: PI Start date: | E1: 44671 | F1: Today's Date: | G1: =TODAY() -> 44657
P2: Next steps | T2: Owner | W2: Due by
C3: Product Manager(s): Jatin Chauhan | P3: Create features in AzDO | T3: Dana/Vilasini/Jagan | V3: 1 | W3: 44579
C4: Total Ask | D4: Orig Eff | E4: Team | F4: Scrum Master | G4: Product Owner | H4: Team Size S1 | I4: Team Size S2 | J4: Team Size S3 | K4: Team Size S4 | L4: Team Size S5 | M4: Team Size S6 | P4: Create stories in AzDO | T4: Dana/Vilasini/Jagan | W4: 44581
C5: =SUMIFS('PI Commitments'!$I3:$I63,'PI Commitments'!$N3:$N63,"Commit",'PI Commitments'!$P3:$P63,"IM") -> 0 | D5: =SUM(H5:L5)*8 -> 445.76 | E5: The Ninjas | F5: Jagadeesan Balasubramanian | G5: Jatin Chauhan | H5: =SUMIF('Resource Planning'!$D$3:$D$27,E5,'Resource Planning'!$F$3:$F$27) -> 10.3 | I5: =SUMIF('Resource Planning'!$D$3:$D$27,E5,'Resource Planning'!$G$3:$G$27) -> 11.4 | J5: =SUMIF('Resource Planning'!$D$3:$D$27,E5,'Resource Planning'!$H$3:$H$27) -> 11.14 | K5: =SUMIF('Resource Planning'!$D$3:$D$27,E5,'Resource Planning'!$I$3:$I$27) -> 11.5 | L5: =SUMIF('Resource Planning'!$D$3:$D$24,E5,'Resource Planning'!$J$3:$J$24) -> 11.38 | M5: =SUMIF('Resource Planning'!$D$3:$D$24,E5,'Resource Planning'!$J$3:$J$24) -> 11.38 | P5: Create Objectives, risks, Question | T5: Jatin/Dana/Vilasini/Jagan | W5: 44579
C6: =SUMIFS('PI Commitments'!$I3:$I63,'PI Commitments'!$N3:$N63,"Commit",'PI Commitments'!$P3:$P63,"H") -> 0 | D6: =SUM(H6:L6)*8 -> 391.76 | E6: Samurai | F6: Dana Fillhart | G6: Jatin Chauhan | H6: =SUMIF('Resource Planning'!$D$3:$D$27,E6,'Resource Planning'!$F$3:$F$27) -> 9 | I6: =SUMIF('Resource Planning'!$D$3:$D$27,E6,'Resource Planning'!$G$3:$G$27) -> 9.9 | J6: =SUMIF('Resource Planning'!$D$3:$D$27,E6,'Resource Planning'!$H$3:$H$27) -> 10.05 | K6: =SUMIF('Resource Planning'!$D$3:$D$27,E6,'Resource Planning'!$I$3:$I$27) -> 9.7 | L6: =SUMIF('Resource Planning'!$D$3:$D$27,E6,'Resource Planning'!$J$3:$J$27) -> 10.32 | M6: =SUMIF('Resource Planning'!$D$3:$D$27,E6,'Resource Planning'!$K$3:$K$27) -> 10.25 | P6: Size Available Vs Need | T6: Vilasini | W6: 44579
Q10: Assumption
P11: PROOF | Q11: 8 Story points assumed to be delivered by a team member in given sprint
C12: =SUM(C5:C9) -> 0 | D12: =SUM(D5:D9) -> 837.52 | E12: Totals | H12: =SUM(H5:H9) -> 19.3 | I12: =SUM(I5:I9) -> 21.3 | J12: =SUM(J5:J9) -> 21.19 | K12: =SUM(K5:K9) -> 21.2 | L12: =SUM(L5:L9) -> 21.7 | M12: =SUM(M5:M9) -> 21.63 | P12: GRID/DOS | Q12: 8 Story points assumed to be delivered by a team member in given sprint
C15: Rem Ask | D15: Rem Eff | E15: Team | F15: Product | G15: Application Name(s) | H15: Outlook | J15: Deviation | L15: S1: need | M15: S1: avail | N15: S2: need | O15: S2: avail | P15: S3: need | Q15: S3: avail | R15: S4: need | S15: S4: avail | T15: S5: need | U15: S5:avail | V15: S6: need | W15: S6:avail | X15: Check need | Y15: Check avail
C16: =SUMIFS('PI Commitments'!$K3:$K63,'PI Commitments'!$N3:$N63,"Commit",'PI Commitments'!$P3:$P63,"N") -> 463 | D16: =SUM(M16,O16,Q16,S16,U16) -> 445.76 | E16: The Ninjas | G16: IRIDER, PROOF, IDC | H16: =IF(AND(I16>0, (I16/D16) <=0.1),"Good",IF(AND(I16>0,(I16/D16)>0.1), "Under Utilized", IF((I16/D16)>= -0.05, "Good","Over Utilized"))) -> Good | I16: =D16-C16 -> -17.24 | J16: =I16/D16 -> -0.03867552 | K16: The Ninjas | L16: =SUMIFS('PI Commitments'!$T$3:$T$63, 'PI Commitments'!$P$3:$P$63,"=N",'PI Commitments'!$N$3:$N$63,"=Commit") -> 82.583333 | M16: =IF($H$25>0, (H5*(($H$25/10)*8)),0) -> 82.4 | N16: =SUMIFS('PI Commitments'!$U$3:$U$63, 'PI Commitments'!$P$3:$P$63,"=N",'PI Commitments'!$N$3:$N$63,"=Commit") -> 86.583333 | O16: =IF($H$26>0, (I5*(($H$26/10)*8)),0) -> 91.2 | P16: =SUMIFS('PI Commitments'!$V$3:$V$63, 'PI Commitments'!$P$3:$P$63,"=N",'PI Commitments'!$N$3:$N$63,"=Commit") -> 95.083333 | Q16: =IF($H$27>0, (J5*(($H$27/10)*8)),0) -> 89.12 | R16: =SUMIFS('PI Commitments'!$W$3:$W$63, 'PI Commitments'!$P$3:$P$63,"=N",'PI Commitments'!$N$3:$N$63,"=Commit") -> 76.083333 | S16: =IF($H$28>0, (K5*(($H$28/10)*8)),0) -> 92 | T16: =SUMIFS('PI Commitments'!$X$3:$X$63, 'PI Commitments'!$P$3:$P$63,"=N",'PI Commitments'!$N$3:$N$63,"=Commit") -> 74.833333 | U16: =IF($H$29>0, (L5*(($H$29/10)*8)),0) -> 91.04 | V16: =SUMIFS('PI Commitments'!$Y$3:$Y$63, 'PI Commitments'!$P$3:$P$63,"=N",'PI Commitments'!$N$3:$N$63,"=Commit") -> 42.833333 | W16: =IF($H$30>0, (M5*(($H$30/10)*8)),0) -> 91.04 | X16: =IF(SUM(T16,R16,P16,N16,L16)-C16>0,1,IF((ABS(SUM(T16,R16,P16,N16,L16)-C16)/C16)>0.02,0,1)) -> 0 | Y16: =IF(SUM(U16,S16,Q16,O16,M16)-D16>0,1,IF((ABS(SUM(U16,S16,Q16,O16,M16)-D16)/D16)>0.02,0,1)) -> 1
C17: =SUMIFS('PI Commitments'!$K3:$K63,'PI Commitments'!$N3:$N63,"Commit",'PI Commitments'!$P3:$P63,"S") -> 421 | D17: =SUM(M17,O17,Q17,S17,U17) -> 391.76 | E17: Samurai | G17: GRID, DOS | H17: =IF(AND(I17>0, (I17/D17) <=0.1),"Good",IF(AND(I17>0,(I17/D17)>0.1), "Under Utilized", IF((I17/D17)>= -0.05, "Good","Over Utilized"))) -> Over Utilized | I17: =D17-C17 -> -29.24 | J17: =I17/D17 -> -0.074637533 | K17: Samurai | L17: =SUMIFS('PI Commitments'!$T$3:$T$63, 'PI Commitments'!$P$3:$P$63,"=S",'PI Commitments'!$N$3:$N$63,"=Commit") -> 56.416667 | M17: =IF($H$25>0, (H6*(($H$25/10)*8)),0) -> 72 | N17: =SUMIFS('PI Commitments'!$U$3:$U$63, 'PI Commitments'!$P$3:$P$63,"=S",'PI Commitments'!$N$3:$N$63,"=Commit") -> 76.166667 | O17: =IF($H$26>0, (I6*(($H$26/10)*8)),0) -> 79.2 | P17: =SUMIFS('PI Commitments'!$V$3:$V$63, 'PI Commitments'!$P$3:$P$63,"=S",'PI Commitments'!$N$3:$N$63,"=Commit") -> 62.166667 | Q17: =IF($H$27>0, (J6*(($H$27/10)*8)),0) -> 80.4 | R17: =SUMIFS('PI Commitments'!$W$3:$W$63, 'PI Commitments'!$P$3:$P$63,"=S",'PI Commitments'!$N$3:$N$63,"=Commit") -> 64.5 | S17: =IF($H$28>0, (K6*(($H$28/10)*8)),0) -> 77.6 | T17: =SUMIFS('PI Commitments'!$X$3:$X$63, 'PI Commitments'!$P$3:$P$63,"=S",'PI Commitments'!$N$3:$N$63,"=Commit") -> 92.75 | U17: =IF($H$29>0, (L6*(($H$29/10)*8)),0) -> 82.56 | V17: =SUMIFS('PI Commitments'!$Y$3:$Y$63, 'PI Commitments'!$P$3:$P$63,"=S",'PI Commitments'!$N$3:$N$63,"=Commit") -> 69 | W17: =IF($H$30>0, (M6*(($H$30/10)*8)),0) -> 82 | X17: =IF(SUM(T17,R17,P17,N17,L17)-C17>0,1,IF((ABS(SUM(T17,R17,P17,N17,L17)-C17)/C17)>0.02,0,1)) -> 0 | Y17: =IF(SUM(U17,S17,Q17,O17,M17)-D17>0,1,IF((ABS(SUM(U17,S17,Q17,O17,M17)-D17)/D17)>0.02,0,1)) -> 1
C23: =SUM(C16:C20) -> 884 | D23: =SUM(D16:D20) -> 837.52 | E23: Totals | H23: =IF(AND(I23>0, (I23/D23) <=0.1),"Good",IF(AND(I23>0,(I23/D23)>0.1), "Under Utilized", IF((I23/D23)>= -0.1, "Good","Over Utilized"))) -> Good | I23: =D23-C23 -> -46.48 | J23: =I23/D23 -> -0.055497182 | L23: =SUM(L16:L20) -> 139 | M23: =SUM(M16:M20) -> 154.4 | N23: =SUM(N16:N20) -> 162.75 | O23: =SUM(O16:O20) -> 170.4 | P23: =SUM(P16:P20) -> 157.25 | Q23: =SUM(Q16:Q20) -> 169.52 | R23: =SUM(R16:R20) -> 140.58333 | S23: =SUM(S16:S20) -> 169.6 | ... W23: =SUM(W16:W20) -> 173.04
C24: Sprints Remaining | E24: Sprint | F24: Start | G24: End | H24: Days remaining
B25: =IF(AND($G$1 >=F25,$G$1<=G25), 1,IF($G$1 < $F$25, 1, 0)) -> 1 | C25: =COUNT($E$25:$E$29) *$C$29 -> 5 | E25: 1 | F25: =E1 -> 44671 | G25: =DATE(YEAR(F25), MONTH(F25), DAY(F25) +13) -> 44684 | H25: 10
B26: =IF(AND($G$1 >=F26,$G$1<=G26), 1,0) -> 0 | C26: Total Days Remaining | E26: 2 | F26: =DATE(YEAR(G25),MONTH(G25), DAY(G25) +1) -> 44685 | G26: =DATE(YEAR(F26), MONTH(F26), DAY(F26) +13) -> 44698 | H26: =IF(AND($G$1 >=F26,$G$1<=G26), IF((DATEDIF($G$1,G26,"D")+1)>=11,(DATEDIF($G$1,G26,"D")+1)-4, IF((DATEDIF($G$1,G26,"D")+1)>=3, (DATEDIF($G$1,G26,"D")+1)-2,(DATEDIF($G$1,G26,"D")+1))),IF($G$1>G26,0,10)) -> 10
B27: =IF(AND($G$1 >=F27,$G$1<=G27), 1,0) -> 0 | C27: =SUM(H25:H29) -> 50 | E27: 3 | F27: =DATE(YEAR(G26),MONTH(G26), DAY(G26) +1) -> 44699 | G27: =DATE(YEAR(F27), MONTH(F27), DAY(F27) +13) -> 44712 | H27: =IF(AND($G$1 >=F27,$G$1<=G27), IF((DATEDIF($G$1,G27,"D")+1)>=11,(DATEDIF($G$1,G27,"D")+1)-4, IF((DATEDIF($G$1,G27,"D")+1)>=3, (DATEDIF($G$1,G27,"D")+1)-2,(DATEDIF($G$1,G27,"D")+1))),IF($G$1>G27,0,10)) -> 10
B28: =IF(AND($G$1 >=F28,$G$1<=G28), 1,0) -> 0 | C28: Sprint % Remaining | E28: 4 | F28: =DATE(YEAR(G27),MONTH(G27), DAY(G27) +1) -> 44713 | G28: =DATE(YEAR(F28), MONTH(F28), DAY(F28) +13) -> 44726 | H28: =IF(AND($G$1 >=F28,$G$1<=G28), IF((DATEDIF($G$1,G28,"D")+1)>=11,(DATEDIF($G$1,G28,"D")+1)-4, IF((DATEDIF($G$1,G28,"D")+1)>=3, (DATEDIF($G$1,G28,"D")+1)-2,(DATEDIF($G$1,G28,"D")+1))),IF($G$1>G28,0,10)) -> 10
B29: =IF(AND($G$1 >=F29,$G$1<=G29), 1,0) -> 0 | C29: =C27/(COUNT(E25:E29) *10) -> 1 | E29: 5 | F29: =DATE(YEAR(G28),MONTH(G28), DAY(G28) +1) -> 44727 | G29: =DATE(YEAR(F29), MONTH(F29), DAY(F29) +13) -> 44740 | H29: =IF(AND($G$1 >=F29,$G$1<=G29), IF((DATEDIF($G$1,G29,"D")+1)>=11,(DATEDIF($G$1,G29,"D")+1)-4, IF((DATEDIF($G$1,G29,"D")+1)>=3, (DATEDIF($G$1,G29,"D")+1)-2,(DATEDIF($G$1,G29,"D")+1))),IF($G$1>G29,0,10)) -> 10
E30: 6 | F30: =DATE(YEAR(G29),MONTH(G29), DAY(G29) +1) -> 44741 | G30: =DATE(YEAR(F30), MONTH(F30), DAY(F30) +13) -> 44754 | H30: =IF(AND($G$1 >=F30,$G$1<=G30), IF((DATEDIF($G$1,G30,"D")+1)>=11,(DATEDIF($G$1,G30,"D")+1)-4, IF((DATEDIF($G$1,G30,"D")+1)>=3, (DATEDIF($G$1,G30,"D")+1)-2,(DATEDIF($G$1,G30,"D")+1))),IF($G$1>G30,0,10)) -> 10

Sheet PIPlanningSessionBestPractices

Sheet Objectives(opt)
B1: Assumptions and Dependencies
B3: Sr. No. | C3: Assumption/Questions/Dependencies | D3: Action item
B4: 1 | C4: MIM Digital Portal priority for Resi API Mapping
B5: 2 | C5: Eng dependency for DOS containers for Resi | D5: Darryl to confirm
B6: 3 | C6: MIM Digital Portal priority/Source dependency for Multicurrency for Commercial | D6: Brian to confirm dates
B7: 4 | C7: GRID Adjustments - Eng Team dependency for PROD/DR and new Azure resources | D7: Darryl to confirm
B8: 5 | C8: GRID Data Validator (GDV) - OSS/GARB dependency | D8: Architecture team (action item?)
B9: 6 | C9: GRID Data Validator (GDV) - DevOps Dependency for making CICD readyf or each environment | D9: Deva to confirm
B19: Risks
B21: Sr. No. | C21: Risks | D21: Action item
B22: 1 | C22: Databricks pool implementation is very detailed and intrusive, need to ensure DOS is onboarded successfully without any impact, it will help with resource contraint on platform and improve performance
B23: 2 | C23: Eng. And DevOps team dependency for GRID Data Validator new capability pipelines
B24: 3
D33: Note - we need these features separated by app in other contexts, please separate your app in the Feature Numbers
B34: Sr. No. | C34: PI Objective - Jan 2022 | D34: Feature Numbers | E34: BV Owner | F34: BV Score | G34: What is being delivered, whats the value, for who, by when
B35: 1 | C35: Deliver Commercial and AG asset class data domain related changes for MIS Refactoring program for Feb and Mar 2022 that will enable MIS application retirement for MIM business domain | D35: GRID: DOS: 460402, 476563 PROOF: | E35: Jatin | F35: 7
B36: 2 | C36: Onboard Residential asset class to GRID and DOS for Digital Data Platform and Portal through PROOF | D36: GRID: DOS: 458720, 463287, 463288, 463289, 476561 PROOF: | E36: Brian | F36: 9
B37: 3 | C37: Onboard Commercial, AG, Private Placement and Private ABS asset class data domain related changes to DOS per business requirement for month of Feb, Mar and Apr 2022, example Rewiring of contacts to pull from Salesforce | D37: GRID: DOS: PABS: 456476 (Feb), 476531 (Mar), 476538 (Apr) PrPl: 456465 (Feb), 476530 (Mar), 476537 (Apr) Coml: 456443 (Feb), 476529 (Mar), 476533 (Apr) Agri: 456454 (Feb), 476528 (Mar), 476532 (Apr) Misc: 476543 (App Readiness Updates) PROOF: | E37: Brian | F37: 9
B38: 4 | C38: Deliver enhancements to GRID Adjustments portal based on business user feedback | D38: GRID: DOS: N/A PROOF: | E38: GP | F38: 7
B39: 5 | C39: Enable automation of queries onboarding to IDC platform per consumer need through a rich UI that allows user to build query, see output and query data stored in GRID for given dataset | D39: GRID: DOS: 473580 PROOF: | E39: Jatin | F39: 8
B40: 6 | C40: Deliver fit for purpose data based on consumer needs through IDC with new queries onboarding or modification to existing queries including optimization of queries | D40: GRID: DOS: N/A PROOF: | E40: Jatin | F40: 8
B41: 7 | C41: Implement central data validation capability on top of Investments Data Lake (GRID) with detailed dashboards providing relevant information to data stewards, support and product teams and in turn help improve data quality on digital platforms | D41: GRID: DOS: N/A PROOF: | E41: Jatin | F41: 8
B42: 8 | C42: PROOF, GRID, DALFI, DOS, , IDC, IRIDER Tech Debt efforts and Optmization: Identify processes and code base needing optimization and fine tune to enhance overall data platform processes performance, SLA, data quality, delivery optimization, SPN+Cert+KV expiry management, DataBricks cluster pools and repo | D42: GRID: DOS: 478268, 476539, 476564, 460322 PROOF: | E42: Jatin | F42: 7
B43: 9 | C43: Continue hydrating lake with additional data domains that meets MIM client reporting, MMR, RE Equity, and SecLending business needs | D43: GRID: DOS: 476583 (Pub. Corp. Analysis), 476566 (RE Eq. Analysis) PROOF: | E43: Jatin | F43: 6
B44: 10 | C44: Deliver PROOF automated testing capability Phase 2 that will reduce manual testing efforts and improve code quality delivered to PROD env; Partially deliver automated testing efforts for GRID and DOS; | D44: GRID: DOS: N/A (efforts done on PROOF side; DOS team to assist with testing) PROOF: | E44: Jatin | F44: 6
B45: 11 | C45: IRIDER Feb, Mar, Apr releases to support Tenant application changes and BAU | D45: GRID: DOS: N/A PROOF: | E45: Jatin | F45: 5

Sheet Summary(not being used)
A1: Count of ID | B1: Column Labels
A2: Category | B2: H | C2: IM | D2: (blank) | E2: Grand Total
A3: BAU | B3: 2 | C3: 3 | E3: 5
A4: Innovation | B4: 1 | E4: 1
A5: Data360 | B5: 6 | E5: 6
A6: Power BI | B6: 7 | E6: 7
A7: (blank)
A8: Decom | B8: 18 | E8: 18
A9: Grand Total | B9: 34 | C9: 3 | E9: 37
A140: Category-Team
A141: Row Labels | B141: H | C141: IM | D141: (blank) | E141: Grand Total
A142: BAU | B142: 2 | C142: 3 | E142: 5
A143: Innovation | B143: 1 | E143: 1
A144: (blank)
A145: Power BI | B145: 7 | E145: 7
A146: Data360 | B146: 6 | E146: 6
A147: Decom | B147: 18 | E147: 18
A148: Grand Total | B148: 34 | C148: 3 | E148: 37

Sheet PI Progress(not being used)

Sheet Raw Data(not being used)
A1: Row Labels | B1: Count of ID | C1: Sum of % Complete | D1: Sum of Planned Business Value | E1: Sum of Actual Business Value
A2: BAU | B2: 5 | C2: 3.5 | D2: 28 | E2: 15
A3: Innovation | B3: 1 | C3: 0 | D3: 7 | E3: 0
A4: Power BI | B4: 7 | C4: 1.25 | D4: 49 | E4: 0
A5: (blank)
A6: Data360 | B6: 6 | C6: 0.7 | D6: 43 | E6: 0
A7: Decom | B7: 18 | C7: 0.93333333 | D7: 127 | E7: 0
A8: Grand Total | B8: 37 | C8: 6.3833333 | D8: 254 | E8: 15
A31: Category | B31: Number of Features | C31: Sum of % Complete | D31: Percent complete | H31: Category | I31: % Planned | J31: % Completed
A32: BAU | B32: 18 | C32: 5.25 | D32: =C32/B32*100 -> 29.166667 | E32: 100 | H32: BAU | I32: 100 | J32: 29.166667
A33: BHF | B33: 2 | C33: 0 | D33: =C33/B33*100 -> 0 | E33: 100 | H33: BHF | I33: 100 | J33: 0
A34: CECL | B34: 3 | C34: 0.33333333 | D34: =C34/B34*100 -> 11.111111 | E34: 100 | H34: CECL | I34: 100 | J34: 11.111111
A35: Innovation | B35: 8 | C35: 0.66666667 | D35: =C35/B35*100 -> 8.3333333 | E35: 100 | H35: Innovation | I35: 100 | J35: 8.3333333
A36: InvestmentTypeClassification | B36: 2 | C36: 0 | D36: =C36/B36*100 -> 0 | E36: 100 | H36: InvestmentTypeClassification | I36: 100 | J36: 0
A37: MIM-AIC | B37: 3 | C37: 1 | D37: =C37/B37*100 -> 33.333333 | E37: 100 | H37: MIM-AIC | I37: 100 | J37: 33.333333
A38: Power BI | B38: 7 | C38: 1.25 | D38: =C38/B38*100 -> 17.857143 | E38: 100 | H38: Power BI | I38: 100 | J38: 17.857143
A39: Support | B39: 10 | C39: 2.5833333 | D39: =C39/B39*100 -> 25.833333 | E39: 100 | H39: Support | I39: 100 | J39: 25.833333
A40: Data360 | B40: 6 | C40: 0.7 | D40: =C40/B40*100 -> 11.666667 | E40: 100 | H40: Data360 | I40: 100 | J40: 11.666667
A41: Decom/Digital | B41: 13 | C41: 1.6166667 | D41: =C41/B41*100 -> 12.435897 | E41: 100 | H41: Decom/Digital | I41: 100 | J41: 12.435897
A42: Argus | B42: 1 | C42: 0 | D42: =C42/B42*100 -> 0 | E42: 100 | H42: Argus | I42: 100 | J42: 0
A43: Tech Debt | B43: 1 | C43: 0.5 | D43: =C43/B43*100 -> 50 | E43: 100 | H43: Tech Debt | I43: 100 | J43: 50
... A50: SOFR/SONIA | B50: 4 | C50: 0.5 | D50: =C50/B50*100 -> 12.5 | E50: 100 | H50: SOFR/SONIA | I50: 100 | J50: 12.5
A56: Category | B56: Sum of Planned Business Value | C56: Sum of Delivered Business Value
A57: BAU | B57: 96 | C57: 29
A58: BHF | B58: 15 | C58: 0
A59: CECL | B59: 24 | C59: 0
A60: Innovation | B60: 46 | C60: 0
A61: InvestmentTypeClassification | B61: 16 | C61: 0
A62: MIM-AIC | B62: 21 | C62: 10
A63: Power BI | B63: 49 | C63: 0
A64: Support | B64: 64 | C64: 5
A65: Data360 | B65: 43 | C65: 0
A66: Decom/Digital | B66: 88 | C66: 0
A67: Argus | B67: 3 | C67: 0
A68: Tech Debt | B68: 3 | C68: 0
... A75: SOFR/SONIA | B75: 28 | C75: 0

Sheet Sprint Goals
A1: Team | B1: Sprint | C1: Sprint Goal (Determine what main focus/objective for your Sprint and should be subset into your PI Objectives) | D1: Confidence Vote (1 lowest -5 highest)
A2: The Ninjas | B2: 2 | C2: IDC Phase 2 | D2: 3.4
A3: The Ninjas | B3: 3 | C3: Adjustment UI | D3: 5
